Workbook

Sheet BS_KO
C2: 대차대조표
C4: 제 37(당) 기 2026년 12월 31일 현재 | H4: OM | I4: 0.01 | J4: ='P&L_KO'!K4 -> 7.0976202e+09
C5: 제 36(전) 기 2025년 12월 31일 현재 | H5: PM | I5: 0.8 | J5: =J4*70% -> 4.9683342e+09
H6: CTT | I6: 0.03 | J6: =J4*3% -> 2.1292861e+08
C7: 주식회사 사노피-아벤티스코리아
C8: 과목 | E8: 2026.09 | G8: 2025.12 | N8: 회사 F/S 대사 (BS_DEC 2026)
E9: 수정전 | F9: 수정후 | G9: 금액 | H9: Var. | I9: Var. % | J9: 증감분석여부? | K9: 증감분석 | N9: 회사 SAP(E열) | O9: Diff (E-N) | P9: 회사 Statutory(K열) | Q9: Diff (F-P)
C10: 자 산
B11: I. Current assets. | C11: I. 유동자산 | E11: =+E12+E27 -> 465905895178 | F11: =+F12+F27 -> 453490085054 | G11: =+G12+G27 -> 399003823525 | H11: =+H12+H27 -> 54486261529 | I11: =IFERROR(H11/G11,IF(H11>0,100%,IF(H11=0,0,-100%))) -> 0.13655574 | L11: =E11-F11 -> 12415810124 | N11: =+N12+N27 -> 465905895178 | O11: =E11-N11 -> 0 | P11: =+P12+P27 -> 453490085054 | Q11: =F11-P11 -> 0
B12: (1) Current assets. | C12: (1) 당좌자산 | E12: =SUM(E13:E24) -> 270465932072 | F12: =SUM(F13:F24) -> 258050121948 | G12: =SUM(G13:G24) -> 222568030855 | H12: =SUM(H13:H24) -> 35482091093 | I12: =IFERROR(H12/G12,IF(H12>0,100%,IF(H12=0,0,-100%))) -> 0.15942133 | L12: =E12-F12 -> 12415810124 | N12: =SUM(N13:N24) -> 270465932072 | O12: =E12-N12 -> 0 | P12: =SUM(P13:P24) -> 258050121948 | Q12: =F12-P12 -> 0
B13: 1. Cash and cash equivalents. | C13: 1. | D13: 현금및현금등가물 | E13: =SUMIF(FS_map!$H:$H,$D13,FS_map!$M:$M) -> 8328079411 | F13: =SUMIF(FS_map!$H:$H,$D13,FS_map!$P:$P) -> 8328079411 | G13: =SUMIF(WBS_2025YE!$D:$D,$D13,WBS_2025YE!$K:$K) -> 11105202344 | H13: =F13-G13 -> -2777122933 | I13: =IFERROR(H13/G13,IF(H13>0,100%,IF(H13=0,0,-100%))) -> -0.25007405 | J13: =IF(AND(ABS(H13)>$J$5,ABS(I13)>5%),"O","") | K13: 전기말 111억원 → 당기 9월말 83억원 (−28억원, HSBC 원화예금 단일계좌) 1. 당기 배당금 520억원 지급 (SAP 3월 기표, 회사 자료상 2분기 지급) 2. 그룹 현금 최적화 정책에 따라 관계사 채무를 연중 조기 결제 ※ 회사는 기말에 관계사 채무를 대량 결제하여 기말 예금잔액을 낮게 유지하는 경향이 있으므로, 기말 잔액 및 관계사 채무 결제 시점 확인 필요 | L13: =E13-F13 -> 0 | N13: =SUMIF('BS_DEC 2026'!$D:$D,$D13,'BS_DEC 2026'!$E:$E) -> 8328079411 | O13: =E13-N13 -> 0 | P13: =SUMIF('BS_DEC 2026'!$D:$D,$D13,'BS_DEC 2026'!$K:$K) -> 8328079411 | Q13: =F13-P13 -> 0
B14: 2. Accounts receivable. | C14: 2. | D14: 매출채권 | E14: =SUMIF(FS_map!$H:$H,$D14,FS_map!$M:$M) -> 227594760909 | F14: =SUMIF(FS_map!$H:$H,$D14,FS_map!$P:$P) -> 215178950785 | G14: =SUMIF(WBS_2025YE!$D:$D,$D14,WBS_2025YE!$K:$K) -> 166754777499 | H14: =F14-G14 -> 48424173286 | I14: =IFERROR(H14/G14,IF(H14>0,100%,IF(H14=0,0,-100%))) -> 0.29039152 | J14: =IF(AND(ABS(H14)>$J$5,ABS(I14)>5%),"O","") -> O | K14: 총 매출채권(SAP) 전기말 1,739억원 → 9월말 2,276억원(+537억원), 매출에누리 미지급분 직접차감(statutory #5) 124억원(전기말 72억원) 반영 후 2,152억원 1. 증가 요인: 매출 증가(9월 누적 매출 5,323억원, 전년 동기 대비 +333억원) 및 9월 매출 증가 - 주요 거래처: 비아다빈치 152억 → 197억원, 부림약품(대구) 95억 → 134억원, 지오영 106억 → 134억원, 기타 Pharma 1,194억 → 1,281억원 2. 백신 도매 매출채권은 192억 → 102억원으로 감소: 9월부터 독감백신 성수기 주문이 시작되어 4분기 증가 예상 3. 연체채권: 신광약품 69백만원 1건(12월 회수 예정, 회사 평가 low risk). 쥴릭파마는 25년 4월 계약 종료 후 유효기간 반품에 따른 credit note 정산 진행 중 4. 매출채권 회전일수(연환산 매출 기준) 111일로 전기말 94일 대비 증가 → 기간후 회수 확인 필요 (출처: 회사 BS 분석적검토 – CI2C AR 분석) | L14: =E14-F14 -> 12415810124 | N14: =SUMIF('BS_DEC 2026'!$D:$D,$D14,'BS_DEC 2026'!$E:$E) -> 227594760909 | O14: =E14-N14 -> 0 | P14: =SUMIF('BS_DEC 2026'!$D:$D,$D14,'BS_DEC 2026'!$K:$K) -> 215178950785 | Q14: =F14-P14 -> 0
B15: 3. Provision for bad debts. | C15: 3. | D15: 대손충당금 | E15: =SUMIF(FS_map!$H:$H,$D15,FS_map!$M:$M) -> -118149382 | F15: =SUMIF(FS_map!$H:$H,$D15,FS_map!$P:$P) -> -118149382 | G15: =SUMIF(WBS_2025YE!$D:$D,$D15,WBS_2025YE!$K:$K) -> -122273991 | H15: =F15-G15 -> 4124609 | I15: =IFERROR(H15/G15,IF(H15>0,100%,IF(H15=0,0,-100%))) -> -0.033732513 | J15: =IF(AND(ABS(H15)>$J$5,ABS(I15)>5%),"O","") | K15: 클리닉 매출채권에 대한 대손충당금 118백만원(전기말 122백만원). 당기 4백만원 환입(대손상각비 음수 표시). 금액 중요하지 않음 | L15: =E15-F15 -> 0 | N15: =SUMIF('BS_DEC 2026'!$D:$D,$D15,'BS_DEC 2026'!$E:$E) -> -118149382 | O15: =E15-N15 -> 0 | P15: =SUMIF('BS_DEC 2026'!$D:$D,$D15,'BS_DEC 2026'!$K:$K) -> -118149382 | Q15: =F15-P15 -> 0
B16: 4. Unpaid money. | C16: 4. | D16: 미수금 | E16: =SUMIF(FS_map!$H:$H,$D16,FS_map!$M:$M) -> 12002662102 | F16: =SUMIF(FS_map!$H:$H,$D16,FS_map!$P:$P) -> 12002662102 | G16: =SUMIF(WBS_2025YE!$D:$D,$D16,WBS_2025YE!$K:$K) -> 19254727447 | H16: =F16-G16 -> -7252065345 | I16: =IFERROR(H16/G16,IF(H16>0,100%,IF(H16=0,0,-100%))) -> -0.37663817 | J16: =IF(AND(ABS(H16)>$J$5,ABS(I16)>5%),"O","") -> O | K16: 전기말 193억원 → 9월말 120억원 (−73억원) 1. 관계사 미수금(26050000) 167억 → 116억원(−51억원) - Sanofi SA 165억 → 114억원: 3분기 R&D(CRU) 비용 recharge 미수분 - Sanofi Winthrop Industrie 1.2억원(9월 rebilling), Sanofi Pasteur Inc 1.0억원(3분기 R&D) 2. 전기말 statutory 조정으로 인식한 CRU true-up 미수금 22.6억원(86260033)은 당기 2월 확정·기표되어 잔액 0 3. 기타: 임직원 우리사주(Action Share) 공제분 4.2억원(전기말 3.1억원) | L16: =E16-F16 -> 0 | N16: =SUMIF('BS_DEC 2026'!$D:$D,$D16,'BS_DEC 2026'!$E:$E) -> 12002662102 | O16: =E16-N16 -> 0 | P16: =SUMIF('BS_DEC 2026'!$D:$D,$D16,'BS_DEC 2026'!$K:$K) -> 12002662102 | Q16: =F16-P16 -> 0
B17: 5. Value-added tax not collected. | C17: 5. | D17: 부가가치세미수금 | E17: =SUMIF(FS_map!$H:$H,$D17,FS_map!$M:$M) -> 0 | F17: =SUMIF(FS_map!$H:$H,$D17,FS_map!$P:$P) -> 0 | G17: =SUMIF(WBS_2025YE!$D:$D,$D17,WBS_2025YE!$K:$K) -> 0 | H17: =F17-G17 -> 0 | I17: =IFERROR(H17/G17,IF(H17>0,100%,IF(H17=0,0,-100%))) -> 0 | J17: =IF(AND(ABS(H17)>$J$5,ABS(I17)>5%),"O","") | L17: =E17-F17 -> 0 | N17: =SUMIF('BS_DEC 2026'!$D:$D,$D17,'BS_DEC 2026'!$E:$E) -> 0 | O17: =E17-N17 -> 0 | P17: =SUMIF('BS_DEC 2026'!$D:$D,$D17,'BS_DEC 2026'!$K:$K) -> 0 | Q17: =F17-P17 -> 0
B18: 6. Minus profit. | C18: 6. | D18: 미수수익 | E18: =SUMIF(FS_map!$H:$H,$D18,FS_map!$M:$M) -> 981690770 | F18: =SUMIF(FS_map!$H:$H,$D18,FS_map!$P:$P) -> 981690770 | G18: =SUMIF(WBS_2025YE!$D:$D,$D18,WBS_2025YE!$K:$K) -> 979522461 | H18: =F18-G18 -> 2168309 | I18: =IFERROR(H18/G18,IF(H18>0,100%,IF(H18=0,0,-100%))) -> 0.0022136389 | J18: =IF(AND(ABS(H18)>$J$5,ABS(I18)>5%),"O","") | K18: 로열티 수익 미수분: Aprovasc(한독) 955백만원, 디트로반(동화약품) 26백만원 – 9월 누적 accrual. 전기말 로열티 미수 971백만원은 당기 수령 완료 | L18: =E18-F18 -> 0 | N18: =SUMIF('BS_DEC 2026'!$D:$D,$D18,'BS_DEC 2026'!$E:$E) -> 981690770 | O18: =E18-N18 -> 0 | P18: =SUMIF('BS_DEC 2026'!$D:$D,$D18,'BS_DEC 2026'!$K:$K) -> 981690770 | Q18: =F18-P18 -> 0
B19: 7. Advance payment. | C19: 7. | D19: 선급금 | E19: =SUMIF(FS_map!$H:$H,$D19,FS_map!$M:$M) -> 1159433436 | F19: =SUMIF(FS_map!$H:$H,$D19,FS_map!$P:$P) -> 1159433436 | G19: =SUMIF(WBS_2025YE!$D:$D,$D19,WBS_2025YE!$K:$K) -> 93970356 | H19: =F19-G19 -> 1065463080 | I19: =IFERROR(H19/G19,IF(H19>0,100%,IF(H19=0,0,-100%))) -> 11.338289 | J19: =IF(AND(ABS(H19)>$J$5,ABS(I19)>5%),"O","") | K19: 전기말 94백만원 → 9월말 1,159백만원 1. 임직원 선급(Payroll deductions) 810백만원: 급여시스템 오류로 인한 일회성 원천세 조정 809.6백만원 – 10월 원천세 납부 시 정산 예정(예수금 증가와 대응) 2. 공급업체 선급금 415백만원: 협회 후원금 334백만원 신규, CSU 연구비·IRB 심사비 66백만원. 30일 초과 8건(90일 초과 3건) → 비용처리 시기 및 회수가능성 확인 필요 | L19: =E19-F19 -> 0 | N19: =SUMIF('BS_DEC 2026'!$D:$D,$D19,'BS_DEC 2026'!$E:$E) -> 1159433436 | O19: =E19-N19 -> 0 | P19: =SUMIF('BS_DEC 2026'!$D:$D,$D19,'BS_DEC 2026'!$K:$K) -> 1159433436 | Q19: =F19-P19 -> 0
B20: 8. Provisional payment. | C20: 8. | D20: 가지급금 | E20: =SUMIF(FS_map!$H:$H,$D20,FS_map!$M:$M) -> 0 | F20: =SUMIF(FS_map!$H:$H,$D20,FS_map!$P:$P) -> 0 | G20: =SUMIF(WBS_2025YE!$D:$D,$D20,WBS_2025YE!$K:$K) -> 0 | H20: =F20-G20 -> 0 | I20: =IFERROR(H20/G20,IF(H20>0,100%,IF(H20=0,0,-100%))) -> 0 | J20: =IF(AND(ABS(H20)>$J$5,ABS(I20)>5%),"O","") | L20: =E20-F20 -> 0 | N20: =SUMIF('BS_DEC 2026'!$D:$D,$D20,'BS_DEC 2026'!$E:$E) -> 0 | O20: =E20-N20 -> 0 | P20: =SUMIF('BS_DEC 2026'!$D:$D,$D20,'BS_DEC 2026'!$K:$K) -> 0 | Q20: =F20-P20 -> 0
B21: 9. Loan. | C21: 9. | D21: 대여금 | E21: =SUMIF(FS_map!$H:$H,$D21,FS_map!$M:$M) -> 0 | F21: =SUMIF(FS_map!$H:$H,$D21,FS_map!$P:$P) -> 0 | G21: =SUMIF(WBS_2025YE!$D:$D,$D21,WBS_2025YE!$K:$K) -> 0 | H21: =F21-G21 -> 0 | I21: =IFERROR(H21/G21,IF(H21>0,100%,IF(H21=0,0,-100%))) -> 0 | J21: =IF(AND(ABS(H21)>$J$5,ABS(I21)>5%),"O","") | L21: =E21-F21 -> 0 | N21: =SUMIF('BS_DEC 2026'!$D:$D,$D21,'BS_DEC 2026'!$E:$E) -> 0 | O21: =E21-N21 -> 0 | P21: =SUMIF('BS_DEC 2026'!$D:$D,$D21,'BS_DEC 2026'!$K:$K) -> 0 | Q21: =F21-P21 -> 0
B22: 10. Advance payment. | C22: 10. | D22: 선급비용 | E22: =SUMIF(FS_map!$H:$H,$D22,FS_map!$M:$M) -> 1049728634 | F22: =SUMIF(FS_map!$H:$H,$D22,FS_map!$P:$P) -> 1049728634 | G22: =SUMIF(WBS_2025YE!$D:$D,$D22,WBS_2025YE!$K:$K) -> 307501499 | H22: =F22-G22 -> 742227135 | I22: =IFERROR(H22/G22,IF(H22>0,100%,IF(H22=0,0,-100%))) -> 2.413735 | J22: =IF(AND(ABS(H22)>$J$5,ABS(I22)>5%),"O","") | K22: 전기말 308백만원 → 9월말 1,050백만원 1. OneCASA 임상 선급비용 657백만원 신규 (R&D non-PO) 2. 연회비(26.1~12월) 358백만원, 단체보험(26.7~27.6) 236백만원 등을 신규로 선급하고 월할 상각 - 신규 선급 +742백만원, 상각 −657백만원 (2026 단체보험 −170, 연회비 −268, 사이버보험 −55, 운송보험 −53백만원 등) | L22: =E22-F22 -> 0 | N22: =SUMIF('BS_DEC 2026'!$D:$D,$D22,'BS_DEC 2026'!$E:$E) -> 1049728634 | O22: =E22-N22 -> 0 | P22: =SUMIF('BS_DEC 2026'!$D:$D,$D22,'BS_DEC 2026'!$K:$K) -> 1049728634 | Q22: =F22-P22 -> 0
B23: 11. Liquidity Annual Tax Assets | C23: 11. | D23: 유동성이연법인세자산 | E23: =SUMIF(FS_map!$H:$H,$D23,FS_map!$M:$M) -> 19467726192 | F23: =SUMIF(FS_map!$H:$H,$D23,FS_map!$P:$P) -> 19467726192 | G23: =SUMIF(WBS_2025YE!$D:$D,$D23,WBS_2025YE!$K:$K) -> 24194603240 | H23: =F23-G23 -> -4726877048 | I23: =IFERROR(H23/G23,IF(H23>0,100%,IF(H23=0,0,-100%))) -> -0.19536907 | J23: =IF(AND(ABS(H23)>$J$5,ABS(I23)>5%),"O","") | K23: 전기말 242억원 → 9월말 195억원 (−47억원) 1. 3분기 법인세 추정에 따른 이연법인세 감소 −5,791백만원 2. 법인세율 변경(23.1% → 24.2%)에 따른 기초 이연법인세자산 재측정 +1,163백만원 (244억 → 256억원) 3. 로컬 조정(86291000) −317백만원 ※ 중간기간 이연법인세는 회사 추정치이므로 기말 세무조정 후 재검토 필요 | L23: =E23-F23 -> 0 | N23: =SUMIF('BS_DEC 2026'!$D:$D,$D23,'BS_DEC 2026'!$E:$E) -> 19467726192 | O23: =E23-N23 -> 0 | P23: =SUMIF('BS_DEC 2026'!$D:$D,$D23,'BS_DEC 2026'!$K:$K) -> 19467726192 | Q23: =F23-P23 -> 0
B24: 12. National Pension Conversion Assets | C24: 12. | D24: 국민연금전환금자산 | E24: =SUMIF(FS_map!$H:$H,$D24,FS_map!$M:$M) -> 0 | F24: =SUMIF(FS_map!$H:$H,$D24,FS_map!$P:$P) -> 0 | G24: =SUMIF(WBS_2025YE!$D:$D,$D24,WBS_2025YE!$K:$K) -> 0 | H24: =F24-G24 -> 0 | I24: =IFERROR(H24/G24,IF(H24>0,100%,IF(H24=0,0,-100%))) -> 0 | J24: =IF(AND(ABS(H24)>$J$5,ABS(I24)>5%),"O","") | L24: =E24-F24 -> 0 | N24: =SUMIF('BS_DEC 2026'!$D:$D,$D24,'BS_DEC 2026'!$E:$E) -> 0 | O24: =E24-N24 -> 0 | P24: =SUMIF('BS_DEC 2026'!$D:$D,$D24,'BS_DEC 2026'!$K:$K) -> 0 | Q24: =F24-P24 -> 0
C25: 13 | D25: 유동성보증금 | E25: =SUMIF(FS_map!$H:$H,$D25,FS_map!$M:$M) -> 0 | F25: =SUMIF(FS_map!$H:$H,$D25,FS_map!$P:$P) -> 0 | G25: =SUMIF(WBS_2025YE!$D:$D,$D25,WBS_2025YE!$K:$K) -> 0 | H25: =F25-G25 -> 0 | I25: =IFERROR(H25/G25,IF(H25>0,100%,IF(H25=0,0,-100%))) -> 0 | J25: =IF(AND(ABS(H25)>$J$5,ABS(I25)>5%),"O","") | L25: =E25-F25 -> 0 | N25: =SUMIF('BS_DEC 2026'!$D:$D,$D25,'BS_DEC 2026'!$E:$E) -> 0 | O25: =E25-N25 -> 0 | P25: =SUMIF('BS_DEC 2026'!$D:$D,$D25,'BS_DEC 2026'!$K:$K) -> 0 | Q25: =F25-P25 -> 0
I26: =IFERROR(H26/G26,IF(H26>0,100%,IF(H26=0,0,-100%))) -> 0 | J26: =IF(AND(ABS(H26)>$J$5,ABS(I26)>5%),"O","") | L26: =E26-F26 -> 0
B27: (2) Inventory assets. | C27: (2) 재고자산 | E27: =SUM(E28:E37) -> 195439963106 | F27: =SUM(F28:F37) -> 195439963106 | G27: =SUM(G28:G37) -> 176435792670 | H27: =SUM(H28:H37) -> 19004170436 | I27: =IFERROR(H27/G27,IF(H27>0,100%,IF(H27=0,0,-100%))) -> 0.10771154 | J27: =IF(AND(ABS(H27)>$J$5,ABS(I27)>5%),"O","") -> O | K27: 재고회전일수(연환산 매출원가 기준) 131일(전기말 128일). 세부 내역은 상품·평가충당금·미착품 코멘트 참조 | L27: =E27-F27 -> 0 | N27: =SUM(N28:N37) -> 195439963106 | O27: =E27-N27 -> 0 | P27: =SUM(P28:P37) -> 195439963106 | Q27: =F27-P27 -> 0
B28: 1. Prize. | C28: 1. | D28: 상품 | E28: =SUMIF(FS_map!$H:$H,$D28,FS_map!$M:$M) -> 180063595464 | F28: =SUMIF(FS_map!$H:$H,$D28,FS_map!$P:$P) -> 180063595464 | G28: =SUMIF(WBS_2025YE!$D:$D,$D28,WBS_2025YE!$K:$K) -> 160568039290 | H28: =F28-G28 -> 19495556174 | I28: =IFERROR(H28/G28,IF(H28>0,100%,IF(H28=0,0,-100%))) -> 0.12141617 | J28: =IF(AND(ABS(H28)>$J$5,ABS(I28)>5%),"O","") -> O | K28: 전기말 1,606억원 → 9월말 1,801억원 (+195억원) 1. Pharma 1,166억 → 1,263억원(+97억원): Taxotere MA 이전 프로젝트에 대비한 재고 선확보(stock piling) +90억원 2. Vaccines 440억 → 538억원(+98억원): Pentaxim → Hexaxim 전환에 따른 Hexaxim 재고 +70억원, Beyfortus 시즌 재고 +80억원 3. 원가차이 자본화(20000030) −17억 → −9억원 (출처: 회사 BS 분석적검토 – 상품수불부 기준) | L28: =E28-F28 -> 0 | N28: =SUMIF('BS_DEC 2026'!$D:$D,$D28,'BS_DEC 2026'!$E:$E) -> 180063595464 | O28: =E28-N28 -> 0 | P28: =SUMIF('BS_DEC 2026'!$D:$D,$D28,'BS_DEC 2026'!$K:$K) -> 180063595464 | Q28: =F28-P28 -> 0
B29: Evaluation allowance - product | D29: 평가충당금-상품 | E29: =SUMIF(FS_map!$H:$H,$D29,FS_map!$M:$M) -> -2420155943 | F29: =SUMIF(FS_map!$H:$H,$D29,FS_map!$P:$P) -> -2420155943 | G29: =SUMIF(WBS_2025YE!$D:$D,$D29,WBS_2025YE!$K:$K) -> -4823897784 | H29: =F29-G29 -> 2403741841 | I29: =IFERROR(H29/G29,IF(H29>0,100%,IF(H29=0,0,-100%))) -> -0.49829867 | J29: =IF(AND(ABS(H29)>$J$5,ABS(I29)>5%),"O","") | K29: 전기말 48.2억원 → 9월말 24.2억원 (24억원 감소) 1. Pharma 1.6억 → 8.6억원: Dupixent(2억원) 등 유효기간 반품 및 단종 품목에 대한 충당금 증가 2. Vaccines 46.1억 → 15.1억원: Pentaxim 수요 증가로 기존 충당 재고 소진, Efluelda 유효기간 반품 감소 ※ 전기말 충당 재고의 당기 폐기·판매 내역 확인 필요 | L29: =E29-F29 -> 0 | N29: =SUMIF('BS_DEC 2026'!$D:$D,$D29,'BS_DEC 2026'!$E:$E) -> -2420155943 | O29: =E29-N29 -> 0 | P29: =SUMIF('BS_DEC 2026'!$D:$D,$D29,'BS_DEC 2026'!$K:$K) -> -2420155943 | Q29: =F29-P29 -> 0
B30: 2. Product. | C30: 2. | D30: 제품 | E30: =SUMIF(FS_map!$H:$H,$D30,FS_map!$M:$M) -> 0 | F30: =SUMIF(FS_map!$H:$H,$D30,FS_map!$P:$P) -> 0 | G30: =SUMIF(WBS_2025YE!$D:$D,$D30,WBS_2025YE!$K:$K) -> 0 | H30: =F30-G30 -> 0 | I30: =IFERROR(H30/G30,IF(H30>0,100%,IF(H30=0,0,-100%))) -> 0 | J30: =IF(AND(ABS(H30)>$J$5,ABS(I30)>5%),"O","") | L30: =E30-F30 -> 0 | N30: =SUMIF('BS_DEC 2026'!$D:$D,$D30,'BS_DEC 2026'!$E:$E) -> 0 | O30: =E30-N30 -> 0 | P30: =SUMIF('BS_DEC 2026'!$D:$D,$D30,'BS_DEC 2026'!$K:$K) -> 0 | Q30: =F30-P30 -> 0
B31: Evaluation allowance - product | D31: 평가충당금-제품 | E31: =SUMIF(FS_map!$H:$H,$D31,FS_map!$M:$M) -> 0 | F31: =SUMIF(FS_map!$H:$H,$D31,FS_map!$P:$P) -> 0 | G31: =SUMIF(WBS_2025YE!$D:$D,$D31,WBS_2025YE!$K:$K) -> 0 | H31: =F31-G31 -> 0 | I31: =IFERROR(H31/G31,IF(H31>0,100%,IF(H31=0,0,-100%))) -> 0 | J31: =IF(AND(ABS(H31)>$J$5,ABS(I31)>5%),"O","") | L31: =E31-F31 -> 0 | N31: =SUMIF('BS_DEC 2026'!$D:$D,$D31,'BS_DEC 2026'!$E:$E) -> 0 | O31: =E31-N31 -> 0 | P31: =SUMIF('BS_DEC 2026'!$D:$D,$D31,'BS_DEC 2026'!$K:$K) -> 0 | Q31: =F31-P31 -> 0
B32: 3. Reproduct. | C32: 3. | D32: 재공품 | E32: =SUMIF(FS_map!$H:$H,$D32,FS_map!$M:$M) -> 0 | F32: =SUMIF(FS_map!$H:$H,$D32,FS_map!$P:$P) -> 0 | G32: =SUMIF(WBS_2025YE!$D:$D,$D32,WBS_2025YE!$K:$K) -> 0 | H32: =F32-G32 -> 0 | I32: =IFERROR(H32/G32,IF(H32>0,100%,IF(H32=0,0,-100%))) -> 0 | J32: =IF(AND(ABS(H32)>$J$5,ABS(I32)>5%),"O","") | L32: =E32-F32 -> 0 | N32: =SUMIF('BS_DEC 2026'!$D:$D,$D32,'BS_DEC 2026'!$E:$E) -> 0 | O32: =E32-N32 -> 0 | P32: =SUMIF('BS_DEC 2026'!$D:$D,$D32,'BS_DEC 2026'!$K:$K) -> 0 | Q32: =F32-P32 -> 0
B33: 4. Raw materials. | C33: 4. | D33: 원재료 | E33: =SUMIF(FS_map!$H:$H,$D33,FS_map!$M:$M) -> 0 | F33: =SUMIF(FS_map!$H:$H,$D33,FS_map!$P:$P) -> 0 | G33: =SUMIF(WBS_2025YE!$D:$D,$D33,WBS_2025YE!$K:$K) -> 0 | H33: =F33-G33 -> 0 | I33: =IFERROR(H33/G33,IF(H33>0,100%,IF(H33=0,0,-100%))) -> 0 | J33: =IF(AND(ABS(H33)>$J$5,ABS(I33)>5%),"O","") | L33: =E33-F33 -> 0 | N33: =SUMIF('BS_DEC 2026'!$D:$D,$D33,'BS_DEC 2026'!$E:$E) -> 0 | O33: =E33-N33 -> 0 | P33: =SUMIF('BS_DEC 2026'!$D:$D,$D33,'BS_DEC 2026'!$K:$K) -> 0 | Q33: =F33-P33 -> 0
B34: Evaluation allowance - raw material. | D34: 평가충당금-원재료 | E34: =SUMIF(FS_map!$H:$H,$D34,FS_map!$M:$M) -> 0 | F34: =SUMIF(FS_map!$H:$H,$D34,FS_map!$P:$P) -> 0 | G34: =SUMIF(WBS_2025YE!$D:$D,$D34,WBS_2025YE!$K:$K) -> 0 | H34: =F34-G34 -> 0 | I34: =IFERROR(H34/G34,IF(H34>0,100%,IF(H34=0,0,-100%))) -> 0 | J34: =IF(AND(ABS(H34)>$J$5,ABS(I34)>5%),"O","") | L34: =E34-F34 -> 0 | N34: =SUMIF('BS_DEC 2026'!$D:$D,$D34,'BS_DEC 2026'!$E:$E) -> 0 | O34: =E34-N34 -> 0 | P34: =SUMIF('BS_DEC 2026'!$D:$D,$D34,'BS_DEC 2026'!$K:$K) -> 0 | Q34: =F34-P34 -> 0
B35: 5. Packaging ingredients. | C35: 5. | D35: 포장재료 | E35: =SUMIF(FS_map!$H:$H,$D35,FS_map!$M:$M) -> 0 | F35: =SUMIF(FS_map!$H:$H,$D35,FS_map!$P:$P) -> 0 | G35: =SUMIF(WBS_2025YE!$D:$D,$D35,WBS_2025YE!$K:$K) -> 0 | H35: =F35-G35 -> 0 | I35: =IFERROR(H35/G35,IF(H35>0,100%,IF(H35=0,0,-100%))) -> 0 | J35: =IF(AND(ABS(H35)>$J$5,ABS(I35)>5%),"O","") | L35: =E35-F35 -> 0 | N35: =SUMIF('BS_DEC 2026'!$D:$D,$D35,'BS_DEC 2026'!$E:$E) -> 0 | O35: =E35-N35 -> 0 | P35: =SUMIF('BS_DEC 2026'!$D:$D,$D35,'BS_DEC 2026'!$K:$K) -> 0 | Q35: =F35-P35 -> 0
B36: Evaluation allowance - Packaging material | D36: 평가충당금-포장재료 | E36: =SUMIF(FS_map!$H:$H,$D36,FS_map!$M:$M) -> 0 | F36: =SUMIF(FS_map!$H:$H,$D36,FS_map!$P:$P) -> 0 | G36: =SUMIF(WBS_2025YE!$D:$D,$D36,WBS_2025YE!$K:$K) -> 0 | H36: =F36-G36 -> 0 | I36: =IFERROR(H36/G36,IF(H36>0,100%,IF(H36=0,0,-100%))) -> 0 | J36: =IF(AND(ABS(H36)>$J$5,ABS(I36)>5%),"O","") | L36: =E36-F36 -> 0 | N36: =SUMIF('BS_DEC 2026'!$D:$D,$D36,'BS_DEC 2026'!$E:$E) -> 0 | O36: =E36-N36 -> 0 | P36: =SUMIF('BS_DEC 2026'!$D:$D,$D36,'BS_DEC 2026'!$K:$K) -> 0 | Q36: =F36-P36 -> 0
B37: 6. Not received. | C37: 6. | D37: 미착품 | E37: =SUMIF(FS_map!$H:$H,$D37,FS_map!$M:$M) -> 17796523585 | F37: =SUMIF(FS_map!$H:$H,$D37,FS_map!$P:$P) -> 17796523585 | G37: =SUMIF(WBS_2025YE!$D:$D,$D37,WBS_2025YE!$K:$K) -> 20691651164 | H37: =F37-G37 -> -2895127579 | I37: =IFERROR(H37/G37,IF(H37>0,100%,IF(H37=0,0,-100%))) -> -0.13991767 | J37: =IF(AND(ABS(H37)>$J$5,ABS(I37)>5%),"O","") | K37: 전기말 207억원 → 9월말 178억원 (−29억원, GR/IR 40500001 기준) 1. Pharma 미착품 203억 → 147억원: Multaq(−40억원), Toujeo(−20억원) 선적 시점 차이 2. Vaccines 미착품 4억 → 32억원: Adacel 선적 진행분 ※ 기말 cut-off 검토 시 선적조건(인도기준) 확인 필요 | L37: =E37-F37 -> 0 | N37: =SUMIF('BS_DEC 2026'!$D:$D,$D37,'BS_DEC 2026'!$E:$E) -> 17796523585 | O37: =E37-N37 -> 0 | P37: =SUMIF('BS_DEC 2026'!$D:$D,$D37,'BS_DEC 2026'!$K:$K) -> 17796523585 | Q37: =F37-P37 -> 0
I38: =IFERROR(H38/G38,IF(H38>0,100%,IF(H38=0,0,-100%))) -> 0 | J38: =IF(AND(ABS(H38)>$J$5,ABS(I38)>5%),"O","") | L38: =E38-F38 -> 0
B39: II. Fixed assets. | C39: II. 고정자산 | E39: =+E44+E40+E58+E66+E73 -> 3546064105 | F39: =+F44+F40+F58+F66+F73 -> 3546064105 | G39: =+G44+G40+G58+G66+G73 -> 3167547191 | H39: =+H44+H40+H58+H66+H73 -> 378516914 | I39: =IFERROR(H39/G39,IF(H39>0,100%,IF(H39=0,0,-100%))) -> 0.11949843 | L39: =E39-F39 -> 0 | N39: =+N44+N40+N58+N66+N73 -> 3546064105 | O39: =E39-N39 -> 0 | P39: =+P44+P40+P58+P66+P73 -> 3546064105 | Q39: =F39-P39 -> 0
B40: (1) Investment assets. | C40: (1) 투자자산 | E40: =SUM(E41:E43) -> 0 | F40: =SUM(F41:F43) -> 30000000 | G40: =SUM(G41:G43) -> 30000000 | H40: =SUM(H41:H43) -> 0 | I40: =IFERROR(H40/G40,IF(H40>0,100%,IF(H40=0,0,-100%))) -> 0 | J40: =IF(AND(ABS(H40)>$J$5,ABS(I40)>5%),"O","") | L40: =E40-F40 -> -30000000 | N40: =SUM(N41:N43) -> 0 | O40: =E40-N40 -> 0 | P40: =SUM(P41:P43) -> 30000000 | Q40: =F40-P40 -> 0
B41: 1. Long-term financial instruments. | C41: 1. | D41: 장기금융상품 | E41: =SUMIF(FS_map!$H:$H,$D41,FS_map!$M:$M) -> 0 | F41: =SUMIF(FS_map!$H:$H,$D41,FS_map!$P:$P) -> 0 | G41: =SUMIF(WBS_2025YE!$D:$D,$D41,WBS_2025YE!$K:$K) -> 0 | H41: =F41-G41 -> 0 | I41: =IFERROR(H41/G41,IF(H41>0,100%,IF(H41=0,0,-100%))) -> 0 | J41: =IF(AND(ABS(H41)>$J$5,ABS(I41)>5%),"O","") | L41: =E41-F41 -> 0 | N41: =SUMIF('BS_DEC 2026'!$D:$D,$D41,'BS_DEC 2026'!$E:$E) -> 0 | O41: =E41-N41 -> 0 | P41: =SUMIF('BS_DEC 2026'!$D:$D,$D41,'BS_DEC 2026'!$K:$K) -> 0 | Q41: =F41-P41 -> 0
C42: 2. | D42: 지분법적용투자주식 | E42: =SUMIF(FS_map!$H:$H,$D42,FS_map!$M:$M) -> 0 | F42: =SUMIF(FS_map!$H:$H,$D42,FS_map!$P:$P) -> 0 | G42: =SUMIF(WBS_2025YE!$D:$D,$D42,WBS_2025YE!$K:$K) -> 0 | H42: =F42-G42 -> 0 | I42: =IFERROR(H42/G42,IF(H42>0,100%,IF(H42=0,0,-100%))) -> 0 | J42: =IF(AND(ABS(H42)>$J$5,ABS(I42)>5%),"O","") | L42: =E42-F42 -> 0 | N42: =SUMIF('BS_DEC 2026'!$D:$D,$D42,'BS_DEC 2026'!$E:$E) -> 0 | O42: =E42-N42 -> 0 | P42: =SUMIF('BS_DEC 2026'!$D:$D,$D42,'BS_DEC 2026'!$K:$K) -> 0 | Q42: =F42-P42 -> 0
B43: 2. Other investment assets. | C43: 3. | D43: 기타의 투자자산 | E43: =SUMIF(FS_map!$H:$H,$D43,FS_map!$M:$M) -> 0 | F43: =SUMIF(FS_map!$H:$H,$D43,FS_map!$P:$P) -> 30000000 | G43: =SUMIF(WBS_2025YE!$D:$D,$D43,WBS_2025YE!$K:$K) -> 30000000 | H43: =F43-G43 -> 0 | I43: =IFERROR(H43/G43,IF(H43>0,100%,IF(H43=0,0,-100%))) -> 0 | J43: =IF(AND(ABS(H43)>$J$5,ABS(I43)>5%),"O","") | L43: =E43-F43 -> -30000000 | M43: 서울클럽회원권 30,000,000원 | N43: =SUMIF('BS_DEC 2026'!$D:$D,$D43,'BS_DEC 2026'!$E:$E) -> 0 | O43: =E43-N43 -> 0 | P43: =SUMIF('BS_DEC 2026'!$D:$D,$D43,'BS_DEC 2026'!$K:$K) -> 30000000 | Q43: =F43-P43 -> 0
B44: (2) Tangible assets. | C44: (2) 유형자산 | E44: =SUM(E45:E57) -> 1118160218 | F44: =SUM(F45:F57) -> 1118160218 | G44: =SUM(G45:G57) -> 1525937673 | H44: =SUM(H45:H57) -> -407777455 | I44: =IFERROR(H44/G44,IF(H44>0,100%,IF(H44=0,0,-100%))) -> -0.26723074 | J44: =IF(AND(ABS(H44)>$J$5,ABS(I44)>5%),"O","") | K44: 1. 취득: IT장비 등 집기비품 86백만원, 건설중인자산 43백만원 증가(서울 사무실 이전 관련 – 회사 자료상 AUC 74백만원: 사무실 이전 51.5백만원, 기타 22.5백만원) 2. 감가상각: 494백만원 (K-GAAP 기준, 사용권자산 상각 제외) 3. 처분 및 대체 없음 | L44: =E44-F44 -> 0 | N44: =SUM(N45:N57) -> 1118160218 | O44: =E44-N44 -> 0 | P44: =SUM(P45:P57) -> 1118160218 | Q44: =F44-P44 -> 0
B45: 1. Land. | C45: 1. | D45: 토지 | E45: =SUMIF(FS_map!$H:$H,$D45,FS_map!$M:$M) -> 0 | F45: =SUMIF(FS_map!$H:$H,$D45,FS_map!$P:$P) -> 0 | G45: =SUMIF(WBS_2025YE!$D:$D,$D45,WBS_2025YE!$K:$K) -> 0 | H45: =F45-G45 -> 0 | I45: =IFERROR(H45/G45,IF(H45>0,100%,IF(H45=0,0,-100%))) -> 0 | J45: =IF(AND(ABS(H45)>$J$5,ABS(I45)>5%),"O","") | L45: =E45-F45 -> 0 | N45: =SUMIF('BS_DEC 2026'!$D:$D,$D45,'BS_DEC 2026'!$E:$E) -> 0 | O45: =E45-N45 -> 0 | P45: =SUMIF('BS_DEC 2026'!$D:$D,$D45,'BS_DEC 2026'!$K:$K) -> 0 | Q45: =F45-P45 -> 0
B46: 2. Building. | C46: 2. | D46: 건물 | E46: =SUMIF(FS_map!$H:$H,$D46,FS_map!$M:$M) -> 0 | F46: =SUMIF(FS_map!$H:$H,$D46,FS_map!$P:$P) -> 0 | G46: =SUMIF(WBS_2025YE!$D:$D,$D46,WBS_2025YE!$K:$K) -> 0 | H46: =F46-G46 -> 0 | I46: =IFERROR(H46/G46,IF(H46>0,100%,IF(H46=0,0,-100%))) -> 0 | J46: =IF(AND(ABS(H46)>$J$5,ABS(I46)>5%),"O","") | L46: =E46-F46 -> 0 | N46: =SUMIF('BS_DEC 2026'!$D:$D,$D46,'BS_DEC 2026'!$E:$E) -> 0 | O46: =E46-N46 -> 0 | P46: =SUMIF('BS_DEC 2026'!$D:$D,$D46,'BS_DEC 2026'!$K:$K) -> 0 | Q46: =F46-P46 -> 0
B47: Accumulated depreciation - Building | D47: 감가상각누계액-건물 | E47: =SUMIF(FS_map!$H:$H,$D47,FS_map!$M:$M) -> 0 | F47: =SUMIF(FS_map!$H:$H,$D47,FS_map!$P:$P) -> 0 | G47: =SUMIF(WBS_2025YE!$D:$D,$D47,WBS_2025YE!$K:$K) -> 0 | H47: =F47-G47 -> 0 | I47: =IFERROR(H47/G47,IF(H47>0,100%,IF(H47=0,0,-100%))) -> 0 | J47: =IF(AND(ABS(H47)>$J$5,ABS(I47)>5%),"O","") | L47: =E47-F47 -> 0 | N47: =SUMIF('BS_DEC 2026'!$D:$D,$D47,'BS_DEC 2026'!$E:$E) -> 0 | O47: =E47-N47 -> 0 | P47: =SUMIF('BS_DEC 2026'!$D:$D,$D47,'BS_DEC 2026'!$K:$K) -> 0 | Q47: =F47-P47 -> 0
B48: 3. Construction. | C48: 3. | D48: 구축물 | E48: =SUMIF(FS_map!$H:$H,$D48,FS_map!$M:$M) -> 2388145890 | F48: =SUMIF(FS_map!$H:$H,$D48,FS_map!$P:$P) -> 2388145890 | G48: =SUMIF(WBS_2025YE!$D:$D,$D48,WBS_2025YE!$K:$K) -> 2388145890 | H48: =F48-G48 -> 0 | I48: =IFERROR(H48/G48,IF(H48>0,100%,IF(H48=0,0,-100%))) -> 0 | J48: =IF(AND(ABS(H48)>$J$5,ABS(I48)>5%),"O","") | L48: =E48-F48 -> 0 | N48: =SUMIF('BS_DEC 2026'!$D:$D,$D48,'BS_DEC 2026'!$E:$E) -> 2388145890 | O48: =E48-N48 -> 0 | P48: =SUMIF('BS_DEC 2026'!$D:$D,$D48,'BS_DEC 2026'!$K:$K) -> 2388145890 | Q48: =F48-P48 -> 0
B49: Accumulated depreciation - Construction | D49: 감가상각누계액-구축물 | E49: =SUMIF(FS_map!$H:$H,$D49,FS_map!$M:$M) -> -1988077100 | F49: =SUMIF(FS_map!$H:$H,$D49,FS_map!$P:$P) -> -1988077100 | G49: =SUMIF(WBS_2025YE!$D:$D,$D49,WBS_2025YE!$K:$K) -> -1743247679 | H49: =F49-G49 -> -244829421 | I49: =IFERROR(H49/G49,IF(H49>0,100%,IF(H49=0,0,-100%))) -> 0.14044443 | J49: =IF(AND(ABS(H49)>$J$5,ABS(I49)>5%),"O","") | L49: =E49-F49 -> 0 | N49: =SUMIF('BS_DEC 2026'!$D:$D,$D49,'BS_DEC 2026'!$E:$E) -> -1988077100 | O49: =E49-N49 -> 0 | P49: =SUMIF('BS_DEC 2026'!$D:$D,$D49,'BS_DEC 2026'!$K:$K) -> -1988077100 | Q49: =F49-P49 -> 0
B50: 4. Mechanical equipment. | C50: 4. | D50: 기계장치 | E50: =SUMIF(FS_map!$H:$H,$D50,FS_map!$M:$M) -> 1434004742 | F50: =SUMIF(FS_map!$H:$H,$D50,FS_map!$P:$P) -> 948975000 | G50: =SUMIF(WBS_2025YE!$D:$D,$D50,WBS_2025YE!$K:$K) -> 948975000 | H50: =F50-G50 -> 0 | I50: =IFERROR(H50/G50,IF(H50>0,100%,IF(H50=0,0,-100%))) -> 0 | J50: =IF(AND(ABS(H50)>$J$5,ABS(I50)>5%),"O","") | L50: =E50-F50 -> 485029742 | N50: =SUMIF('BS_DEC 2026'!$D:$D,$D50,'BS_DEC 2026'!$E:$E) -> 1434004742 | O50: =E50-N50 -> 0 | P50: =SUMIF('BS_DEC 2026'!$D:$D,$D50,'BS_DEC 2026'!$K:$K) -> 948975000 | Q50: =F50-P50 -> 0
B51: Accumulated depreciation - Machinery | D51: 감가상각누계액-기계장치 | E51: =SUMIF(FS_map!$H:$H,$D51,FS_map!$M:$M) -> -1021598692 | F51: =SUMIF(FS_map!$H:$H,$D51,FS_map!$P:$P) -> -599068950 | G51: =SUMIF(WBS_2025YE!$D:$D,$D51,WBS_2025YE!$K:$K) -> -494021176 | H51: =F51-G51 -> -105047774 | I51: =IFERROR(H51/G51,IF(H51>0,100%,IF(H51=0,0,-100%))) -> 0.2126382 | J51: =IF(AND(ABS(H51)>$J$5,ABS(I51)>5%),"O","") | L51: =E51-F51 -> -422529742 | N51: =SUMIF('BS_DEC 2026'!$D:$D,$D51,'BS_DEC 2026'!$E:$E) -> -1021598692 | O51: =E51-N51 -> 0 | P51: =SUMIF('BS_DEC 2026'!$D:$D,$D51,'BS_DEC 2026'!$K:$K) -> -599068950 | Q51: =F51-P51 -> 0
B52: 5. Carrier. | C52: 5. | D52: 차량운반구 | E52: =SUMIF(FS_map!$H:$H,$D52,FS_map!$M:$M) -> 0 | F52: =SUMIF(FS_map!$H:$H,$D52,FS_map!$P:$P) -> 0 | G52: =SUMIF(WBS_2025YE!$D:$D,$D52,WBS_2025YE!$K:$K) -> 0 | H52: =F52-G52 -> 0 | I52: =IFERROR(H52/G52,IF(H52>0,100%,IF(H52=0,0,-100%))) -> 0 | J52: =IF(AND(ABS(H52)>$J$5,ABS(I52)>5%),"O","") | L52: =E52-F52 -> 0 | N52: =SUMIF('BS_DEC 2026'!$D:$D,$D52,'BS_DEC 2026'!$E:$E) -> 0 | O52: =E52-N52 -> 0 | P52: =SUMIF('BS_DEC 2026'!$D:$D,$D52,'BS_DEC 2026'!$K:$K) -> 0 | Q52: =F52-P52 -> 0
B53: Accumulated Depreciation Amount - Carrier | D53: 감가상각누계액-차량운반구 | E53: =SUMIF(FS_map!$H:$H,$D53,FS_map!$M:$M) -> 0 | F53: =SUMIF(FS_map!$H:$H,$D53,FS_map!$P:$P) -> 0 | G53: =SUMIF(WBS_2025YE!$D:$D,$D53,WBS_2025YE!$K:$K) -> 0 | H53: =F53-G53 -> 0 | I53: =IFERROR(H53/G53,IF(H53>0,100%,IF(H53=0,0,-100%))) -> 0 | J53: =IF(AND(ABS(H53)>$J$5,ABS(I53)>5%),"O","") | L53: =E53-F53 -> 0 | N53: =SUMIF('BS_DEC 2026'!$D:$D,$D53,'BS_DEC 2026'!$E:$E) -> 0 | O53: =E53-N53 -> 0 | P53: =SUMIF('BS_DEC 2026'!$D:$D,$D53,'BS_DEC 2026'!$K:$K) -> 0 | Q53: =F53-P53 -> 0
B54: 6. Tools and equipment. | C54: 6. | D54: 공구와기구 | E54: =SUMIF(FS_map!$H:$H,$D54,FS_map!$M:$M) -> 76984016 | F54: =SUMIF(FS_map!$H:$H,$D54,FS_map!$P:$P) -> 562013758 | G54: =SUMIF(WBS_2025YE!$D:$D,$D54,WBS_2025YE!$K:$K) -> 562013758 | H54: =F54-G54 -> 0 | I54: =IFERROR(H54/G54,IF(H54>0,100%,IF(H54=0,0,-100%))) -> 0 | J54: =IF(AND(ABS(H54)>$J$5,ABS(I54)>5%),"O","") | L54: =E54-F54 -> -485029742 | N54: =SUMIF('BS_DEC 2026'!$D:$D,$D54,'BS_DEC 2026'!$E:$E) -> 76984016 | O54: =E54-N54 -> 0 | P54: =SUMIF('BS_DEC 2026'!$D:$D,$D54,'BS_DEC 2026'!$K:$K) -> 562013758 | Q54: =F54-P54 -> 0
B55: Accumulated depreciation - tools and equipment | D55: 감가상각누계액-공구와기구 | E55: =SUMIF(FS_map!$H:$H,$D55,FS_map!$M:$M) -> -75250683 | F55: =SUMIF(FS_map!$H:$H,$D55,FS_map!$P:$P) -> -497780425 | G55: =SUMIF(WBS_2025YE!$D:$D,$D55,WBS_2025YE!$K:$K) -> -479817925 | H55: =F55-G55 -> -17962500 | I55: =IFERROR(H55/G55,IF(H55>0,100%,IF(H55=0,0,-100%))) -> 0.037436075 | J55: =IF(AND(ABS(H55)>$J$5,ABS(I55)>5%),"O","") | L55: =E55-F55 -> 422529742 | N55: =SUMIF('BS_DEC 2026'!$D:$D,$D55,'BS_DEC 2026'!$E:$E) -> -75250683 | O55: =E55-N55 -> 0 | P55: =SUMIF('BS_DEC 2026'!$D:$D,$D55,'BS_DEC 2026'!$K:$K) -> -497780425 | Q55: =F55-P55 -> 0
B56: 7. Furniture. | C56: 7. | D56: 집기비품 | E56: =SUMIF(FS_map!$H:$H,$D56,FS_map!$M:$M) -> 1719424779 | F56: =SUMIF(FS_map!$H:$H,$D56,FS_map!$P:$P) -> 1719424779 | G56: =SUMIF(WBS_2025YE!$D:$D,$D56,WBS_2025YE!$K:$K) -> 1632938339 | H56: =F56-G56 -> 86486440 | I56: =IFERROR(H56/G56,IF(H56>0,100%,IF(H56=0,0,-100%))) -> 0.05296369 | J56: =IF(AND(ABS(H56)>$J$5,ABS(I56)>5%),"O","") | L56: =E56-F56 -> 0 | N56: =SUMIF('BS_DEC 2026'!$D:$D,$D56,'BS_DEC 2026'!$E:$E) -> 1719424779 | O56: =E56-N56 -> 0 | P56: =SUMIF('BS_DEC 2026'!$D:$D,$D56,'BS_DEC 2026'!$K:$K) -> 1719424779 | Q56: =F56-P56 -> 0
B57: Accumulated Depreciation Amount - Furniture Equipment | D57: 감가상각누계액-집기비품 | E57: =SUMIF(FS_map!$H:$H,$D57,FS_map!$M:$M) -> -1415472734 | F57: =SUMIF(FS_map!$H:$H,$D57,FS_map!$P:$P) -> -1415472734 | G57: =SUMIF(WBS_2025YE!$D:$D,$D57,WBS_2025YE!$K:$K) -> -1289048534 | H57: =F57-G57 -> -126424200 | I57: =IFERROR(H57/G57,IF(H57>0,100%,IF(H57=0,0,-100%))) -> 0.098075593 | J57: =IF(AND(ABS(H57)>$J$5,ABS(I57)>5%),"O","") | L57: =E57-F57 -> 0 | N57: =SUMIF('BS_DEC 2026'!$D:$D,$D57,'BS_DEC 2026'!$E:$E) -> -1415472734 | O57: =E57-N57 -> 0 | P57: =SUMIF('BS_DEC 2026'!$D:$D,$D57,'BS_DEC 2026'!$K:$K) -> -1415472734 | Q57: =F57-P57 -> 0
B58: (3) Intangible assets. | C58: (3) 무형자산 | E58: =SUM(E59:E65) -> 22468609 | F58: =SUM(F59:F65) -> 22468609 | G58: =SUM(G59:G65) -> 0 | H58: =SUM(H59:H65) -> 22468609 | I58: =IFERROR(H58/G58,IF(H58>0,100%,IF(H58=0,0,-100%))) -> 1 | J58: =IF(AND(ABS(H58)>$J$5,ABS(I58)>5%),"O","") | K58: 1. 상표권: 취득원가 10억원과 해당 상각누계액·손상충당금(404백만원·596백만원)을 전액 제거하여 순장부금액 0 → 손익 영향 없음. 제거 사유(Taxotere 글로벌 divestment 관련 여부) 확인 필요 2. 소프트웨어 22백만원 신규 취득(10550400) | L58: =E58-F58 -> 0 | N58: =SUM(N59:N65) -> 22468609 | O58: =E58-N58 -> 0 | P58: =SUM(P59:P65) -> 22468609 | Q58: =F58-P58 -> 0
B59: 1. Software. | C59: 1. | D59: 소프트웨어 | E59: =SUMIF(FS_map!$H:$H,$D59,FS_map!$M:$M) -> 378228066 | F59: =SUMIF(FS_map!$H:$H,$D59,FS_map!$P:$P) -> 378228066 | G59: =SUMIF(WBS_2025YE!$D:$D,$D59,WBS_2025YE!$K:$K) -> 355759457 | H59: =F59-G59 -> 22468609 | I59: =IFERROR(H59/G59,IF(H59>0,100%,IF(H59=0,0,-100%))) -> 0.063156744 | J59: =IF(AND(ABS(H59)>$J$5,ABS(I59)>5%),"O","") | L59: =E59-F59 -> 0 | N59: =SUMIF('BS_DEC 2026'!$D:$D,$D59,'BS_DEC 2026'!$E:$E) -> 378228066 | O59: =E59-N59 -> 0 | P59: =SUMIF('BS_DEC 2026'!$D:$D,$D59,'BS_DEC 2026'!$K:$K) -> 378228066 | Q59: =F59-P59 -> 0
B60: Accumulated depreciation - Software | D60: 감가상각누계액-소프트웨어 | E60: =SUMIF(FS_map!$H:$H,$D60,FS_map!$M:$M) -> -355759457 | F60: =SUMIF(FS_map!$H:$H,$D60,FS_map!$P:$P) -> -355759457 | G60: =SUMIF(WBS_2025YE!$D:$D,$D60,WBS_2025YE!$K:$K) -> -355759457 | H60: =F60-G60 -> 0 | I60: =IFERROR(H60/G60,IF(H60>0,100%,IF(H60=0,0,-100%))) -> 0 | J60: =IF(AND(ABS(H60)>$J$5,ABS(I60)>5%),"O","") | L60: =E60-F60 -> 0 | N60: =SUMIF('BS_DEC 2026'!$D:$D,$D60,'BS_DEC 2026'!$E:$E) -> -355759457 | O60: =E60-N60 -> 0 | P60: =SUMIF('BS_DEC 2026'!$D:$D,$D60,'BS_DEC 2026'!$K:$K) -> -355759457 | Q60: =F60-P60 -> 0
B61: 2. Trademark rights. | C61: 2. | D61: 상표권 | E61: =SUMIF(FS_map!$H:$H,$D61,FS_map!$M:$M) -> 2706860500 | F61: =SUMIF(FS_map!$H:$H,$D61,FS_map!$P:$P) -> 2706860500 | G61: =SUMIF(WBS_2025YE!$D:$D,$D61,WBS_2025YE!$K:$K) -> 3706860500 | H61: =F61-G61 -> -1000000000 | I61: =IFERROR(H61/G61,IF(H61>0,100%,IF(H61=0,0,-100%))) -> -0.26977007 | J61: =IF(AND(ABS(H61)>$J$5,ABS(I61)>5%),"O","") | L61: =E61-F61 -> 0 | N61: =SUMIF('BS_DEC 2026'!$D:$D,$D61,'BS_DEC 2026'!$E:$E) -> 2706860500 | O61: =E61-N61 -> 0 | P61: =SUMIF('BS_DEC 2026'!$D:$D,$D61,'BS_DEC 2026'!$K:$K) -> 2706860500 | Q61: =F61-P61 -> 0
B62: Accumulated amortization of trademark rights. | D62: 상표권상각누계액 | E62: =SUMIF(FS_map!$H:$H,$D62,FS_map!$M:$M) -> -2706860500 | F62: =SUMIF(FS_map!$H:$H,$D62,FS_map!$P:$P) -> -2706860500 | G62: =SUMIF(WBS_2025YE!$D:$D,$D62,WBS_2025YE!$K:$K) -> -3111195178 | H62: =F62-G62 -> 404334678 | I62: =IFERROR(H62/G62,IF(H62>0,100%,IF(H62=0,0,-100%))) -> -0.12996121 | J62: =IF(AND(ABS(H62)>$J$5,ABS(I62)>5%),"O","") | L62: =E62-F62 -> 0 | N62: =SUMIF('BS_DEC 2026'!$D:$D,$D62,'BS_DEC 2026'!$E:$E) -> -2706860500 | O62: =E62-N62 -> 0 | P62: =SUMIF('BS_DEC 2026'!$D:$D,$D62,'BS_DEC 2026'!$K:$K) -> -2706860500 | Q62: =F62-P62 -> 0
B63: Provision for loss reduction of intangible assets | D63: 무형자산감액손실충당금 | E63: =SUMIF(FS_map!$H:$H,$D63,FS_map!$M:$M) -> 0 | F63: =SUMIF(FS_map!$H:$H,$D63,FS_map!$P:$P) -> 0 | G63: =SUMIF(WBS_2025YE!$D:$D,$D63,WBS_2025YE!$K:$K) -> -595665322 | H63: =F63-G63 -> 595665322 | I63: =IFERROR(H63/G63,IF(H63>0,100%,IF(H63=0,0,-100%))) -> -1 | J63: =IF(AND(ABS(H63)>$J$5,ABS(I63)>5%),"O","") | L63: =E63-F63 -> 0 | N63: =SUMIF('BS_DEC 2026'!$D:$D,$D63,'BS_DEC 2026'!$E:$E) -> 0 | O63: =E63-N63 -> 0 | P63: =SUMIF('BS_DEC 2026'!$D:$D,$D63,'BS_DEC 2026'!$K:$K) -> 0 | Q63: =F63-P63 -> 0
B64: 3. Business right. | C64: 3. | D64: 영업권 | E64: =SUMIF(FS_map!$H:$H,$D64,FS_map!$M:$M) -> 0 | F64: =SUMIF(FS_map!$H:$H,$D64,FS_map!$P:$P) -> 0 | G64: =SUMIF(WBS_2025YE!$D:$D,$D64,WBS_2025YE!$K:$K) -> 0 | H64: =F64-G64 -> 0 | I64: =IFERROR(H64/G64,IF(H64>0,100%,IF(H64=0,0,-100%))) -> 0 | J64: =IF(AND(ABS(H64)>$J$5,ABS(I64)>5%),"O","") | L64: =E64-F64 -> 0 | N64: =SUMIF('BS_DEC 2026'!$D:$D,$D64,'BS_DEC 2026'!$E:$E) -> 0 | O64: =E64-N64 -> 0 | P64: =SUMIF('BS_DEC 2026'!$D:$D,$D64,'BS_DEC 2026'!$K:$K) -> 0 | Q64: =F64-P64 -> 0
B65: Accumulated amortization of goodwill. | D65: 영업권상각누계액 | E65: =SUMIF(FS_map!$H:$H,$D65,FS_map!$M:$M) -> 0 | F65: =SUMIF(FS_map!$H:$H,$D65,FS_map!$P:$P) -> 0 | G65: =SUMIF(WBS_2025YE!$D:$D,$D65,WBS_2025YE!$K:$K) -> 0 | H65: =F65-G65 -> 0 | I65: =IFERROR(H65/G65,IF(H65>0,100%,IF(H65=0,0,-100%))) -> 0 | J65: =IF(AND(ABS(H65)>$J$5,ABS(I65)>5%),"O","") | L65: =E65-F65 -> 0 | N65: =SUMIF('BS_DEC 2026'!$D:$D,$D65,'BS_DEC 2026'!$E:$E) -> 0 | O65: =E65-N65 -> 0 | P65: =SUMIF('BS_DEC 2026'!$D:$D,$D65,'BS_DEC 2026'!$K:$K) -> 0 | Q65: =F65-P65 -> 0
B66: (4) Other non-current assets. | C66: (4) 기타의 비유동자산 | E66: =SUM(E67:E72) -> 2353872442 | F66: =SUM(F67:F72) -> 2323872442 | G66: =SUM(G67:G72) -> 1603371682 | H66: =SUM(H67:H72) -> 720500760 | I66: =IFERROR(H66/G66,IF(H66>0,100%,IF(H66=0,0,-100%))) -> 0.44936603 | L66: =E66-F66 -> 30000000 | N66: =SUM(N67:N72) -> 2353872442 | O66: =E66-N66 -> 0 | P66: =SUM(P67:P72) -> 2323872442 | Q66: =F66-P66 -> 0
B67: 1. Deposit. | C67: 1. | D67: 보증금 | E67: =SUMIF(FS_map!$H:$H,$D67,FS_map!$M:$M) -> 1931634850 | F67: =SUMIF(FS_map!$H:$H,$D67,FS_map!$P:$P) -> 1901634850 | G67: =SUMIF(WBS_2025YE!$D:$D,$D67,WBS_2025YE!$K:$K) -> 1181134090 | H67: =F67-G67 -> 720500760 | I67: =IFERROR(H67/G67,IF(H67>0,100%,IF(H67=0,0,-100%))) -> 0.61000759 | J67: =IF(AND(ABS(H67)>$J$5,ABS(I67)>5%),"O","") | K67: 전기말 1,181백만원 → 9월말 1,902백만원 (+721백만원) 1. 반포 본사 임차보증금 1,181백만원 (계약기간 22.1.1~26.11.30) 2. 신규 사무실(센터필드) 임차보증금 30% 선지급 721백만원 → 26년 11월 반포 계약 만료에 따라 사무실 이전 예정 3. 서울클럽 회원권 30백만원은 기타의 투자자산으로 재분류 (statutory #1) ※ 이전 시 반포 사무실 복구충당부채(912백만원) 정산 및 신규 임차계약 조건 검토 필요 | L67: =E67-F67 -> 30000000 | N67: =SUMIF('BS_DEC 2026'!$D:$D,$D67,'BS_DEC 2026'!$E:$E) -> 1931634850 | O67: =E67-N67 -> 0 | P67: =SUMIF('BS_DEC 2026'!$D:$D,$D67,'BS_DEC 2026'!$K:$K) -> 1901634850 | Q67: =F67-P67 -> 0
B68: 2. Long-term advance payment cost. | C68: 2. | D68: 장기선급비용 | E68: =SUMIF(FS_map!$H:$H,$D68,FS_map!$M:$M) -> 0 | F68: =SUMIF(FS_map!$H:$H,$D68,FS_map!$P:$P) -> 0 | G68: =SUMIF(WBS_2025YE!$D:$D,$D68,WBS_2025YE!$K:$K) -> 0 | H68: =F68-G68 -> 0 | I68: =IFERROR(H68/G68,IF(H68>0,100%,IF(H68=0,0,-100%))) -> 0 | J68: =IF(AND(ABS(H68)>$J$5,ABS(I68)>5%),"O","") | L68: =E68-F68 -> 0 | N68: =SUMIF('BS_DEC 2026'!$D:$D,$D68,'BS_DEC 2026'!$E:$E) -> 0 | O68: =E68-N68 -> 0 | P68: =SUMIF('BS_DEC 2026'!$D:$D,$D68,'BS_DEC 2026'!$K:$K) -> 0 | Q68: =F68-P68 -> 0
B69: 3. Deferred corporate tax assets. | C69: 3. | D69: 이연법인세자산 | E69: =SUMIF(FS_map!$H:$H,$D69,FS_map!$M:$M) -> 422237592 | F69: =SUMIF(FS_map!$H:$H,$D69,FS_map!$P:$P) -> 422237592 | G69: =SUMIF(WBS_2025YE!$D:$D,$D69,WBS_2025YE!$K:$K) -> 422237592 | H69: =F69-G69 -> 0 | I69: =IFERROR(H69/G69,IF(H69>0,100%,IF(H69=0,0,-100%))) -> 0 | J69: =IF(AND(ABS(H69)>$J$5,ABS(I69)>5%),"O","") | L69: =E69-F69 -> 0 | N69: =SUMIF('BS_DEC 2026'!$D:$D,$D69,'BS_DEC 2026'!$E:$E) -> 422237592 | O69: =E69-N69 -> 0 | P69: =SUMIF('BS_DEC 2026'!$D:$D,$D69,'BS_DEC 2026'!$K:$K) -> 422237592 | Q69: =F69-P69 -> 0
B70: 4. Prepaid corporate tax. | C70: 4. | D70: 선급법인세 | E70: =SUMIF(FS_map!$H:$H,$D70,FS_map!$M:$M) -> 0 | F70: =SUMIF(FS_map!$H:$H,$D70,FS_map!$P:$P) -> 0 | G70: =SUMIF(WBS_2025YE!$D:$D,$D70,WBS_2025YE!$K:$K) -> 0 | H70: =F70-G70 -> 0 | I70: =IFERROR(H70/G70,IF(H70>0,100%,IF(H70=0,0,-100%))) -> 0 | J70: =IF(AND(ABS(H70)>$J$5,ABS(I70)>5%),"O","") | L70: =E70-F70 -> 0 | N70: =SUMIF('BS_DEC 2026'!$D:$D,$D70,'BS_DEC 2026'!$E:$E) -> 0 | O70: =E70-N70 -> 0 | P70: =SUMIF('BS_DEC 2026'!$D:$D,$D70,'BS_DEC 2026'!$K:$K) -> 0 | Q70: =F70-P70 -> 0
C71: 5 | D71: 장기미수금 | E71: =SUMIF(FS_map!$H:$H,$D71,FS_map!$M:$M) -> 0 | F71: =SUMIF(FS_map!$H:$H,$D71,FS_map!$P:$P) -> 0 | G71: =SUMIF(WBS_2025YE!$D:$D,$D71,WBS_2025YE!$K:$K) -> 0 | H71: =F71-G71 -> 0 | I71: =IFERROR(H71/G71,IF(H71>0,100%,IF(H71=0,0,-100%))) -> 0 | J71: =IF(AND(ABS(H71)>$J$5,ABS(I71)>5%),"O","") | L71: =E71-F71 -> 0 | N71: =SUMIF('BS_DEC 2026'!$D:$D,$D71,'BS_DEC 2026'!$E:$E) -> 0 | O71: =E71-N71 -> 0 | P71: =SUMIF('BS_DEC 2026'!$D:$D,$D71,'BS_DEC 2026'!$K:$K) -> 0 | Q71: =F71-P71 -> 0
C72: 6 | D72: 대손충당금(비유동) | E72: =SUMIF(FS_map!$H:$H,$D72,FS_map!$M:$M) -> 0 | F72: =SUMIF(FS_map!$H:$H,$D72,FS_map!$P:$P) -> 0 | G72: =SUMIF(WBS_2025YE!$D:$D,$D72,WBS_2025YE!$K:$K) -> 0 | H72: =F72-G72 -> 0 | I72: =IFERROR(H72/G72,IF(H72>0,100%,IF(H72=0,0,-100%))) -> 0 | J72: =IF(AND(ABS(H72)>$J$5,ABS(I72)>5%),"O","") | L72: =E72-F72 -> 0 | N72: =SUMIF('BS_DEC 2026'!$D:$D,$D72,'BS_DEC 2026'!$E:$E) -> 0 | O72: =E72-N72 -> 0 | P72: =SUMIF('BS_DEC 2026'!$D:$D,$D72,'BS_DEC 2026'!$K:$K) -> 0 | Q72: =F72-P72 -> 0
B73: (5) Assets under construction. | C73: (5) | D73: 건설중인자산 | E73: =SUMIF(FS_map!$H:$H,$D73,FS_map!$M:$M) -> 51562836 | F73: =SUMIF(FS_map!$H:$H,$D73,FS_map!$P:$P) -> 51562836 | G73: =WBS_2025YE!L69 -> 8237836 | H73: =F73-G73 -> 43325000 | I73: =IFERROR(H73/G73,IF(H73>0,100%,IF(H73=0,0,-100%))) -> 5.2592695 | J73: =IF(AND(ABS(H73)>$J$5,ABS(I73)>5%),"O","") | K73: 서울 사무실 이전 관련 건설중인자산 43백만원 증가 (회사 자료상 AUC 74백만원과 차이 → 확인 필요) | L73: =E73-F73 -> 0 | N73: ='BS_DEC 2026'!F71 -> 51562836 | O73: =E73-N73 -> 0 | P73: ='BS_DEC 2026'!L71 -> 51562836 | Q73: =F73-P73 -> 0
I74: =IFERROR(H74/G74,IF(H74>0,100%,IF(H74=0,0,-100%))) -> 0 | J74: =IF(AND(ABS(H74)>$J$5,ABS(I74)>5%),"O","") | L74: =E74-F74 -> 0
B75: Total assets. | C75: 자산총계 | E75: =+E11+E39 -> 469451959283 | F75: =+F11+F39 -> 457036149159 | G75: =+G11+G39 -> 402171370716 | H75: =+H11+H39 -> 54864778443 | I75: =IFERROR(H75/G75,IF(H75>0,100%,IF(H75=0,0,-100%))) -> 0.13642139 | L75: =E75-F75 -> 12415810124 | N75: =+N11+N39 -> 469451959283 | O75: =E75-N75 -> 0 | P75: =+P11+P39 -> 457036149159 | Q75: =F75-P75 -> 0
I76: =IFERROR(H76/G76,IF(H76>0,100%,IF(H76=0,0,-100%))) -> 0 | J76: =IF(AND(ABS(H76)>$J$5,ABS(I76)>5%),"O","") | L76: =E76-F76 -> 0
C77: 부채 | I77: =IFERROR(H77/G77,IF(H77>0,100%,IF(H77=0,0,-100%))) -> 0 | J77: =IF(AND(ABS(H77)>$J$5,ABS(I77)>5%),"O","") | L77: =E77-F77 -> 0
B78: I. Current liabilities. | C78: I. 유동부채 | E78: =SUM(E79:E91) -> 212685219604 | F78: =SUM(F79:F91) -> 198490213063 | G78: =SUM(G79:G91) -> 140791861473 | H78: =SUM(H79:H91) -> 57698351590 | I78: =IFERROR(H78/G78,IF(H78>0,100%,IF(H78=0,0,-100%))) -> 0.40981312 | J78: =IF(AND(ABS(H78)>$J$5,ABS(I78)>5%),"O","") -> O | K78: 주요 증가 원인은 관계사 매입채무 875억원 증가임 (매입채무 코멘트 참조) | L78: =E78-F78 -> 14195006541 | N78: =SUM(N79:N91) -> 212685219604 | O78: =E78-N78 -> 0 | P78: =SUM(P79:P91) -> 199623153058 | Q78: =F78-P78 -> -1132939995
B79: 1. Purchase obligation. | C79: 1. | D79: 매입채무 | E79: =SUMIF(FS_map!$H:$H,$D79,FS_map!$M:$M)*-1 -> 90624050033 | F79: =SUMIF(FS_map!$H:$H,$D79,FS_map!$P:$P)*-1 -> 90624050033 | G79: =SUMIF(WBS_2025YE!$D:$D,$D79,WBS_2025YE!$K:$K) -> 13684687580 | H79: =F79-G79 -> 76939362453 | I79: =IFERROR(H79/G79,IF(H79>0,100%,IF(H79=0,0,-100%))) -> 5.6222959 | J79: =IF(AND(ABS(H79)>$J$5,ABS(I79)>5%),"O","") -> O | K79: 전기말 137억원 → 9월말 906억원 (+769억원) 1. 관계사 매입채무(40100000) 0 → 875억원: Sanofi-Aventis Singapore 874억원 - 9월 매입 trade invoice 미결제분 (VAXIGRIP 21%, ELOXATIN 13%, TAXOTERE 11%, FABRAZYME 11%) - 지급조건에 따라 12월 지급 예정 (114백만원은 9월 결제분이 treasury 조정으로 연체됨) - 전기말에는 그룹 현금 최적화 정책에 따라 관계사 채무를 조기 결제하여 잔액 0 2. 제3자 상품 매입채무(40000000) 135억 → 27억원: 한독 117억 → 15억원(상품 매입 102억원 감소), 한미약품 18억 → 12억원(Rovelito 매입 감소) 3. 매입채무 회전일수(연환산 매입액 기준) 59일 (전기말 10일) ※ 회사 2026 매핑에 따라 OneCASA 임상 미지급(40000850, 131억원)은 미지급비용으로 분류 (전기 FS_map: 매입채무) | L79: =E79-F79 -> 0 | N79: =SUMIF('BS_DEC 2026'!$D:$D,$D79,'BS_DEC 2026'!$E:$E) -> 90624050033 | O79: =E79-N79 -> 0 | P79: =SUMIF('BS_DEC 2026'!$D:$D,$D79,'BS_DEC 2026'!$K:$K) -> 90624050033 | Q79: =F79-P79 -> 0
B80: 2. Short-term loans. | C80: 2. | D80: 단기차입금 | E80: =SUMIF(FS_map!$H:$H,$D80,FS_map!$M:$M)*-1 -> 0 | F80: =SUMIF(FS_map!$H:$H,$D80,FS_map!$P:$P)*-1 -> 0 | G80: =SUMIF(WBS_2025YE!$D:$D,$D80,WBS_2025YE!$K:$K) -> 0 | H80: =F80-G80 -> 0 | I80: =IFERROR(H80/G80,IF(H80>0,100%,IF(H80=0,0,-100%))) -> 0 | J80: =IF(AND(ABS(H80)>$J$5,ABS(I80)>5%),"O","") | L80: =E80-F80 -> 0 | N80: =SUMIF('BS_DEC 2026'!$D:$D,$D80,'BS_DEC 2026'!$E:$E) -> 0 | O80: =E80-N80 -> 0 | P80: =SUMIF('BS_DEC 2026'!$D:$D,$D80,'BS_DEC 2026'!$K:$K) -> 0 | Q80: =F80-P80 -> 0
B81: 3. Outstanding payments. | C81: 3. | D81: 미지급금 | E81: =SUMIF(FS_map!$H:$H,$D81,FS_map!$M:$M)*-1 -> 11973774324 | F81: =SUMIF(FS_map!$H:$H,$D81,FS_map!$P:$P)*-1 -> 11361514234 | G81: =SUMIF(WBS_2025YE!$D:$D,$D81,WBS_2025YE!$K:$K) -> 14114112505 | H81: =F81-G81 -> -2752598271 | I81: =IFERROR(H81/G81,IF(H81>0,100%,IF(H81=0,0,-100%))) -> -0.19502454 | J81: =IF(AND(ABS(H81)>$J$5,ABS(I81)>5%),"O","") | K81: 전기말 141억원 → 9월말 114억원 (−28억원) 1. 비상품 매입채무(AP Trade non-COGS, 40000012) 128억 → 77억원(−51억원): 상위 5개 거래처가 −32억원 기여 - 마콜컨설팅 −9.1억, ICON CRO −8.8억, LG화학 −7.6억, 쉥커코리아 −3.9억, 엠투컴 −2.7억원 2. 관계사 미지급금(42050000) Sanofi Pasteur Inc 25억원 신규 (Beyfortus trade invoice, 12월 지급 예정) 3. GR/IR(비재고) 19억 → 18억원 4. statutory #8: 사회보험 관련 그룹리포팅/SAP 매핑차이 612백만원을 미지급비용으로 대체 | L81: =E81-F81 -> 612260090 | N81: =SUMIF('BS_DEC 2026'!$D:$D,$D81,'BS_DEC 2026'!$E:$E) -> 11973774324 | O81: =E81-N81 -> 0 | P81: =SUMIF('BS_DEC 2026'!$D:$D,$D81,'BS_DEC 2026'!$K:$K) -> 11361514312 | Q81: =F81-P81 -> -78
B82: 4. Advance payment. | C82: 4. | D82: 선수금 | E82: =SUMIF(FS_map!$H:$H,$D82,FS_map!$M:$M)*-1 -> 0 | F82: =SUMIF(FS_map!$H:$H,$D82,FS_map!$P:$P)*-1 -> 0 | G82: =SUMIF(WBS_2025YE!$D:$D,$D82,WBS_2025YE!$K:$K) -> 2737532 | H82: =F82-G82 -> -2737532 | I82: =IFERROR(H82/G82,IF(H82>0,100%,IF(H82=0,0,-100%))) -> -1 | J82: =IF(AND(ABS(H82)>$J$5,ABS(I82)>5%),"O","") | L82: =E82-F82 -> 0 | N82: =SUMIF('BS_DEC 2026'!$D:$D,$D82,'BS_DEC 2026'!$E:$E) -> 0 | O82: =E82-N82 -> 0 | P82: =SUMIF('BS_DEC 2026'!$D:$D,$D82,'BS_DEC 2026'!$K:$K) -> 0 | Q82: =F82-P82 -> 0
B83: 5. Deposit. | C83: 5. | D83: 예수금 | E83: =SUMIF(FS_map!$H:$H,$D83,FS_map!$M:$M)*-1 -> 2221411285 | F83: =SUMIF(FS_map!$H:$H,$D83,FS_map!$P:$P)*-1 -> 2221411285 | G83: =SUMIF(WBS_2025YE!$D:$D,$D83,WBS_2025YE!$K:$K) -> 1217627633 | H83: =F83-G83 -> 1003783652 | I83: =IFERROR(H83/G83,IF(H83>0,100%,IF(H83=0,0,-100%))) -> 0.82437654 | J83: =IF(AND(ABS(H83)>$J$5,ABS(I83)>5%),"O","") | K83: 전기말 12억원 → 9월말 22억원 (+10억원) 1. 임직원 원천세 예수금 561백만원 → 1,404백만원: 급여시스템 오류로 인한 일회성 원천세 조정 810백만원 포함(10월 원천세 납부 시 정산 예정). 이를 제외한 9월분은 595백만원으로 예년 수준 2. 로열티 원천세 214백만원 (Rezurock 로열티 관련) 3. 사회보험 예수금 609백만원 (전기말 616백만원) | L83: =E83-F83 -> 0 | N83: =SUMIF('BS_DEC 2026'!$D:$D,$D83,'BS_DEC 2026'!$E:$E) -> 2221411285 | O83: =E83-N83 -> 0 | P83: =SUMIF('BS_DEC 2026'!$D:$D,$D83,'BS_DEC 2026'!$K:$K) -> 2221411285 | Q83: =F83-P83 -> 0
B84: 6. Outstanding expenses. | C84: 6. | D84: 미지급비용 | E84: =SUMIF(FS_map!$H:$H,$D84,FS_map!$M:$M)*-1 -> 94434209558 | F84: =SUMIF(FS_map!$H:$H,$D84,FS_map!$P:$P)*-1 -> 82630659524 | G84: =SUMIF(WBS_2025YE!$D:$D,$D84,WBS_2025YE!$K:$K) -> 93900348921 | H84: =F84-G84 -> -11269689397 | I84: =IFERROR(H84/G84,IF(H84>0,100%,IF(H84=0,0,-100%))) -> -0.12001755 | J84: =IF(AND(ABS(H84)>$J$5,ABS(I84)>5%),"O","") -> O | K84: 전기말 939억원 → 9월말 826억원 (−113억원) 1. 구조조정충당부채(38160000) 169억 → 45억원: 2025년 Drive 구조조정 충당금 정산 −134억원, 2026년 신규 설정 10억원 2. 매출 리베이트·장려금 - Provision for rebate 522억 → 500억원: 24년분 23억원 정리 (잔액 Dupixent 426억원, Rezurock 75억원; 25년분 160억원은 27년까지 월별 정리 예정) - Partner incentive(42910852) 51억 → 105억원: 26년부터 백신 장려금 계상 25억원, 한독 24/25년분 24억원 미정산(시장자료 지연·분쟁, 10월 정리 예정) 및 당기 27억원 - 백신 판매장려금(42910854) 50억원 → 0 (2분기 전액 정산) - 이 중 매출채권 직접차감 대상(42910850/852/853) 124억원은 statutory #5로 매출채권과 상계 3. 신규 accrual: OneCASA 임상비용 131억원(40000850), Non-PO 비용(SPC Medical, Diabetes, Transplant, CV-EP 등) 50억원, Rezurock 로열티 18억원(+16억원) 4. AP trade 기타 accrual(42910000) 116억 → 15억원: 25년말 accrual 정리 5. 상여충당금 59억 → 46억원 (25년 STI 45억원 지급·환입, 26년 STI 35억원·영업인센티브 11억원 누적), 연차충당금 12억 → 11억원 6. statutory #8: 미지급금에서 612백만원 대체 ※ IFRS16 리스부채의 K-GAAP 제거 조정 후 순액 333백만원(42911100 −232, 86911100 +131, 86200800 −232)이 미지급비용에 남아 있음(전기말 0) → 제거 조정 적정성 확인 필요 | L84: =E84-F84 -> 11803550034 | N84: =SUMIF('BS_DEC 2026'!$D:$D,$D84,'BS_DEC 2026'!$E:$E) -> 94434209558 | O84: =E84-N84 -> 0 | P84: =SUMIF('BS_DEC 2026'!$D:$D,$D84,'BS_DEC 2026'!$K:$K) -> 82630659524 | Q84: =F84-P84 -> 0
B85: 7. Value-added tax deposit. | C85: 7. | D85: 부가가치세예수금 | E85: =SUMIF(FS_map!$H:$H,$D85,FS_map!$M:$M)*-1 -> 3833429789 | F85: =SUMIF(FS_map!$H:$H,$D85,FS_map!$P:$P)*-1 -> 3833429789 | G85: =SUMIF(WBS_2025YE!$D:$D,$D85,WBS_2025YE!$K:$K) -> 4357240088 | H85: =F85-G85 -> -523810299 | I85: =IFERROR(H85/G85,IF(H85>0,100%,IF(H85=0,0,-100%))) -> -0.12021607 | J85: =IF(AND(ABS(H85)>$J$5,ABS(I85)>5%),"O","") | K85: 매출세액 178억 → 223억원(+44억원, 매출 증가), 매입세액 135억 → 184억원(+49억원, 인천공항세관 수입부가세 +36억원 등)으로 순액 5억원 감소 | L85: =E85-F85 -> 0 | N85: =SUMIF('BS_DEC 2026'!$D:$D,$D85,'BS_DEC 2026'!$E:$E) -> 3833429789 | O85: =E85-N85 -> 0 | P85: =SUMIF('BS_DEC 2026'!$D:$D,$D85,'BS_DEC 2026'!$K:$K) -> 3833429789 | Q85: =F85-P85 -> 0
B86: 9. Unpaid corporate tax. | C86: 9. | D86: 미지급법인세 | E86: =SUMIF(FS_map!$H:$H,$D86,FS_map!$M:$M)*-1 -> 2668049829 | F86: =SUMIF(FS_map!$H:$H,$D86,FS_map!$P:$P)*-1 -> 1535109912 | G86: =SUMIF(WBS_2025YE!$D:$D,$D86,WBS_2025YE!$K:$K) -> 6632631113 | H86: =F86-G86 -> -5097521201 | I86: =IFERROR(H86/G86,IF(H86>0,100%,IF(H86=0,0,-100%))) -> -0.76855189 | J86: =IF(AND(ABS(H86)>$J$5,ABS(I86)>5%),"O","") -> O | K86: 전기말 66억원 → 9월말 15억원 (−51억원) 1. SAP 당기 미지급법인세(42930000) 110억 → 35억원 - 25년 법인세 신고·납부 −110억원, 26년 9월 누적 법인세 추정 88억원 계상 - 중간예납 50억원 상계 (회사: A25000 → L45005 netting −45억원), Taxotere 처분손실 관련 −3억원 등 2. 로컬 조정(86429307): 전기말 statutory 법인세 조정 잔액 35.9억원은 당기 P16에서 정리(0) 3. statutory #15(잉여금 차이 조정) 11.3억원 차변 반영 → 상대계정 및 근거 확인 필요 4. Local PCoA(84429300) 7.8억원은 전기 이전부터 변동 없는 잔액 → 실재성 확인 필요 | L86: =E86-F86 -> 1132939917 | N86: =SUMIF('BS_DEC 2026'!$D:$D,$D86,'BS_DEC 2026'!$E:$E) -> 2668049829 | O86: =E86-N86 -> 0 | P86: =SUMIF('BS_DEC 2026'!$D:$D,$D86,'BS_DEC 2026'!$K:$K) -> 2668049829 | Q86: =F86-P86 -> -1132939917
B87: 10. The unpaid currency line. | C87: 10. | D87: 미지급통화선도 | E87: =SUMIF(FS_map!$H:$H,$D87,FS_map!$M:$M)*-1 -> 0 | F87: =SUMIF(FS_map!$H:$H,$D87,FS_map!$P:$P)*-1 -> 0 | G87: =SUMIF(WBS_2025YE!$D:$D,$D87,WBS_2025YE!$K:$K) -> 0 | H87: =F87-G87 -> 0 | I87: =IFERROR(H87/G87,IF(H87>0,100%,IF(H87=0,0,-100%))) -> 0 | J87: =IF(AND(ABS(H87)>$J$5,ABS(I87)>5%),"O","") | L87: =E87-F87 -> 0 | N87: =SUMIF('BS_DEC 2026'!$D:$D,$D87,'BS_DEC 2026'!$E:$E) -> 0 | O87: =E87-N87 -> 0 | P87: =SUMIF('BS_DEC 2026'!$D:$D,$D87,'BS_DEC 2026'!$K:$K) -> 0 | Q87: =F87-P87 -> 0
B88: 11. Liquidity bonds. | C88: 11. | D88: 유동성사채 | E88: =SUMIF(FS_map!$H:$H,$D88,FS_map!$M:$M)*-1 -> 0 | F88: =SUMIF(FS_map!$H:$H,$D88,FS_map!$P:$P)*-1 -> 0 | G88: =SUMIF(WBS_2025YE!$D:$D,$D88,WBS_2025YE!$K:$K) -> 0 | H88: =F88-G88 -> 0 | I88: =IFERROR(H88/G88,IF(H88>0,100%,IF(H88=0,0,-100%))) -> 0 | J88: =IF(AND(ABS(H88)>$J$5,ABS(I88)>5%),"O","") | L88: =E88-F88 -> 0 | N88: =SUMIF('BS_DEC 2026'!$D:$D,$D88,'BS_DEC 2026'!$E:$E) -> 0 | O88: =E88-N88 -> 0 | P88: =SUMIF('BS_DEC 2026'!$D:$D,$D88,'BS_DEC 2026'!$K:$K) -> 0 | Q88: =F88-P88 -> 0
B89: 12. Rental deposit. | C89: 12. | D89: 임대보증금 | E89: =SUMIF(FS_map!$H:$H,$D89,FS_map!$M:$M)*-1 -> 0 | F89: =SUMIF(FS_map!$H:$H,$D89,FS_map!$P:$P)*-1 -> 0 | G89: =SUMIF(WBS_2025YE!$D:$D,$D89,WBS_2025YE!$K:$K) -> 0 | H89: =F89-G89 -> 0 | I89: =IFERROR(H89/G89,IF(H89>0,100%,IF(H89=0,0,-100%))) -> 0 | J89: =IF(AND(ABS(H89)>$J$5,ABS(I89)>5%),"O","") | L89: =E89-F89 -> 0 | N89: =SUMIF('BS_DEC 2026'!$D:$D,$D89,'BS_DEC 2026'!$E:$E) -> 0 | O89: =E89-N89 -> 0 | P89: =SUMIF('BS_DEC 2026'!$D:$D,$D89,'BS_DEC 2026'!$K:$K) -> 0 | Q89: =F89-P89 -> 0
C90: 13. | D90: 반품충당금유동 | E90: =SUMIF(FS_map!$H:$H,$D90,FS_map!$M:$M)*-1 -> 6930294786 | F90: =SUMIF(FS_map!$H:$H,$D90,FS_map!$P:$P)*-1 -> 6284038286 | G90: =SUMIF(WBS_2025YE!$D:$D,$D90,WBS_2025YE!$K:$K) -> 6882476101 | H90: =F90-G90 -> -598437815 | I90: =IFERROR(H90/G90,IF(H90>0,100%,IF(H90=0,0,-100%))) -> -0.086950947 | J90: =IF(AND(ABS(H90)>$J$5,ABS(I90)>5%),"O","") | K90: 반품충당부채(유동+비유동) 전기말 77억원 → 9월말 69억원 (−7억원) 1. 백신 −6.8억원: 2025년분 대부분 정산. 9월말 잔액 44.5억원 (25년분 26억원(Vaxigrip 23억원) – 10월 정산 예정, 26년분 18억원) 2. Pharma −0.5억원: 24/25년분을 매월 정액 환입 중. 9월말 잔액 24.8억원 (24년분 3억원 – 26년 중 정리, 25년분 9억원 – 27년 정리, 26년분 12억원) 3. statutory #3: Pharma 반품충당부채 중 비유동분 646백만원(전기말 780백만원)을 비유동으로 대체 | L90: =E90-F90 -> 646256500 | N90: =SUMIF('BS_DEC 2026'!$D:$D,$D90,'BS_DEC 2026'!$E:$E) -> 6930294786 | O90: =E90-N90 -> 0 | P90: =SUMIF('BS_DEC 2026'!$D:$D,$D90,'BS_DEC 2026'!$K:$K) -> 6284038286 | Q90: =F90-P90 -> 0
I91: =IFERROR(H91/G91,IF(H91>0,100%,IF(H91=0,0,-100%))) -> 0 | J91: =IF(AND(ABS(H91)>$J$5,ABS(I91)>5%),"O","") | L91: =E91-F91 -> 0
B92: II. Fixed debt. | C92: II. 고 정 부 채 | E92: =SUM(E93:E99) -> 912409574 | F92: =SUM(F93:F99) -> 1558666074 | G92: =SUM(G93:G99) -> 1681126243 | H92: =SUM(H93:H99) -> -122460169 | I92: =IFERROR(H92/G92,IF(H92>0,100%,IF(H92=0,0,-100%))) -> -0.072844124 | L92: =E92-F92 -> -646256500 | N92: =SUM(N93:N99) -> 912409574 | O92: =E92-N92 -> 0 | P92: =SUM(P93:P99) -> 1558666074 | Q92: =F92-P92 -> 0
B93: 1. Allowance for retirement benefits. | C93: 1. | D93: 퇴직급여충당금 | E93: =SUMIF(FS_map!$H:$H,$D93,FS_map!$M:$M)*-1 -> 0 | F93: =SUMIF(FS_map!$H:$H,$D93,FS_map!$P:$P)*-1 -> 0 | G93: =SUMIF(WBS_2025YE!$D:$D,$D93,WBS_2025YE!$K:$K) -> 0 | H93: =F93-G93 -> 0 | I93: =IFERROR(H93/G93,IF(H93>0,100%,IF(H93=0,0,-100%))) -> 0 | J93: =IF(AND(ABS(H93)>$J$5,ABS(I93)>5%),"O","") | L93: =E93-F93 -> 0 | N93: =SUMIF('BS_DEC 2026'!$D:$D,$D93,'BS_DEC 2026'!$E:$E) -> 0 | O93: =E93-N93 -> 0 | P93: =SUMIF('BS_DEC 2026'!$D:$D,$D93,'BS_DEC 2026'!$K:$K) -> 0 | Q93: =F93-P93 -> 0
B94: Retirement insurance deposit. | C94: 2. | D94: 퇴직보험예치금 | E94: =SUMIF(FS_map!$H:$H,$D94,FS_map!$M:$M)*-1 -> 0 | F94: =SUMIF(FS_map!$H:$H,$D94,FS_map!$P:$P)*-1 -> 0 | G94: =SUMIF(WBS_2025YE!$D:$D,$D94,WBS_2025YE!$K:$K) -> 0 | H94: =F94-G94 -> 0 | I94: =IFERROR(H94/G94,IF(H94>0,100%,IF(H94=0,0,-100%))) -> 0 | J94: =IF(AND(ABS(H94)>$J$5,ABS(I94)>5%),"O","") | L94: =E94-F94 -> 0 | N94: =SUMIF('BS_DEC 2026'!$D:$D,$D94,'BS_DEC 2026'!$E:$E) -> 0 | O94: =E94-N94 -> 0 | P94: =SUMIF('BS_DEC 2026'!$D:$D,$D94,'BS_DEC 2026'!$K:$K) -> 0 | Q94: =F94-P94 -> 0
B95: National pension conversion fund. | C95: 3. | D95: 국민연금전환금 | E95: =SUMIF(FS_map!$H:$H,$D95,FS_map!$M:$M)*-1 -> 0 | F95: =SUMIF(FS_map!$H:$H,$D95,FS_map!$P:$P)*-1 -> 0 | G95: =SUMIF(WBS_2025YE!$D:$D,$D95,WBS_2025YE!$K:$K) -> 0 | H95: =F95-G95 -> 0 | I95: =IFERROR(H95/G95,IF(H95>0,100%,IF(H95=0,0,-100%))) -> 0 | J95: =IF(AND(ABS(H95)>$J$5,ABS(I95)>5%),"O","") | L95: =E95-F95 -> 0 | N95: =SUMIF('BS_DEC 2026'!$D:$D,$D95,'BS_DEC 2026'!$E:$E) -> 0 | O95: =E95-N95 -> 0 | P95: =SUMIF('BS_DEC 2026'!$D:$D,$D95,'BS_DEC 2026'!$K:$K) -> 0 | Q95: =F95-P95 -> 0
B96: 2. Allowance for returns. | C96: 4. | D96: 반품충당금 | E96: =SUMIF(FS_map!$H:$H,$D96,FS_map!$M:$M)*-1 -> 0 | F96: =SUMIF(FS_map!$H:$H,$D96,FS_map!$P:$P)*-1 -> 646256500 | G96: =SUMIF(WBS_2025YE!$D:$D,$D96,WBS_2025YE!$K:$K) -> 779863000 | H96: =F96-G96 -> -133606500 | I96: =IFERROR(H96/G96,IF(H96>0,100%,IF(H96=0,0,-100%))) -> -0.17132048 | J96: =IF(AND(ABS(H96)>$J$5,ABS(I96)>5%),"O","") | K96: 반품충당금유동 코멘트 참조 (Pharma 반품충당부채의 50%를 비유동으로 분류) | L96: =E96-F96 -> -646256500 | N96: =SUMIF('BS_DEC 2026'!$D:$D,$D96,'BS_DEC 2026'!$E:$E) -> 0 | O96: =E96-N96 -> 0 | P96: =SUMIF('BS_DEC 2026'!$D:$D,$D96,'BS_DEC 2026'!$K:$K) -> 646256500 | Q96: =F96-P96 -> 0
C97: 5. | D97: 복구충당부채 | E97: =SUMIF(FS_map!$H:$H,$D97,FS_map!$M:$M)*-1 -> 912409574 | F97: =SUMIF(FS_map!$H:$H,$D97,FS_map!$P:$P)*-1 -> 912409574 | G97: =SUMIF(WBS_2025YE!$D:$D,$D97,WBS_2025YE!$K:$K) -> 901263243 | H97: =F97-G97 -> 11146331 | I97: =IFERROR(H97/G97,IF(H97>0,100%,IF(H97=0,0,-100%))) -> 0.012367453 | J97: =IF(AND(ABS(H97)>$J$5,ABS(I97)>5%),"O","") | K97: 반포 사무실 복구충당부채 912백만원, 할인액 상각 11백만원. 26년 11월 임차계약 만료 및 이전 예정 → 복구의무 이행 및 정산 여부 확인 필요 | L97: =E97-F97 -> 0 | N97: =SUMIF('BS_DEC 2026'!$D:$D,$D97,'BS_DEC 2026'!$E:$E) -> 912409574 | O97: =E97-N97 -> 0 | P97: =SUMIF('BS_DEC 2026'!$D:$D,$D97,'BS_DEC 2026'!$K:$K) -> 912409574 | Q97: =F97-P97 -> 0
C98: 6. | D98: 이연법인세부채 | E98: =SUMIF(FS_map!$H:$H,$D98,FS_map!$M:$M)*-1 -> 0 | F98: =SUMIF(FS_map!$H:$H,$D98,FS_map!$P:$P)*-1 -> 0 | G98: =SUMIF(WBS_2025YE!$D:$D,$D98,WBS_2025YE!$K:$K) -> 0 | H98: =F98-G98 -> 0 | I98: =IFERROR(H98/G98,IF(H98>0,100%,IF(H98=0,0,-100%))) -> 0 | J98: =IF(AND(ABS(H98)>$J$5,ABS(I98)>5%),"O","") | L98: =E98-F98 -> 0 | N98: =SUMIF('BS_DEC 2026'!$D:$D,$D98,'BS_DEC 2026'!$E:$E) -> 0 | O98: =E98-N98 -> 0 | P98: =SUMIF('BS_DEC 2026'!$D:$D,$D98,'BS_DEC 2026'!$K:$K) -> 0 | Q98: =F98-P98 -> 0
C99: 7. | D99: 소송충당부채 | E99: =SUMIF(FS_map!$H:$H,$D99,FS_map!$M:$M)*-1 -> 0 | F99: =SUMIF(FS_map!$H:$H,$D99,FS_map!$P:$P)*-1 -> 0 | G99: =SUMIF(WBS_2025YE!$D:$D,$D99,WBS_2025YE!$K:$K) -> 0 | H99: =F99-G99 -> 0 | I99: =IFERROR(H99/G99,IF(H99>0,100%,IF(H99=0,0,-100%))) -> 0 | J99: =IF(AND(ABS(H99)>$J$5,ABS(I99)>5%),"O","") | L99: =E99-F99 -> 0 | N99: =SUMIF('BS_DEC 2026'!$D:$D,$D99,'BS_DEC 2026'!$E:$E) -> 0 | O99: =E99-N99 -> 0 | P99: =SUMIF('BS_DEC 2026'!$D:$D,$D99,'BS_DEC 2026'!$K:$K) -> 0 | Q99: =F99-P99 -> 0
B100: Total amount of fans. | C100: 부채총계 | E100: =+E78+E92 -> 213597629178 | F100: =+F78+F92 -> 200048879137 | G100: =+G78+G92 -> 142472987716 | H100: =+H78+H92 -> 57575891421 | I100: =IFERROR(H100/G100,IF(H100>0,100%,IF(H100=0,0,-100%))) -> 0.40411795 | J100: =IF(AND(ABS(H100)>$J$5,ABS(I100)>5%),"O","") -> O | K100: 주요 증가 원인은 관계사 매입채무 875억원 증가임 (매입채무·미지급비용 코멘트 참조) | L100: =E100-F100 -> 13548750041 | N100: =+N78+N92 -> 213597629178 | O100: =E100-N100 -> 0 | P100: =+P78+P92 -> 201181819132 | Q100: =F100-P100 -> -1132939995
I101: =IFERROR(H101/G101,IF(H101>0,100%,IF(H101=0,0,-100%))) -> 0 | J101: =IF(AND(ABS(H101)>$J$5,ABS(I101)>5%),"O","") | L101: =E101-F101 -> 0
B102: negative debt | C102: 자본 | I102: =IFERROR(H102/G102,IF(H102>0,100%,IF(H102=0,0,-100%))) -> 0 | J102: =IF(AND(ABS(H102)>$J$5,ABS(I102)>5%),"O","") | L102: =E102-F102 -> 0
...

Sheet P&L_KO
C2: 손익계산서
C4: =+BS_KO!C4 -> 제 37(당) 기 2026년 12월 31일 현재 | I4: OM | J4: 0.01 | K4: =G10*J4 -> 7.0976202e+09 | L4: 벤치마크: 매출액
C5: =+BS_KO!C5 -> 제 36(전) 기 2025년 12월 31일 현재 | I5: PM | J5: 0.8 | K5: =K4*J5 -> 5.6780962e+09
I6: CTT | J6: 0.03 | K6: =K4*J6 -> 2.1292861e+08
C7: =+BS_KO!C7 -> 주식회사 사노피-아벤티스코리아
C8: 과목 | E8: =BS_KO!E8 -> 2026.09 | G8: 2026.09 | H8: =BS_KO!G8 -> 2025.12 | U8: 회사 F/S 대사 (PL_DEC.2026)
E9: 수정전 | F9: 수정후 | G9: 연환산 | H9: 금액 | I9: Var. | J9: Var. % | K9: 증감분석여부? | L9: 증감분석 | U9: 회사 SAP(E열) | V9: Diff (E-U) | W9: 회사 Statutory(L열) | X9: Diff (F-W)
C10: I. 매출액 | E10: =SUM(E11:E12) -> 532321516164 | F10: =SUM(F11:F12) -> 532321516164 | G10: =F10*12/9 -> 709762021552 | H10: =SUM(H11:H12) -> 645754460671 | I10: =G10-H10 -> 64007560881 | J10: =IFERROR(I10/H10,IF(I10>0,100%,IF(I10=0,0,-100%))) -> 0.099120587 | N10: =+F10/H10-1 -> -0.17565956 | U10: =SUM(U11:U12) -> 532321516164 | V10: =E10-U10 -> 0 | W10: =SUM(W11:W12) -> 532321516164 | X10: =F10-W10 -> 0
C11: 1. | D11: 매출액 | E11: =SUMIF(FS_map!$H:$H,$D11,FS_map!$M:$M)*-1 -> 532321516164 | F11: =SUMIF(FS_map!$H:$H,$D11,FS_map!$P:$P)*-1 -> 532321516164 | G11: =F11*12/9 -> 709762021552 | H11: =SUMIF(WPL_2025YE!$D:$D,$D11,WPL_2025YE!$AI:$AI) -> 645754460671 | I11: =G11-H11 -> 64007560881 | J11: =IFERROR(I11/H11,IF(I11>0,100%,IF(I11=0,0,-100%))) -> 0.099120587 | K11: =IF(AND(ABS(I11)>$K$5,ABS(J11)>5%),"O","") -> O | L11: 9월 누적 5,323억원 (전년 동기 4,991억원 대비 +333억원, +6.7%), 연환산 7,098억원 (전기 6,458억원 대비 +640억원, +9.9%) 1. 총매출 +475억원 (회사 IFRS 분석 기준) 1) Pharma +368억원: Dupixent +160억원(AS 적응증 급여, COPD 출시, 환자 수 증가), Rezurock +145억원(급여 출시), Plavix +75억원(의료파업 영향) 2) Vaccines −3억원: Beyfortus +273억원, Hexaxim +122억원(Pentaxim 전환 및 출생아 증가), Menquadfi +68억원(군납 조기주문) vs Vaxigrip −299억원(공급 제약), 기타 제품 믹스 −166억원 3) 글로벌 divestment 품목은 MA 이전 완료 전까지 매출에 포함: Taxotere 94억원, Carprelsa 16억원 2. 매출차감 - 시장접근(MA) 약정 546억원 (전년 동기 412억원, Dupixent·Rezurock 증가) - 입찰/가격조정 115억원 (전년 동기 193억원, Vaxigrip 공급 제약) - 판매장려금 658억원 (전년 동기 562억원, Eloxatin·Plavix 판매 증가) - 반품 30억원 (Taxotere 품질이슈 회수 등) 3. 관계사 수출 매출 8.4억원 (Sanofi Winthrop, Menquadfi QC 실패 관련 수출) (출처: 회사 PL 분석적검토 – YTD Sep'26 vs YTD Sep'25) | M11: =E11-F11 -> 0 | N11: =+F11/H11-1 -> -0.17565956 | U11: =SUMIF('PL_DEC.2026'!$D:$D,$D11,'PL_DEC.2026'!$E:$E) -> 532321516164 | V11: =E11-U11 -> 0 | W11: =SUMIF('PL_DEC.2026'!$D:$D,$D11,'PL_DEC.2026'!$L:$L) -> 532321516164 | X11: =F11-W11 -> 0
C12: 2. | D12: 용역수익 | E12: =SUMIF(FS_map!$H:$H,$D12,FS_map!$M:$M)*-1 -> 0 | F12: =SUMIF(FS_map!$H:$H,$D12,FS_map!$P:$P)*-1 -> 0 | G12: =F12*12/9 -> 0 | H12: =SUMIF(WPL_2025YE!$D:$D,$D12,WPL_2025YE!$AI:$AI) -> 0 | I12: =G12-H12 -> 0 | J12: =IFERROR(I12/H12,IF(I12>0,100%,IF(I12=0,0,-100%))) -> 0 | K12: =IF(AND(ABS(I12)>$K$5,ABS(J12)>5%),"O","") | M12: =E12-F12 -> 0 | U12: =SUMIF('PL_DEC.2026'!$D:$D,$D12,'PL_DEC.2026'!$E:$E) -> 0 | V12: =E12-U12 -> 0 | W12: =SUMIF('PL_DEC.2026'!$D:$D,$D12,'PL_DEC.2026'!$L:$L) -> 0 | X12: =F12-W12 -> 0
C13: II. 매출원가 | E13: =+E14+E23+E31 -> 401363779478 | F13: =+F14+F23+F31 -> 401363779478 | G13: =G14 -> 542995529309 | H13: =+H14+H23+H31 -> 501702262547 | I13: =G13-H13 -> 41293266762 | J13: =IFERROR(I13/H13,IF(I13>0,100%,IF(I13=0,0,-100%))) -> 0.08230632 | M13: =E13-F13 -> 0 | N13: =+F13/F10 -> 0.75398752 | O13: =+H13/H10 -> 0.77692419 | U13: =+U14+U23+U31 -> 401363779478 | V13: =E13-U13 -> 0 | W13: =+W14+W23+W31 -> 401771822503 | X13: =F13-W13 -> -408043025
C14: (1) | D14: 상품매출원가 | E14: =SUMIF(FS_map!$H:$H,$D14,FS_map!$M:$M) -> 401363779478 | F14: =SUMIF(FS_map!$H:$H,$D14,FS_map!$P:$P) -> 401363779478 | G14: =SUM(G20:G22) -> 542995529309 | H14: =SUMIF(WPL_2025YE!$D:$D,$D14,WPL_2025YE!$AI:$AI) -> 501702262547 | I14: =G14-H14 -> 41293266762 | J14: =IFERROR(I14/H14,IF(I14>0,100%,IF(I14=0,0,-100%))) -> 0.08230632 | K14: =IF(AND(ABS(I14)>$K$5,ABS(J14)>5%),"O","") -> O | L14: 9월 누적 4,014억원 (전년 동기 3,748억원 대비 +266억원). 매출원가율 75.4% (전년 동기 75.1%, 전기 77.7%) 1. 매출 증가에 따른 원가 증가가 주요인. 회사 IFRS 기준 매출원가 +293억원이며, 회사는 매출총이익률을 그룹 TP 정책에 따라 월별로 관리함 2. 수불부 대사: 수불부 매출원가 4,018억원과 GL 상품매출원가의 차이 −4.1억원은 86000800(P16, 전기 TP조정 408백만원 reversal)으로 설명됨 (N14 = 0) 3. 관계사 전기 TP조정 비용 30.2억원과 백신 TP credit note −26.2억원은 잡손실로 분류됨 → 매출원가 해당 여부 검토 필요 4. 수불부 타계정(매입가격차이) 산식에 회사가 확인한 오류 −5.2억원 포함 (10월 수정 예정) | M14: =E14-F14 -> 0 | N14: =+F14-R22-SUMIF(FS_map!$D:$D,"86000800",FS_map!$P:$P) -> 0 | O14: ← 0이어야 함 (SAP 상품매출원가 = 수불부 매출원가 + 86000800 P16 reversal) | U14: =SUMIF('PL_DEC.2026'!$D:$D,$D14,'PL_DEC.2026'!$E:$E) -> 401363779478 | V14: =E14-U14 -> 0 | W14: =SUMIF('PL_DEC.2026'!$D:$D,$D14,'PL_DEC.2026'!$L:$L) -> 401771822503 | X14: =F14-W14 -> -408043025
C15: 1. | D15: 기초상품재고액 | E15: =R17 -> 155744141506 | F15: =R17 -> 155744141506 | G15: =F15 -> 155744141506 | H15: =SUMIF(WPL_2025YE!$D:$D,$D15,WPL_2025YE!$AI:$AI) -> 160701424589 | I15: =G15-H15 -> -4957283083 | J15: =IFERROR(I15/H15,IF(I15>0,100%,IF(I15=0,0,-100%))) -> -0.030847786 | M15: =E15-F15 -> 0 | Q15: <상품수불부> | U15: =W15 -> 155744141506 | V15: =E15-U15 -> 0 | W15: =SUMIF('PL_DEC.2026'!$D:$D,$D15,'PL_DEC.2026'!$L:$L) -> 155744141506 | X15: =F15-W15 -> 0
D16: 합병으로인한전입액 | E16: =SUMIF(FS_map!$H:$H,$D16,FS_map!$M:$M) -> 0 | F16: =SUMIF(FS_map!$H:$H,$D16,FS_map!$P:$P) -> 0 | G16: =F16*12/9 -> 0 | H16: =SUMIF(WPL_2025YE!$D:$D,$D16,WPL_2025YE!$AI:$AI) -> 0 | I16: =G16-H16 -> 0 | J16: =IFERROR(I16/H16,IF(I16>0,100%,IF(I16=0,0,-100%))) -> 0 | K16: =IF(AND(ABS(I16)>$K$5,ABS(J16)>5%),"O","") | M16: =E16-F16 -> 0 | Q16: 구분 | R16: <'26년9월말> | U16: =SUMIF('PL_DEC.2026'!$D:$D,$D16,'PL_DEC.2026'!$E:$E) -> 0 | V16: =E16-U16 -> 0 | W16: =SUMIF('PL_DEC.2026'!$D:$D,$D16,'PL_DEC.2026'!$L:$L) -> 0 | X16: =F16-W16 -> 0
C17: 2. | D17: 당기상품매입액 | E17: =$R$18 -> 423703487976 | F17: =$R$18 -> 423703487976 | G17: =F17*12/9 -> 564937983968 | H17: =SUMIF(WPL_2025YE!$D:$D,$D17,WPL_2025YE!$AI:$AI) -> 497042768857 | I17: =G17-H17 -> 67895215111 | J17: =IFERROR(I17/H17,IF(I17>0,100%,IF(I17=0,0,-100%))) -> 0.13659834 | K17: =IF(AND(ABS(I17)>$K$5,ABS(J17)>5%),"O","") -> O | L17: 9월 누적 4,237억원 (전년 동기 3,664억원 대비 +573억원), 연환산 5,649억원 (전기 4,970억원) 1. 매출 증가 및 재고 증가(기말상품 +219억원: Taxotere MA 이전 대비 선확보 90억원, Hexaxim·Beyfortus 시즌재고 150억원)에 따른 매입 증가 2. 관계사 매입채무(Sanofi-Aventis Singapore) 874억원 증가와 일관됨 3. 매입가격차이(타계정) −10.5억원 포함 | M17: =E17-F17 -> 0 | Q17: 기초 | R17: =H22*-1 -> 155744141506 | U17: =W17 -> 423703488001 | V17: =E17-U17 -> -25 | W17: =SUMIF('PL_DEC.2026'!$D:$D,$D17,'PL_DEC.2026'!$L:$L) -> 423703488001 | X17: =F17-W17 -> -25
D18: 관세환급금 | E18: =SUMIF(FS_map!$H:$H,$D18,FS_map!$M:$M) -> 0 | F18: =SUMIF(FS_map!$H:$H,$D18,FS_map!$P:$P) -> 0 | G18: =F18*12/9 -> 0 | H18: =SUMIF(WPL_2025YE!$D:$D,$D18,WPL_2025YE!$AI:$AI) -> 0 | I18: =G18-H18 -> 0 | J18: =IFERROR(I18/H18,IF(I18>0,100%,IF(I18=0,0,-100%))) -> 0 | K18: =IF(AND(ABS(I18)>$K$5,ABS(J18)>5%),"O","") | M18: =E18-F18 -> 0 | N18: =(+F15+F17+F21+F22)-F14 -> 408043000 | Q18: 입고 | R18: =+R19+R20 -> 423703487976 | U18: =SUMIF('PL_DEC.2026'!$D:$D,$D18,'PL_DEC.2026'!$E:$E) -> 0 | V18: =E18-U18 -> 0 | W18: =SUMIF('PL_DEC.2026'!$D:$D,$D18,'PL_DEC.2026'!$L:$L) -> 0 | X18: =F18-W18 -> 0
C19: 3. | D19: 타계정에서대체-상품 | E19: =SUMIF(FS_map!$H:$H,$D19,FS_map!$M:$M) -> 0 | F19: =SUMIF(FS_map!$H:$H,$D19,FS_map!$P:$P) -> 0 | G19: =F19*12/9 -> 0 | H19: =SUMIF(WPL_2025YE!$D:$D,$D19,WPL_2025YE!$AI:$AI) -> 0 | I19: =G19-H19 -> 0 | J19: =IFERROR(I19/H19,IF(I19>0,100%,IF(I19=0,0,-100%))) -> 0 | K19: =IF(AND(ABS(I19)>$K$5,ABS(J19)>5%),"O","") | M19: =E19-F19 -> 0 | Q19: 상품매입 | R19: ='PL_DEC.2026'!R5 -> 424753563203 | S19: Q | U19: =SUMIF('PL_DEC.2026'!$D:$D,$D19,'PL_DEC.2026'!$E:$E) -> 0 | V19: =E19-U19 -> 0 | W19: =SUMIF('PL_DEC.2026'!$D:$D,$D19,'PL_DEC.2026'!$L:$L) -> 0 | X19: =F19-W19 -> 0
D20: 계 | E20: =SUM(E15:E19) -> 579447629482 | F20: =SUM(F15:F19) -> 579447629482 | G20: =SUM(G15:G19) -> 720682125474 | H20: =SUM(H15:H19) -> 657744193446 | I20: =G20-H20 -> 62937932028 | J20: =IFERROR(I20/H20,IF(I20>0,100%,IF(I20=0,0,-100%))) -> 0.095687552 | M20: =E20-F20 -> 0 | Q20: 타계정(매입가격차이) | R20: ='PL_DEC.2026'!R6 -> -1050075227 | S20: T | U20: =SUM(U15:U19) -> 579447629507 | V20: =E20-U20 -> -25 | W20: =SUM(W15:W19) -> 579447629507 | X20: =F20-W20 -> -25
C21: 3. | D21: 타계정으로대체-상품 | E21: =R23*-1 -> -32367483 | F21: =R23*-1 -> -32367483 | G21: =F21*12/9 -> -43156644 | H21: =SUMIF(WPL_2025YE!$D:$D,$D21,WPL_2025YE!$AI:$AI) -> -297789393 | I21: =G21-H21 -> 254632749 | J21: =IFERROR(I21/H21,IF(I21>0,100%,IF(I21=0,0,-100%))) -> -0.85507662 | K21: =IF(AND(ABS(I21)>$K$5,ABS(J21)>5%),"O","") | L21: 견본품 등 타계정 대체 32백만원 (전년 동기 260백만원, 전기 연간 298백만원) | M21: =E21-F21 -> 0 | Q21: 출고 | R21: =+R22+R23 -> 401804189961 | U21: =W21 -> -32367483 | V21: =E21-U21 -> 0 | W21: =SUMIF('PL_DEC.2026'!$D:$D,$D21,'PL_DEC.2026'!$L:$L) -> -32367483 | X21: =F21-W21 -> 0
C22: 4. | D22: 기말상품재고액 | E22: =SUM(BS_KO!E28:E29)*-1 -> -177643439521 | F22: =SUM(BS_KO!F28:F29)*-1 -> -177643439521 | G22: =F22 -> -177643439521 | H22: =SUMIF(WPL_2025YE!$D:$D,$D22,WPL_2025YE!$AI:$AI) -> -155744141506 | I22: =G22-H22 -> -21899298015 | J22: =IFERROR(I22/H22,IF(I22>0,100%,IF(I22=0,0,-100%))) -> 0.14061073 | L22: 기말상품(평가충당금 차감 후) 1,776억원. BS 재고자산 코멘트 참조 | M22: =E22-F22 -> 0 | N22: =+F22=-(BS_KO!F28+BS_KO!F29) -> 1 | Q22: 매출원가 | R22: ='PL_DEC.2026'!R8 -> 401771822478 | S22: AA | U22: =W22 -> -177643439521 | V22: =E22-U22 -> 0 | W22: =SUMIF('PL_DEC.2026'!$D:$D,$D22,'PL_DEC.2026'!$L:$L) -> -177643439521 | X22: =F22-W22 -> 0
C23: (2) 제품매출원가 | E23: =SUMIF(FS_map!$H:$H,"제품매출원가",FS_map!$M:$M) -> 0 | G23: =F23*12/9 -> 0 | H23: =SUMIF(WPL_2025YE!$D:$D,"제품매출원가",WPL_2025YE!$AI:$AI) -> 0 | I23: =G23-H23 -> 0 | J23: =IFERROR(I23/H23,IF(I23>0,100%,IF(I23=0,0,-100%))) -> 0 | K23: =IF(AND(ABS(I23)>$K$5,ABS(J23)>5%),"O","") | M23: =E23-F23 -> 0 | Q23: 타계정 | R23: ='PL_DEC.2026'!R9 -> 32367483 | S23: AD -sampling | U23: =0 -> 0 | V23: =E23-U23 -> 0 | W23: =0 -> 0 | X23: =F23-W23 -> 0
C24: 1. | D24: 기초제품재고액 | G24: =F24*12/9 -> 0 | I24: =G24-H24 -> 0 | J24: =IFERROR(I24/H24,IF(I24>0,100%,IF(I24=0,0,-100%))) -> 0 | K24: =IF(AND(ABS(I24)>$K$5,ABS(J24)>5%),"O","") | M24: =E24-F24 -> 0 | Q24: 기말 | R24: =R17+R18-R21 -> 177643439521
D25: 합병으로인한전입액 | G25: =F25*12/9 -> 0 | I25: =G25-H25 -> 0 | J25: =IFERROR(I25/H25,IF(I25>0,100%,IF(I25=0,0,-100%))) -> 0 | K25: =IF(AND(ABS(I25)>$K$5,ABS(J25)>5%),"O","") | M25: =E25-F25 -> 0
C26: 2. | D26: 당기제품제조원가 | G26: =F26*12/9 -> 0 | I26: =G26-H26 -> 0 | J26: =IFERROR(I26/H26,IF(I26>0,100%,IF(I26=0,0,-100%))) -> 0 | K26: =IF(AND(ABS(I26)>$K$5,ABS(J26)>5%),"O","") | M26: =E26-F26 -> 0
C27: 3. | D27: 타계정에서대체-제품 | G27: =F27*12/9 -> 0 | I27: =G27-H27 -> 0 | J27: =IFERROR(I27/H27,IF(I27>0,100%,IF(I27=0,0,-100%))) -> 0 | K27: =IF(AND(ABS(I27)>$K$5,ABS(J27)>5%),"O","") | M27: =E27-F27 -> 0
D28: 계 | E28: =SUM(E24:E27) -> 0 | F28: =SUM(F24:F27) -> 0 | G28: =F28*12/9 -> 0 | H28: =SUM(H24:H27) -> 0 | I28: =G28-H28 -> 0 | J28: =IFERROR(I28/H28,IF(I28>0,100%,IF(I28=0,0,-100%))) -> 0 | K28: =IF(AND(ABS(I28)>$K$5,ABS(J28)>5%),"O","") | M28: =E28-F28 -> 0 | U28: =SUM(U24:U27) -> 0 | V28: =E28-U28 -> 0 | W28: =SUM(W24:W27) -> 0 | X28: =F28-W28 -> 0
C29: 4. | D29: 타계정으로대체-제품 | G29: =F29*12/9 -> 0 | I29: =G29-H29 -> 0 | J29: =IFERROR(I29/H29,IF(I29>0,100%,IF(I29=0,0,-100%))) -> 0 | K29: =IF(AND(ABS(I29)>$K$5,ABS(J29)>5%),"O","") | M29: =E29-F29 -> 0
C30: 5. | D30: 기말제품재고액 | G30: =F30*12/9 -> 0 | I30: =G30-H30 -> 0 | J30: =IFERROR(I30/H30,IF(I30>0,100%,IF(I30=0,0,-100%))) -> 0 | K30: =IF(AND(ABS(I30)>$K$5,ABS(J30)>5%),"O","") | M30: =E30-F30 -> 0
C31: (3) | D31: 용역원가 | E31: =SUMIF(FS_map!$H:$H,$D31,FS_map!$M:$M) -> 0 | F31: =SUMIF(FS_map!$H:$H,$D31,FS_map!$P:$P) -> 0 | G31: =F31*12/9 -> 0 | H31: =WPL_2025YE!AI17 -> 0 | I31: =G31-H31 -> 0 | J31: =IFERROR(I31/H31,IF(I31>0,100%,IF(I31=0,0,-100%))) -> 0 | K31: =IF(AND(ABS(I31)>$K$5,ABS(J31)>5%),"O","") | M31: =E31-F31 -> 0 | N31: =IFERROR(+F31/F12,0) -> 0 | O31: =IFERROR(+H31/H12,0) -> 0 | U31: =SUMIF('PL_DEC.2026'!$D:$D,$D31,'PL_DEC.2026'!$E:$E) -> 0 | V31: =E31-U31 -> 0 | W31: =SUMIF('PL_DEC.2026'!$D:$D,$D31,'PL_DEC.2026'!$L:$L) -> 0 | X31: =F31-W31 -> 0
C32: III. 매출총이익 | E32: =+E10-E13 -> 130957736686 | F32: =+F10-F13 -> 130957736686 | G32: =F32*12/9 -> 1.7461032e+11 | H32: =+H10-H13 -> 144052198124 | I32: =G32-H32 -> 3.0558117e+10 | J32: =IFERROR(I32/H32,IF(I32>0,100%,IF(I32=0,0,-100%))) -> 0.21213225 | M32: =E32-F32 -> 0 | U32: =+U10-U13 -> 130957736686 | V32: =E32-U32 -> 0 | W32: =+W10-W13 -> 130549693661 | X32: =F32-W32 -> 408043025
C33: IV. 판매비와일반관리비 | E33: =E34+E40+E48+E74 -> 90107200362 | F33: =F34+F40+F48+F74 -> 69362864046 | G33: =F33*12/9 -> 92483818728 | H33: =H34+H40+H48+H74 -> 114570413852 | I33: =G33-H33 -> -22086595124 | J33: =IFERROR(I33/H33,IF(I33>0,100%,IF(I33=0,0,-100%))) -> -0.19277748 | M33: =E33-F33 -> 20744336316 | U33: =U34+U40+U48+U74 -> 90107200362 | V33: =E33-U33 -> 0 | W33: =W34+W40+W48+W74 -> 69362864046 | X33: =F33-W33 -> 0
C34: (1) 판매직접비 | E34: =SUM(E35:E39) -> 15965818075 | F34: =SUM(F35:F39) -> 15958336946 | G34: =F34*12/9 -> 2.1277783e+10 | H34: =SUM(H35:H39) -> 24336799235 | I34: =G34-H34 -> -3.0590166e+09 | J34: =IFERROR(I34/H34,IF(I34>0,100%,IF(I34=0,0,-100%))) -> -0.12569511 | K34: =IF(AND(ABS(I34)>$K$5,ABS(J34)>5%),"O","") | M34: =E34-F34 -> 7481129 | U34: =SUM(U35:U39) -> 15965818075 | V34: =E34-U34 -> 0 | W34: =SUM(W35:W39) -> 15958336946 | X34: =F34-W34 -> 0
C35: 1. | D35: 판매수당 | E35: =SUMIF(FS_map!$H:$H,$D35,FS_map!$M:$M) -> 3354728043 | F35: =SUMIF(FS_map!$H:$H,$D35,FS_map!$P:$P) -> 3354728043 | G35: =F35*12/9 -> 4472970724 | H35: =SUMIF(WPL_2025YE!$D:$D,$D35,WPL_2025YE!$AI:$AI) -> 4150097232 | I35: =G35-H35 -> 322873492 | J35: =IFERROR(I35/H35,IF(I35>0,100%,IF(I35=0,0,-100%))) -> 0.077799019 | K35: =IF(AND(ABS(I35)>$K$5,ABS(J35)>5%),"O","") | L35: 9월 누적 33.5억원 (전년 동기 32.4억원) 1. 영업 인센티브 지급 41.6억원 (전기 연간 41.7억원) 2. 충당금 −8.1억원: 24년분 영업인센티브 3.8억원(3월)과 25년분 8억원(7월)을 손익으로 환입 | M35: =E35-F35 -> 0 | U35: =SUMIF('PL_DEC.2026'!$D:$D,$D35,'PL_DEC.2026'!$E:$E) -> 3354728043 | V35: =E35-U35 -> 0 | W35: =SUMIF('PL_DEC.2026'!$D:$D,$D35,'PL_DEC.2026'!$L:$L) -> 3354728043 | X35: =F35-W35 -> 0
C36: 2. | D36: 판매촉진비 | E36: =SUMIF(FS_map!$H:$H,$D36,FS_map!$M:$M) -> 0 | F36: =SUMIF(FS_map!$H:$H,$D36,FS_map!$P:$P) -> 0 | G36: =F36*12/9 -> 0 | H36: =SUMIF(WPL_2025YE!$D:$D,$D36,WPL_2025YE!$AI:$AI) -> 0 | I36: =G36-H36 -> 0 | J36: =IFERROR(I36/H36,IF(I36>0,100%,IF(I36=0,0,-100%))) -> 0 | K36: =IF(AND(ABS(I36)>$K$5,ABS(J36)>5%),"O","") | M36: =E36-F36 -> 0 | U36: =SUMIF('PL_DEC.2026'!$D:$D,$D36,'PL_DEC.2026'!$E:$E) -> 0 | V36: =E36-U36 -> 0 | W36: =SUMIF('PL_DEC.2026'!$D:$D,$D36,'PL_DEC.2026'!$L:$L) -> 0 | X36: =F36-W36 -> 0
C37: 3. | D37: 하조및운임 | E37: =SUMIF(FS_map!$H:$H,$D37,FS_map!$M:$M) -> 1641883650 | F37: =SUMIF(FS_map!$H:$H,$D37,FS_map!$P:$P) -> 1641883650 | G37: =F37*12/9 -> 2189178200 | H37: =SUMIF(WPL_2025YE!$D:$D,$D37,WPL_2025YE!$AI:$AI) -> 2701698214 | I37: =G37-H37 -> -512520014 | J37: =IFERROR(I37/H37,IF(I37>0,100%,IF(I37=0,0,-100%))) -> -0.18970291 | K37: =IF(AND(ABS(I37)>$K$5,ABS(J37)>5%),"O","") | L37: 9월 누적 16.4억원 (전년 동기 18.7억원). 운송비 8.8억원 (전기 연간 18.2억원), 외부보관료 7.6억원 (전기 연간 12.2억원) | M37: =E37-F37 -> 0 | U37: =SUMIF('PL_DEC.2026'!$D:$D,$D37,'PL_DEC.2026'!$E:$E) -> 1641883650 | V37: =E37-U37 -> 0 | W37: =SUMIF('PL_DEC.2026'!$D:$D,$D37,'PL_DEC.2026'!$L:$L) -> 1641883650 | X37: =F37-W37 -> 0
C38: 4. | D38: 시장개척비 | E38: =SUMIF(FS_map!$H:$H,$D38,FS_map!$M:$M) -> 0 | F38: =SUMIF(FS_map!$H:$H,$D38,FS_map!$P:$P) -> 0 | G38: =F38*12/9 -> 0 | H38: =SUMIF(WPL_2025YE!$D:$D,$D38,WPL_2025YE!$AI:$AI) -> 0 | I38: =G38-H38 -> 0 | J38: =IFERROR(I38/H38,IF(I38>0,100%,IF(I38=0,0,-100%))) -> 0 | K38: =IF(AND(ABS(I38)>$K$5,ABS(J38)>5%),"O","") | M38: =E38-F38 -> 0 | U38: =SUMIF('PL_DEC.2026'!$D:$D,$D38,'PL_DEC.2026'!$E:$E) -> 0 | V38: =E38-U38 -> 0 | W38: =SUMIF('PL_DEC.2026'!$D:$D,$D38,'PL_DEC.2026'!$L:$L) -> 0 | X38: =F38-W38 -> 0
C39: 5. | D39: 광고선전비 | E39: =SUMIF(FS_map!$H:$H,$D39,FS_map!$M:$M) -> 10969206382 | F39: =SUMIF(FS_map!$H:$H,$D39,FS_map!$P:$P) -> 10961725253 | G39: =F39*12/9 -> 1.4615634e+10 | H39: =SUMIF(WPL_2025YE!$D:$D,$D39,WPL_2025YE!$AI:$AI) -> 17485003789 | I39: =G39-H39 -> -2.8693701e+09 | J39: =IFERROR(I39/H39,IF(I39>0,100%,IF(I39=0,0,-100%))) -> -0.16410463 | K39: =IF(AND(ABS(I39)>$K$5,ABS(J39)>5%),"O","") | L39: 9월 누적 110억원 (전년 동기 122억원 대비 −12억원) 1. Pharma A&P 감소: EP·희귀질환 판촉활동 축소, 항암 사업 divestment, 활동 지연 2. 백신은 전년 RSV 출시 관련 조기 집행 효과가 소멸 3. 주요 계정 (전기 연간 → 당기 9월 누적): PR비 42억 → 22억원, 후원비 26억 → 14억원, 외부행사 34억 → 23억원 | M39: =E39-F39 -> 7481129 | U39: =SUMIF('PL_DEC.2026'!$D:$D,$D39,'PL_DEC.2026'!$E:$E) -> 10969206382 | V39: =E39-U39 -> 0 | W39: =SUMIF('PL_DEC.2026'!$D:$D,$D39,'PL_DEC.2026'!$L:$L) -> 10961725253 | X39: =F39-W39 -> 0
C40: (2) 인건비 | E40: =SUM(E41:E47) -> 34547108797 | F40: =SUM(F41:F47) -> 31494645340 | G40: =F40*12/9 -> 4.199286e+10 | H40: =SUM(H41:H47) -> 59889099005 | I40: =G40-H40 -> -1.7896239e+10 | J40: =IFERROR(I40/H40,IF(I40>0,100%,IF(I40=0,0,-100%))) -> -0.29882297 | M40: =E40-F40 -> 3052463457 | U40: =SUM(U41:U47) -> 34547108797 | V40: =E40-U40 -> 0 | W40: =SUM(W41:W47) -> 31494645340 | X40: =F40-W40 -> 0
C41: 1. | D41: 임원급여 | E41: =SUMIF(FS_map!$H:$H,$D41,FS_map!$M:$M) -> 0 | F41: =SUMIF(FS_map!$H:$H,$D41,FS_map!$P:$P) -> 0 | G41: =F41*12/9 -> 0 | H41: =SUMIF(WPL_2025YE!$D:$D,$D41,WPL_2025YE!$AI:$AI) -> 0 | I41: =G41-H41 -> 0 | J41: =IFERROR(I41/H41,IF(I41>0,100%,IF(I41=0,0,-100%))) -> 0 | K41: =IF(AND(ABS(I41)>$K$5,ABS(J41)>5%),"O","") | M41: =E41-F41 -> 0 | U41: =SUMIF('PL_DEC.2026'!$D:$D,$D41,'PL_DEC.2026'!$E:$E) -> 0 | V41: =E41-U41 -> 0 | W41: =SUMIF('PL_DEC.2026'!$D:$D,$D41,'PL_DEC.2026'!$L:$L) -> 0 | X41: =F41-W41 -> 0
C42: 2. | D42: 급여 | E42: =SUMIF(FS_map!$H:$H,$D42,FS_map!$M:$M) -> 27029848823 | F42: =SUMIF(FS_map!$H:$H,$D42,FS_map!$P:$P) -> 24660200591 | G42: =F42*12/9 -> 3.2880267e+10 | H42: =SUMIF(WPL_2025YE!$D:$D,$D42,WPL_2025YE!$AI:$AI) -> 51357142027 | I42: =G42-H42 -> -1.8476875e+10 | J42: =IFERROR(I42/H42,IF(I42>0,100%,IF(I42=0,0,-100%))) -> -0.35977225 | K42: =IF(AND(ABS(I42)>$K$5,ABS(J42)>5%),"O","") -> O | L42: 9월 누적 247억원 (전년 동기 273억원), 연환산 329억원으로 전기 514억원 대비 −185억원 1. 전기 급여에는 Drive 구조조정 관련 명예퇴직 충당금 166억원(70051000)이 포함됨. 당기는 −14억원 순환입 (전기 Drive 구조조정 충당금 초과분 환입, GSF 구조조정(Argo·DD&O 등) 신규 비용 반영) 2. 경상 급여(62000300) 9월 누적 276억원 (연환산 368억원, 전기 372억원): 영업인력 감소(전년 대비 −20명) 효과로 소폭 감소 3. CRU rebilling 비용차감 조정(statutory #2): 당기 23.7억원, 전기 연간 42.4억원 → 배분 기준 일관성 확인 필요 | M42: =E42-F42 -> 2369648232 | U42: =SUMIF('PL_DEC.2026'!$D:$D,$D42,'PL_DEC.2026'!$E:$E) -> 27029848823 | V42: =E42-U42 -> 0 | W42: =SUMIF('PL_DEC.2026'!$D:$D,$D42,'PL_DEC.2026'!$L:$L) -> 24660200591 | X42: =F42-W42 -> 0
C43: 3. | D43: 상여와수당 | E43: =SUMIF(FS_map!$H:$H,$D43,FS_map!$M:$M) -> 2514418581 | F43: =SUMIF(FS_map!$H:$H,$D43,FS_map!$P:$P) -> 2514418581 | G43: =F43*12/9 -> 3352558108 | H43: =SUMIF(WPL_2025YE!$D:$D,$D43,WPL_2025YE!$AI:$AI) -> 3105838674 | I43: =G43-H43 -> 246719434 | J43: =IFERROR(I43/H43,IF(I43>0,100%,IF(I43=0,0,-100%))) -> 0.079437299 | K43: =IF(AND(ABS(I43)>$K$5,ABS(J43)>5%),"O","") | L43: 9월 누적 25.1억원 (전년 동기 28.0억원): 26년 미사용연차 충당 11.3억원(62000717), 종업원 경비 9.1억원, 기타 수당 2.8억원, 연차수당 지급 2.0억원 등 | M43: =E43-F43 -> 0 | U43: =SUMIF('PL_DEC.2026'!$D:$D,$D43,'PL_DEC.2026'!$E:$E) -> 2514418581 | V43: =E43-U43 -> 0 | W43: =SUMIF('PL_DEC.2026'!$D:$D,$D43,'PL_DEC.2026'!$L:$L) -> 2514418581 | X43: =F43-W43 -> 0
C44: 4. | D44: 성과급여 | E44: =SUMIF(FS_map!$H:$H,$D44,FS_map!$M:$M) -> 342470945 | F44: =SUMIF(FS_map!$H:$H,$D44,FS_map!$P:$P) -> 9060981 | G44: =F44*12/9 -> 12081308 | H44: =SUMIF(WPL_2025YE!$D:$D,$D44,WPL_2025YE!$AI:$AI) -> 238756591 | I44: =G44-H44 -> -226675283 | J44: =IFERROR(I44/H44,IF(I44>0,100%,IF(I44=0,0,-100%))) -> -0.94939906 | K44: =IF(AND(ABS(I44)>$K$5,ABS(J44)>5%),"O","") | L44: SAP 성과급여 342백만원 중 333백만원이 CRU rebilling 비용차감 조정으로 대체되어 9백만원 남음 (전기 연간 대체 687백만원) → 배분 기준 확인 필요 | M44: =E44-F44 -> 333409964 | U44: =SUMIF('PL_DEC.2026'!$D:$D,$D44,'PL_DEC.2026'!$E:$E) -> 342470945 | V44: =E44-U44 -> 0 | W44: =SUMIF('PL_DEC.2026'!$D:$D,$D44,'PL_DEC.2026'!$L:$L) -> 9060981 | X44: =F44-W44 -> 0
C45: 5. | D45: 퇴직급여 | E45: =SUMIF(FS_map!$H:$H,$D45,FS_map!$M:$M) -> 4660370448 | F45: =SUMIF(FS_map!$H:$H,$D45,FS_map!$P:$P) -> 4310965187 | G45: =F45*12/9 -> 5.7479536e+09 | H45: =SUMIF(WPL_2025YE!$D:$D,$D45,WPL_2025YE!$AI:$AI) -> 5187361713 | I45: =G45-H45 -> 5.6059187e+08 | J45: =IFERROR(I45/H45,IF(I45>0,100%,IF(I45=0,0,-100%))) -> 0.10806878 | K45: =IF(AND(ABS(I45)>$K$5,ABS(J45)>5%),"O","") | L45: 확정기여형(DC) 퇴직급여 46.6억원 (연환산 62억원, 전기 SAP 58억원). CRU 대체 3.5억원 차감 후 43.1억원 | M45: =E45-F45 -> 349405261 | U45: =SUMIF('PL_DEC.2026'!$D:$D,$D45,'PL_DEC.2026'!$E:$E) -> 4660370448 | V45: =E45-U45 -> 0 | W45: =SUMIF('PL_DEC.2026'!$D:$D,$D45,'PL_DEC.2026'!$L:$L) -> 4310965187 | X45: =F45-W45 -> 0
C46: 6. | D46: 명예퇴직금 | E46: =SUMIF(FS_map!$H:$H,$D46,FS_map!$M:$M) -> 0 | F46: =SUMIF(FS_map!$H:$H,$D46,FS_map!$P:$P) -> 0 | G46: =F46*12/9 -> 0 | H46: =SUMIF(WPL_2025YE!$D:$D,$D46,WPL_2025YE!$AI:$AI) -> 0 | I46: =G46-H46 -> 0 | J46: =IFERROR(I46/H46,IF(I46>0,100%,IF(I46=0,0,-100%))) -> 0 | K46: =IF(AND(ABS(I46)>$K$5,ABS(J46)>5%),"O","") | M46: =E46-F46 -> 0 | U46: =SUMIF('PL_DEC.2026'!$D:$D,$D46,'PL_DEC.2026'!$E:$E) -> 0 | V46: =E46-U46 -> 0 | W46: =SUMIF('PL_DEC.2026'!$D:$D,$D46,'PL_DEC.2026'!$L:$L) -> 0 | X46: =F46-W46 -> 0
C47: 7. | D47: 잡급 | E47: =SUMIF(FS_map!$H:$H,$D47,FS_map!$M:$M) -> 0 | F47: =SUMIF(FS_map!$H:$H,$D47,FS_map!$P:$P) -> 0 | G47: =F47*12/9 -> 0 | H47: =SUMIF(WPL_2025YE!$D:$D,$D47,WPL_2025YE!$AI:$AI) -> 0 | I47: =G47-H47 -> 0 | J47: =IFERROR(I47/H47,IF(I47>0,100%,IF(I47=0,0,-100%))) -> 0 | K47: =IF(AND(ABS(I47)>$K$5,ABS(J47)>5%),"O","") | M47: =E47-F47 -> 0 | U47: =SUMIF('PL_DEC.2026'!$D:$D,$D47,'PL_DEC.2026'!$E:$E) -> 0 | V47: =E47-U47 -> 0 | W47: =SUMIF('PL_DEC.2026'!$D:$D,$D47,'PL_DEC.2026'!$L:$L) -> 0 | X47: =F47-W47 -> 0
C48: (3) 경비 | E48: =SUM(E49:E73) -> 39594273490 | F48: =SUM(F49:F73) -> 21909881760 | G48: =F48*12/9 -> 29213175680 | H48: =SUM(H49:H73) -> 30344515612 | I48: =G48-H48 -> -1131339932 | J48: =IFERROR(I48/H48,IF(I48>0,100%,IF(I48=0,0,-100%))) -> -0.037283177 | K48: =IF(AND(ABS(I48)>$K$5,ABS(J48)>5%),"O","") | M48: =E48-F48 -> 17684391730 | U48: =SUM(U49:U73) -> 39594273490 | V48: =E48-U48 -> 0 | W48: =SUM(W49:W73) -> 21909881760 | X48: =F48-W48 -> 0
C49: 1. | D49: 복리후생비 | E49: =SUMIF(FS_map!$H:$H,$D49,FS_map!$M:$M) -> 2631063371 | F49: =SUMIF(FS_map!$H:$H,$D49,FS_map!$P:$P) -> 2475705734 | G49: =F49*12/9 -> 3.300941e+09 | H49: =SUMIF(WPL_2025YE!$D:$D,$D49,WPL_2025YE!$AI:$AI) -> 3449415516 | I49: =G49-H49 -> -1.4847454e+08 | J49: =IFERROR(I49/H49,IF(I49>0,100%,IF(I49=0,0,-100%))) -> -0.04304339 | K49: =IF(AND(ABS(I49)>$K$5,ABS(J49)>5%),"O","") | L49: 9월 누적 24.8억원 (전년 동기 25.5억원). CRU rebilling 대체 1.6억원 차감 후 금액 | M49: =E49-F49 -> 155357637 | U49: =SUMIF('PL_DEC.2026'!$D:$D,$D49,'PL_DEC.2026'!$E:$E) -> 2631063371 | V49: =E49-U49 -> 0 | W49: =SUMIF('PL_DEC.2026'!$D:$D,$D49,'PL_DEC.2026'!$L:$L) -> 2475705734 | X49: =F49-W49 -> 0
C50: 2. | D50: 여비교통비 | E50: =SUMIF(FS_map!$H:$H,$D50,FS_map!$M:$M) -> 3180643883 | F50: =SUMIF(FS_map!$H:$H,$D50,FS_map!$P:$P) -> 3052418493 | G50: =F50*12/9 -> 4069891324 | H50: =SUMIF(WPL_2025YE!$D:$D,$D50,WPL_2025YE!$AI:$AI) -> 4880498630 | I50: =G50-H50 -> -810607306 | J50: =IFERROR(I50/H50,IF(I50>0,100%,IF(I50=0,0,-100%))) -> -0.16609108 | K50: =IF(AND(ABS(I50)>$K$5,ABS(J50)>5%),"O","") | L50: 9월 누적 30.5억원 (전년 동기 34.7억원 대비 −4.2억원). 영업인력 감소에 따른 국내 교통비·식대 감소 | M50: =E50-F50 -> 128225390 | U50: =SUMIF('PL_DEC.2026'!$D:$D,$D50,'PL_DEC.2026'!$E:$E) -> 3180643883 | V50: =E50-U50 -> 0 | W50: =SUMIF('PL_DEC.2026'!$D:$D,$D50,'PL_DEC.2026'!$L:$L) -> 3052418493 | X50: =F50-W50 -> 0
C51: 3. | D51: 통신비 | E51: =SUMIF(FS_map!$H:$H,$D51,FS_map!$M:$M) -> 286038515 | F51: =SUMIF(FS_map!$H:$H,$D51,FS_map!$P:$P) -> 271017893 | G51: =F51*12/9 -> 3.6135719e+08 | H51: =SUMIF(WPL_2025YE!$D:$D,$D51,WPL_2025YE!$AI:$AI) -> 376080533 | I51: =G51-H51 -> -14723342 | J51: =IFERROR(I51/H51,IF(I51>0,100%,IF(I51=0,0,-100%))) -> -0.03914944 | K51: =IF(AND(ABS(I51)>$K$5,ABS(J51)>5%),"O","") | M51: =E51-F51 -> 15020622 | U51: =SUMIF('PL_DEC.2026'!$D:$D,$D51,'PL_DEC.2026'!$E:$E) -> 286038515 | V51: =E51-U51 -> 0 | W51: =SUMIF('PL_DEC.2026'!$D:$D,$D51,'PL_DEC.2026'!$L:$L) -> 271017893 | X51: =F51-W51 -> 0
C52: 4. | D52: 소모품비 | E52: =SUMIF(FS_map!$H:$H,$D52,FS_map!$M:$M) -> 52610582 | F52: =SUMIF(FS_map!$H:$H,$D52,FS_map!$P:$P) -> 34644206 | G52: =F52*12/9 -> 46192275 | H52: =SUMIF(WPL_2025YE!$D:$D,$D52,WPL_2025YE!$AI:$AI) -> 88805964 | I52: =G52-H52 -> -42613689 | J52: =IFERROR(I52/H52,IF(I52>0,100%,IF(I52=0,0,-100%))) -> -0.47985166 | K52: =IF(AND(ABS(I52)>$K$5,ABS(J52)>5%),"O","") | M52: =E52-F52 -> 17966376 | U52: =SUMIF('PL_DEC.2026'!$D:$D,$D52,'PL_DEC.2026'!$E:$E) -> 52610582 | V52: =E52-U52 -> 0 | W52: =SUMIF('PL_DEC.2026'!$D:$D,$D52,'PL_DEC.2026'!$L:$L) -> 34644206 | X52: =F52-W52 -> 0
C53: 5. | D53: 도서인쇄비 | E53: =SUMIF(FS_map!$H:$H,$D53,FS_map!$M:$M) -> 473528691 | F53: =SUMIF(FS_map!$H:$H,$D53,FS_map!$P:$P) -> 473055604 | G53: =F53*12/9 -> 6.3074081e+08 | H53: =SUMIF(WPL_2025YE!$D:$D,$D53,WPL_2025YE!$AI:$AI) -> 327254962 | I53: =G53-H53 -> 3.0348584e+08 | J53: =IFERROR(I53/H53,IF(I53>0,100%,IF(I53=0,0,-100%))) -> 0.92736819 | K53: =IF(AND(ABS(I53)>$K$5,ABS(J53)>5%),"O","") | L53: 인쇄용역(66000650) 9월 누적 4.5억원 (전기 연간 3.0억원) 증가 | M53: =E53-F53 -> 473087 | U53: =SUMIF('PL_DEC.2026'!$D:$D,$D53,'PL_DEC.2026'!$E:$E) -> 473528691 | V53: =E53-U53 -> 0 | W53: =SUMIF('PL_DEC.2026'!$D:$D,$D53,'PL_DEC.2026'!$L:$L) -> 473055604 | X53: =F53-W53 -> 0
C54: 6. | D54: 임차료 | E54: =SUMIF(FS_map!$H:$H,$D54,FS_map!$M:$M) -> 1596899456 | F54: =SUMIF(FS_map!$H:$H,$D54,FS_map!$P:$P) -> 1596899456 | G54: =F54*12/9 -> 2.1291993e+09 | H54: =SUMIF(WPL_2025YE!$D:$D,$D54,WPL_2025YE!$AI:$AI) -> 1464303590 | I54: =G54-H54 -> 6.6489568e+08 | J54: =IFERROR(I54/H54,IF(I54>0,100%,IF(I54=0,0,-100%))) -> 0.45406956 | K54: =IF(AND(ABS(I54)>$K$5,ABS(J54)>5%),"O","") | L54: 9월 누적 16.0억원 (전년 동기 9.8억원 대비 +6.2억원) 1. 구성: K-GAAP 리스료(86132000) 11.5억원 + 부동산 임차료 12.4억원 − IFRS16 clearing 8.1억원 2. 부동산 임차료 9월 누적 12.4억원 (전기 연간 13.4억원) → 연환산 시 증가 ※ 반포 계약 만료(26.11) 및 신규 사무실 이전에 따른 이중 임차 여부와 임차료 기간귀속 확인 필요 | M54: =E54-F54 -> 0 | U54: =SUMIF('PL_DEC.2026'!$D:$D,$D54,'PL_DEC.2026'!$E:$E) -> 1596899456 | V54: =E54-U54 -> 0 | W54: =SUMIF('PL_DEC.2026'!$D:$D,$D54,'PL_DEC.2026'!$L:$L) -> 1596899456 | X54: =F54-W54 -> 0
C55: 7. | D55: 리스료 | E55: =SUMIF(FS_map!$H:$H,$D55,FS_map!$M:$M) -> 0 | F55: =SUMIF(FS_map!$H:$H,$D55,FS_map!$P:$P) -> 0 | G55: =F55*12/9 -> 0 | H55: =SUMIF(WPL_2025YE!$D:$D,$D55,WPL_2025YE!$AI:$AI) -> 0 | I55: =G55-H55 -> 0 | J55: =IFERROR(I55/H55,IF(I55>0,100%,IF(I55=0,0,-100%))) -> 0 | K55: =IF(AND(ABS(I55)>$K$5,ABS(J55)>5%),"O","") | M55: =E55-F55 -> 0 | U55: =SUMIF('PL_DEC.2026'!$D:$D,$D55,'PL_DEC.2026'!$E:$E) -> 0 | V55: =E55-U55 -> 0 | W55: =SUMIF('PL_DEC.2026'!$D:$D,$D55,'PL_DEC.2026'!$L:$L) -> 0 | X55: =F55-W55 -> 0
C56: 8. | D56: 수선비 | E56: =SUMIF(FS_map!$H:$H,$D56,FS_map!$M:$M) -> 71728174 | F56: =SUMIF(FS_map!$H:$H,$D56,FS_map!$P:$P) -> 71728174 | G56: =F56*12/9 -> 95637565 | H56: =SUMIF(WPL_2025YE!$D:$D,$D56,WPL_2025YE!$AI:$AI) -> 96139930 | I56: =G56-H56 -> -502364.67 | J56: =IFERROR(I56/H56,IF(I56>0,100%,IF(I56=0,0,-100%))) -> -0.0052253488 | K56: =IF(AND(ABS(I56)>$K$5,ABS(J56)>5%),"O","") | M56: =E56-F56 -> 0 | U56: =SUMIF('PL_DEC.2026'!$D:$D,$D56,'PL_DEC.2026'!$E:$E) -> 71728174 | V56: =E56-U56 -> 0 | W56: =SUMIF('PL_DEC.2026'!$D:$D,$D56,'PL_DEC.2026'!$L:$L) -> 71728174 | X56: =F56-W56 -> 0
C57: 9. | D57: 수도광열비 | E57: =SUMIF(FS_map!$H:$H,$D57,FS_map!$M:$M) -> 16172820 | F57: =SUMIF(FS_map!$H:$H,$D57,FS_map!$P:$P) -> 16172820 | G57: =F57*12/9 -> 21563760 | H57: =SUMIF(WPL_2025YE!$D:$D,$D57,WPL_2025YE!$AI:$AI) -> 26593320 | I57: =G57-H57 -> -5029560 | J57: =IFERROR(I57/H57,IF(I57>0,100%,IF(I57=0,0,-100%))) -> -0.1891287 | K57: =IF(AND(ABS(I57)>$K$5,ABS(J57)>5%),"O","") | M57: =E57-F57 -> 0 | U57: =SUMIF('PL_DEC.2026'!$D:$D,$D57,'PL_DEC.2026'!$E:$E) -> 16172820 | V57: =E57-U57 -> 0 | W57: =SUMIF('PL_DEC.2026'!$D:$D,$D57,'PL_DEC.2026'!$L:$L) -> 16172820 | X57: =F57-W57 -> 0
C58: 10. | D58: 회의비 | E58: =SUMIF(FS_map!$H:$H,$D58,FS_map!$M:$M) -> 0 | F58: =SUMIF(FS_map!$H:$H,$D58,FS_map!$P:$P) -> 0 | G58: =F58*12/9 -> 0 | H58: =SUMIF(WPL_2025YE!$D:$D,$D58,WPL_2025YE!$AI:$AI) -> 0 | I58: =G58-H58 -> 0 | J58: =IFERROR(I58/H58,IF(I58>0,100%,IF(I58=0,0,-100%))) -> 0 | K58: =IF(AND(ABS(I58)>$K$5,ABS(J58)>5%),"O","") | M58: =E58-F58 -> 0 | U58: =SUMIF('PL_DEC.2026'!$D:$D,$D58,'PL_DEC.2026'!$E:$E) -> 0 | V58: =E58-U58 -> 0 | W58: =SUMIF('PL_DEC.2026'!$D:$D,$D58,'PL_DEC.2026'!$L:$L) -> 0 | X58: =F58-W58 -> 0
C59: 11. | D59: 지급수수료 | E59: =SUMIF(FS_map!$H:$H,$D59,FS_map!$M:$M) -> 14049051551 | F59: =SUMIF(FS_map!$H:$H,$D59,FS_map!$P:$P) -> 13987368867 | G59: =F59*12/9 -> 18649825156 | H59: =SUMIF(WPL_2025YE!$D:$D,$D59,WPL_2025YE!$AI:$AI) -> 10883770009 | I59: =G59-H59 -> 7766055147 | J59: =IFERROR(I59/H59,IF(I59>0,100%,IF(I59=0,0,-100%))) -> 0.71354458 | K59: =IF(AND(ABS(I59)>$K$5,ABS(J59)>5%),"O","") -> O | L59: 9월 누적 139.9억원 (전년 동기 70.7억원 대비 +69.2억원), 연환산 186.5억원 (전기 108.8억원) 1. 주요 원인은 CRU rebilling 비용차감 조정(statutory #2)의 배분 차이: 지급수수료 차감액이 당기 0.6억원, 전기 연간 79.7억원(전년 동기 62.7억원). 조정 전 SAP 기준으로는 9월 누적 140.5억원(연환산 187억원)으로 전기 SAP 188.5억원과 비슷한 수준 2. 3rd party 로열티(55150000, Rezurock) 28.2억원 신규 증가 (전기 연간 4.4억원) 3. 외부 협업 인소싱(68075100) 46.8억원 (전기 연간 67.3억원), 한미약품 profit sharing(Rovelito) 14.4억원 (전기 연간 26.9억원) ※ CRU 대체 배분 기준(지급수수료 0.6억원 vs 보험료 39.8억원)이 적정한지 회사 확인 필요 | M59: =E59-F59 -> 61682684 | U59: =SUMIF('PL_DEC.2026'!$D:$D,$D59,'PL_DEC.2026'!$E:$E) -> 14049051551 | V59: =E59-U59 -> 0 | W59: =SUMIF('PL_DEC.2026'!$D:$D,$D59,'PL_DEC.2026'!$L:$L) -> 13987368867 | X59: =F59-W59 -> 0
C60: 12. | D60: 제세공과 | E60: =SUMIF(FS_map!$H:$H,$D60,FS_map!$M:$M) -> 1609276386 | F60: =SUMIF(FS_map!$H:$H,$D60,FS_map!$P:$P) -> 1609276386 | G60: =F60*12/9 -> 2145701848 | H60: =SUMIF(WPL_2025YE!$D:$D,$D60,WPL_2025YE!$AI:$AI) -> 2776269144 | I60: =G60-H60 -> -630567296 | J60: =IFERROR(I60/H60,IF(I60>0,100%,IF(I60=0,0,-100%))) -> -0.22712758 | K60: =IF(AND(ABS(I60)>$K$5,ABS(J60)>5%),"O","") | L60: 9월 누적 16.1억원 (전년 동기 16.2억원). 전기 연간에는 SMIP → SA 주식양도 관련 증권거래세 포함 | M60: =E60-F60 -> 0 | U60: =SUMIF('PL_DEC.2026'!$D:$D,$D60,'PL_DEC.2026'!$E:$E) -> 1609276386 | V60: =E60-U60 -> 0 | W60: =SUMIF('PL_DEC.2026'!$D:$D,$D60,'PL_DEC.2026'!$L:$L) -> 1609276386 | X60: =F60-W60 -> 0
C61: 13. | D61: 접대비 | E61: =SUMIF(FS_map!$H:$H,$D61,FS_map!$M:$M) -> 417021348 | F61: =SUMIF(FS_map!$H:$H,$D61,FS_map!$P:$P) -> 409977159 | G61: =F61*12/9 -> 546636212 | H61: =SUMIF(WPL_2025YE!$D:$D,$D61,WPL_2025YE!$AI:$AI) -> 799707733 | I61: =G61-H61 -> -253071521 | J61: =IFERROR(I61/H61,IF(I61>0,100%,IF(I61=0,0,-100%))) -> -0.31645501 | K61: =IF(AND(ABS(I61)>$K$5,ABS(J61)>5%),"O","") | L61: 9월 누적 4.1억원 (전년 동기 5.7억원). CRU 대체 0.07억원 차감 | M61: =E61-F61 -> 7044189 | U61: =SUMIF('PL_DEC.2026'!$D:$D,$D61,'PL_DEC.2026'!$E:$E) -> 417021348 | V61: =E61-U61 -> 0 | W61: =SUMIF('PL_DEC.2026'!$D:$D,$D61,'PL_DEC.2026'!$L:$L) -> 409977159 | X61: =F61-W61 -> 0
C62: 14. | D62: 운반및보관료 | E62: =SUMIF(FS_map!$H:$H,$D62,FS_map!$M:$M) -> 0 | F62: =SUMIF(FS_map!$H:$H,$D62,FS_map!$P:$P) -> 0 | G62: =F62*12/9 -> 0 | H62: =SUMIF(WPL_2025YE!$D:$D,$D62,WPL_2025YE!$AI:$AI) -> 0 | I62: =G62-H62 -> 0 | J62: =IFERROR(I62/H62,IF(I62>0,100%,IF(I62=0,0,-100%))) -> 0 | K62: =IF(AND(ABS(I62)>$K$5,ABS(J62)>5%),"O","") | M62: =E62-F62 -> 0 | U62: =SUMIF('PL_DEC.2026'!$D:$D,$D62,'PL_DEC.2026'!$E:$E) -> 0 | V62: =E62-U62 -> 0 | W62: =SUMIF('PL_DEC.2026'!$D:$D,$D62,'PL_DEC.2026'!$L:$L) -> 0 | X62: =F62-W62 -> 0
C63: 15. | D63: 차량비 | E63: =SUMIF(FS_map!$H:$H,$D63,FS_map!$M:$M) -> 274311 | F63: =SUMIF(FS_map!$H:$H,$D63,FS_map!$P:$P) -> 274311 | G63: =F63*12/9 -> 365748 | H63: =SUMIF(WPL_2025YE!$D:$D,$D63,WPL_2025YE!$AI:$AI) -> 1991992 | I63: =G63-H63 -> -1626244 | J63: =IFERROR(I63/H63,IF(I63>0,100%,IF(I63=0,0,-100%))) -> -0.81639083 | K63: =IF(AND(ABS(I63)>$K$5,ABS(J63)>5%),"O","") | M63: =E63-F63 -> 0 | U63: =SUMIF('PL_DEC.2026'!$D:$D,$D63,'PL_DEC.2026'!$E:$E) -> 274311 | V63: =E63-U63 -> 0 | W63: =SUMIF('PL_DEC.2026'!$D:$D,$D63,'PL_DEC.2026'!$L:$L) -> 274311 | X63: =F63-W63 -> 0
C64: 16. | D64: 임상증례조사비 | E64: =SUMIF(FS_map!$H:$H,$D64,FS_map!$M:$M) -> 13638965984 | F64: =SUMIF(FS_map!$H:$H,$D64,FS_map!$P:$P) -> 324767226 | G64: =F64*12/9 -> 433022968 | H64: =SUMIF(WPL_2025YE!$D:$D,$D64,WPL_2025YE!$AI:$AI) -> 2352493481 | I64: =G64-H64 -> -1919470513 | J64: =IFERROR(I64/H64,IF(I64>0,100%,IF(I64=0,0,-100%))) -> -0.81593022 | K64: =IF(AND(ABS(I64)>$K$5,ABS(J64)>5%),"O","") | L64: SAP 기준 9월 누적 136.4억원 (연환산 181.9억원, 전기 SAP 102.5억원)으로 증가 1. OneCASA 연구비 accrual(63450101) 68.9억원, amlitelimab 등 임상 예산 증가 (회사 IFRS: R&D 비용 +65억원) 2. CRU rebilling 비용차감 133.1억원 (전기 연간 78.9억원) 반영 후 3.2억원 | M64: =E64-F64 -> 13314198758 | U64: =SUMIF('PL_DEC.2026'!$D:$D,$D64,'PL_DEC.2026'!$E:$E) -> 13638965984 | V64: =E64-U64 -> 0 | W64: =SUMIF('PL_DEC.2026'!$D:$D,$D64,'PL_DEC.2026'!$L:$L) -> 324767226 | X64: =F64-W64 -> 0
C65: 17. | D65: 감가상각비 | E65: =SUMIF(FS_map!$H:$H,$D65,FS_map!$M:$M) -> 494263895 | F65: =SUMIF(FS_map!$H:$H,$D65,FS_map!$P:$P) -> 494263895 | G65: =F65*12/9 -> 6.5901853e+08 | H65: =SUMIF(WPL_2025YE!$D:$D,$D65,WPL_2025YE!$AI:$AI) -> 1118402963 | I65: =G65-H65 -> -4.5938444e+08 | J65: =IFERROR(I65/H65,IF(I65>0,100%,IF(I65=0,0,-100%))) -> -0.41075037 | K65: =IF(AND(ABS(I65)>$K$5,ABS(J65)>5%),"O","") | L65: K-GAAP 감가상각비 4.9억원 (사용권자산 상각 11.3억원은 제외). 일부 자산의 상각 완료로 감소 | M65: =E65-F65 -> 0 | U65: =SUMIF('PL_DEC.2026'!$D:$D,$D65,'PL_DEC.2026'!$E:$E) -> 494263895 | V65: =E65-U65 -> 0 | W65: =SUMIF('PL_DEC.2026'!$D:$D,$D65,'PL_DEC.2026'!$L:$L) -> 494263895 | X65: =F65-W65 -> 0
C66: 18. | D66: 보험료 | E66: =SUMIF(FS_map!$H:$H,$D66,FS_map!$M:$M) -> 943115504 | F66: =SUMIF(FS_map!$H:$H,$D66,FS_map!$P:$P) -> -3034833479 | G66: =F66*12/9 -> -4.0464446e+09 | H66: =SUMIF(WPL_2025YE!$D:$D,$D66,WPL_2025YE!$AI:$AI) -> 1412322391 | I66: =G66-H66 -> -5.458767e+09 | J66: =IFERROR(I66/H66,IF(I66>0,100%,IF(I66=0,0,-100%))) -> -3.8650998 | K66: =IF(AND(ABS(I66)>$K$5,ABS(J66)>5%),"O","") | L66: 수정후 보험료 −30.3억원 (음수) 1. SAP 보험료 9.4억원에 CRU rebilling 비용차감 39.8억원이 배분되어 음수 발생 (전기 연간 배분 3.3억원) 2. 배분 오류 가능성이 있으므로 회사 확인 및 재분류 필요 (지급수수료 코멘트 참조) | M66: =E66-F66 -> 3977948983 | U66: =SUMIF('PL_DEC.2026'!$D:$D,$D66,'PL_DEC.2026'!$E:$E) -> 943115504 | V66: =E66-U66 -> 0 | W66: =SUMIF('PL_DEC.2026'!$D:$D,$D66,'PL_DEC.2026'!$L:$L) -> -3034833479 | X66: =F66-W66 -> 0
C67: 19. | D67: 교육훈련비 | E67: =SUMIF(FS_map!$H:$H,$D67,FS_map!$M:$M) -> 137743628 | F67: =SUMIF(FS_map!$H:$H,$D67,FS_map!$P:$P) -> 131269624 | G67: =F67*12/9 -> 1.7502617e+08 | H67: =SUMIF(WPL_2025YE!$D:$D,$D67,WPL_2025YE!$AI:$AI) -> 229334737 | I67: =G67-H67 -> -54308572 | J67: =IFERROR(I67/H67,IF(I67>0,100%,IF(I67=0,0,-100%))) -> -0.23680918 | K67: =IF(AND(ABS(I67)>$K$5,ABS(J67)>5%),"O","") | M67: =E67-F67 -> 6474004 | U67: =SUMIF('PL_DEC.2026'!$D:$D,$D67,'PL_DEC.2026'!$E:$E) -> 137743628 | V67: =E67-U67 -> 0 | W67: =SUMIF('PL_DEC.2026'!$D:$D,$D67,'PL_DEC.2026'!$L:$L) -> 131269624 | X67: =F67-W67 -> 0
C68: 20. | D68: 학술비 | E68: =SUMIF(FS_map!$H:$H,$D68,FS_map!$M:$M) -> 0 | F68: =SUMIF(FS_map!$H:$H,$D68,FS_map!$P:$P) -> 0 | G68: =F68*12/9 -> 0 | H68: =SUMIF(WPL_2025YE!$D:$D,$D68,WPL_2025YE!$AI:$AI) -> 0 | I68: =G68-H68 -> 0 | J68: =IFERROR(I68/H68,IF(I68>0,100%,IF(I68=0,0,-100%))) -> 0 | K68: =IF(AND(ABS(I68)>$K$5,ABS(J68)>5%),"O","") | M68: =E68-F68 -> 0 | U68: =SUMIF('PL_DEC.2026'!$D:$D,$D68,'PL_DEC.2026'!$E:$E) -> 0 | V68: =E68-U68 -> 0 | W68: =SUMIF('PL_DEC.2026'!$D:$D,$D68,'PL_DEC.2026'!$L:$L) -> 0 | X68: =F68-W68 -> 0
C69: 21. | D69: 무형자산상각비 | E69: =SUMIF(FS_map!$H:$H,$D69,FS_map!$M:$M) -> 0 | F69: =SUMIF(FS_map!$H:$H,$D69,FS_map!$P:$P) -> 0 | G69: =F69*12/9 -> 0 | H69: =SUMIF(WPL_2025YE!$D:$D,$D69,WPL_2025YE!$AI:$AI) -> 0 | I69: =G69-H69 -> 0 | J69: =IFERROR(I69/H69,IF(I69>0,100%,IF(I69=0,0,-100%))) -> 0 | K69: =IF(AND(ABS(I69)>$K$5,ABS(J69)>5%),"O","") | M69: =E69-F69 -> 0 | U69: =SUMIF('PL_DEC.2026'!$D:$D,$D69,'PL_DEC.2026'!$E:$E) -> 0 | V69: =E69-U69 -> 0 | W69: =SUMIF('PL_DEC.2026'!$D:$D,$D69,'PL_DEC.2026'!$L:$L) -> 0 | X69: =F69-W69 -> 0
C70: 22. | D70: 품질관리비 | E70: =SUMIF(FS_map!$H:$H,$D70,FS_map!$M:$M) -> 0 | F70: =SUMIF(FS_map!$H:$H,$D70,FS_map!$P:$P) -> 0 | G70: =F70*12/9 -> 0 | H70: =SUMIF(WPL_2025YE!$D:$D,$D70,WPL_2025YE!$AI:$AI) -> 0 | I70: =G70-H70 -> 0 | J70: =IFERROR(I70/H70,IF(I70>0,100%,IF(I70=0,0,-100%))) -> 0 | K70: =IF(AND(ABS(I70)>$K$5,ABS(J70)>5%),"O","") | M70: =E70-F70 -> 0 | U70: =SUMIF('PL_DEC.2026'!$D:$D,$D70,'PL_DEC.2026'!$E:$E) -> 0 | V70: =E70-U70 -> 0 | W70: =SUMIF('PL_DEC.2026'!$D:$D,$D70,'PL_DEC.2026'!$L:$L) -> 0 | X70: =F70-W70 -> 0
C71: 23. | D71: 인력채용비 | E71: =SUMIF(FS_map!$H:$H,$D71,FS_map!$M:$M) -> 0 | F71: =SUMIF(FS_map!$H:$H,$D71,FS_map!$P:$P) -> 0 | G71: =F71*12/9 -> 0 | H71: =SUMIF(WPL_2025YE!$D:$D,$D71,WPL_2025YE!$AI:$AI) -> 0 | I71: =G71-H71 -> 0 | J71: =IFERROR(I71/H71,IF(I71>0,100%,IF(I71=0,0,-100%))) -> 0 | K71: =IF(AND(ABS(I71)>$K$5,ABS(J71)>5%),"O","") | M71: =E71-F71 -> 0 | U71: =SUMIF('PL_DEC.2026'!$D:$D,$D71,'PL_DEC.2026'!$E:$E) -> 0 | V71: =E71-U71 -> 0 | W71: =SUMIF('PL_DEC.2026'!$D:$D,$D71,'PL_DEC.2026'!$L:$L) -> 0 | X71: =F71-W71 -> 0
C72: 24. | D72: 대손상각비 | E72: =SUMIF(FS_map!$H:$H,$D72,FS_map!$M:$M) -> -4124609 | F72: =SUMIF(FS_map!$H:$H,$D72,FS_map!$P:$P) -> -4124609 | G72: =F72*12/9 -> -5499478.7 | H72: =SUMIF(WPL_2025YE!$D:$D,$D72,WPL_2025YE!$AI:$AI) -> 61130717 | I72: =G72-H72 -> -66630196 | J72: =IFERROR(I72/H72,IF(I72>0,100%,IF(I72=0,0,-100%))) -> -1.0899626 | K72: =IF(AND(ABS(I72)>$K$5,ABS(J72)>5%),"O","") | L72: 클리닉 매출채권 대손충당금 환입 4백만원 → 대손충당금환입(판관비 차감) 표시 검토 | M72: =E72-F72 -> 0 | U72: =SUMIF('PL_DEC.2026'!$D:$D,$D72,'PL_DEC.2026'!$E:$E) -> -4124609 | V72: =E72-U72 -> 0 | W72: =SUMIF('PL_DEC.2026'!$D:$D,$D72,'PL_DEC.2026'!$L:$L) -> -4124609 | X72: =F72-W72 -> 0
C73: 25. | D73: 잡비 | E73: =SUMIF(FS_map!$H:$H,$D73,FS_map!$M:$M) -> 0 | F73: =SUMIF(FS_map!$H:$H,$D73,FS_map!$P:$P) -> 0 | G73: =F73*12/9 -> 0 | H73: =SUMIF(WPL_2025YE!$D:$D,$D73,WPL_2025YE!$AI:$AI) -> 0 | I73: =G73-H73 -> 0 | J73: =IFERROR(I73/H73,IF(I73>0,100%,IF(I73=0,0,-100%))) -> 0 | K73: =IF(AND(ABS(I73)>$K$5,ABS(J73)>5%),"O","") | M73: =E73-F73 -> 0 | U73: =SUMIF('PL_DEC.2026'!$D:$D,$D73,'PL_DEC.2026'!$E:$E) -> 0 | V73: =E73-U73 -> 0 | W73: =SUMIF('PL_DEC.2026'!$D:$D,$D73,'PL_DEC.2026'!$L:$L) -> 0 | X73: =F73-W73 -> 0
C74: (5) 판매관리비타계정대체 | E74: =SUMIF(FS_map!$H:$H,"판매 및 일반관리비 대체",FS_map!$M:$M) -> 0 | F74: =SUMIF(FS_map!$H:$H,"판매 및 일반관리비 대체",FS_map!$P:$P) -> 0 | G74: =F74*12/9 -> 0 | H74: =WPL_2025YE!AI60 -> 0 | I74: =G74-H74 -> 0 | J74: =IFERROR(I74/H74,IF(I74>0,100%,IF(I74=0,0,-100%))) -> 0 | K74: =IF(AND(ABS(I74)>$K$5,ABS(J74)>5%),"O","") | M74: =E74-F74 -> 0 | U74: =0 -> 0 | V74: =E74-U74 -> 0 | W74: =0 -> 0 | X74: =F74-W74 -> 0
C75: V. 영업이익 | E75: =+E32-E33 -> 40850536324 | F75: =+F32-F33 -> 61594872640 | G75: =F75*12/9 -> 8.2126497e+10 | H75: =+H32-H33 -> 29481784272 | I75: =G75-H75 -> 5.2644713e+10 | J75: =IFERROR(I75/H75,IF(I75>0,100%,IF(I75=0,0,-100%))) -> 1.7856691 | M75: =E75-F75 -> -20744336316 | U75: =+U32-U33 -> 40850536324 | V75: =E75-U75 -> 0 | W75: =+W32-W33 -> 61186829615 | X75: =F75-W75 -> 408043025
C76: VI. 영업외수익 | E76: =SUM(E77:E90) -> 21799718927 | F76: =SUM(F77:F90) -> 1055382611 | G76: =F76*12/9 -> 1.4071768e+09 | H76: =SUM(H77:H90) -> 19209610002 | I76: =G76-H76 -> -1.7802433e+10 | J76: =IFERROR(I76/H76,IF(I76>0,100%,IF(I76=0,0,-100%))) -> -0.92674621 | K76: =IF(AND(ABS(I76)>$K$5,ABS(J76)>5%),"O","") -> O | L76: 잡이익 코멘트 참조. 그 외 외화환산이익 1.2억원, 이자수익 2.0억원 | M76: =E76-F76 -> 20744336316 | U76: =SUM(U77:U90) -> 21799718927 | V76: =E76-U76 -> 0 | W76: =SUM(W77:W90) -> 954170351 | X76: =F76-W76 -> 101212260
C77: 1. | D77: 이자수익 | E77: =-SUMIF(FS_map!$H:$H,$D77,FS_map!$M:$M) -> 201226458 | F77: =-SUMIF(FS_map!$H:$H,$D77,FS_map!$P:$P) -> 201226458 | G77: =F77*12/9 -> 268301944 | H77: =SUMIF(WPL_2025YE!$D:$D,$D77,WPL_2025YE!$AI:$AI) -> 238441022 | I77: =G77-H77 -> 29860922 | J77: =IFERROR(I77/H77,IF(I77>0,100%,IF(I77=0,0,-100%))) -> 0.125234 | K77: =IF(AND(ABS(I77)>$K$5,ABS(J77)>5%),"O","") | M77: =E77-F77 -> 0 | U77: =SUMIF('PL_DEC.2026'!$D:$D,$D77,'PL_DEC.2026'!$E:$E) -> 201226458 | V77: =E77-U77 -> 0 | W77: =SUMIF('PL_DEC.2026'!$D:$D,$D77,'PL_DEC.2026'!$L:$L) -> 201226458 | X77: =F77-W77 -> 0
C78: 2. | D78: 외환차익 | E78: =-SUMIF(FS_map!$H:$H,$D78,FS_map!$M:$M) -> 0 | F78: =-SUMIF(FS_map!$H:$H,$D78,FS_map!$P:$P) -> 0 | G78: =F78*12/9 -> 0 | H78: =SUMIF(WPL_2025YE!$D:$D,$D78,WPL_2025YE!$AI:$AI) -> 0 | I78: =G78-H78 -> 0 | J78: =IFERROR(I78/H78,IF(I78>0,100%,IF(I78=0,0,-100%))) -> 0 | K78: =IF(AND(ABS(I78)>$K$5,ABS(J78)>5%),"O","") | M78: =E78-F78 -> 0 | U78: =SUMIF('PL_DEC.2026'!$D:$D,$D78,'PL_DEC.2026'!$E:$E) -> 0 | V78: =E78-U78 -> 0 | W78: =SUMIF('PL_DEC.2026'!$D:$D,$D78,'PL_DEC.2026'!$L:$L) -> 0 | X78: =F78-W78 -> 0
C79: 3. | D79: 외화환산이익 | E79: =-SUMIF(FS_map!$H:$H,$D79,FS_map!$M:$M) -> 123781136 | F79: =-SUMIF(FS_map!$H:$H,$D79,FS_map!$P:$P) -> 123781136 | G79: =F79*12/9 -> 1.6504151e+08 | H79: =SUMIF(WPL_2025YE!$D:$D,$D79,WPL_2025YE!$AI:$AI) -> 24481540 | I79: =G79-H79 -> 1.4055997e+08 | J79: =IFERROR(I79/H79,IF(I79>0,100%,IF(I79=0,0,-100%))) -> 5.7414678 | K79: =IF(AND(ABS(I79)>$K$5,ABS(J79)>5%),"O","") | L79: 외화 채무 환산이익 1.2억원 (9월말 환율 기준) | M79: =E79-F79 -> 0 | U79: =SUMIF('PL_DEC.2026'!$D:$D,$D79,'PL_DEC.2026'!$E:$E) -> 123781136 | V79: =E79-U79 -> 0 | W79: =SUMIF('PL_DEC.2026'!$D:$D,$D79,'PL_DEC.2026'!$L:$L) -> 123781136 | X79: =F79-W79 -> 0
C80: 4. | D80: 투자자산처분이익 | E80: =-SUMIF(FS_map!$H:$H,$D80,FS_map!$M:$M) -> 0 | F80: =-SUMIF(FS_map!$H:$H,$D80,FS_map!$P:$P) -> 0 | G80: =F80*12/9 -> 0 | H80: =SUMIF(WPL_2025YE!$D:$D,$D80,WPL_2025YE!$AI:$AI) -> 0 | I80: =G80-H80 -> 0 | J80: =IFERROR(I80/H80,IF(I80>0,100%,IF(I80=0,0,-100%))) -> 0 | K80: =IF(AND(ABS(I80)>$K$5,ABS(J80)>5%),"O","") | M80: =E80-F80 -> 0 | U80: =SUMIF('PL_DEC.2026'!$D:$D,$D80,'PL_DEC.2026'!$E:$E) -> 0 | V80: =E80-U80 -> 0 | W80: =SUMIF('PL_DEC.2026'!$D:$D,$D80,'PL_DEC.2026'!$L:$L) -> 0 | X80: =F80-W80 -> 0
C81: 5. | D81: 유형자산처분이익 | E81: =-SUMIF(FS_map!$H:$H,$D81,FS_map!$M:$M) -> 0 | F81: =-SUMIF(FS_map!$H:$H,$D81,FS_map!$P:$P) -> 0 | G81: =F81*12/9 -> 0 | H81: =SUMIF(WPL_2025YE!$D:$D,$D81,WPL_2025YE!$AI:$AI) -> 0 | I81: =G81-H81 -> 0 | J81: =IFERROR(I81/H81,IF(I81>0,100%,IF(I81=0,0,-100%))) -> 0 | K81: =IF(AND(ABS(I81)>$K$5,ABS(J81)>5%),"O","") | M81: =E81-F81 -> 0 | U81: =SUMIF('PL_DEC.2026'!$D:$D,$D81,'PL_DEC.2026'!$E:$E) -> 0 | V81: =E81-U81 -> 0 | W81: =SUMIF('PL_DEC.2026'!$D:$D,$D81,'PL_DEC.2026'!$L:$L) -> 0 | X81: =F81-W81 -> 0
C82: 6. | D82: 통화선도거래이익 | E82: =-SUMIF(FS_map!$H:$H,$D82,FS_map!$M:$M) -> 0 | F82: =-SUMIF(FS_map!$H:$H,$D82,FS_map!$P:$P) -> 0 | G82: =F82*12/9 -> 0 | H82: =SUMIF(WPL_2025YE!$D:$D,$D82,WPL_2025YE!$AI:$AI) -> 0 | I82: =G82-H82 -> 0 | J82: =IFERROR(I82/H82,IF(I82>0,100%,IF(I82=0,0,-100%))) -> 0 | K82: =IF(AND(ABS(I82)>$K$5,ABS(J82)>5%),"O","") | M82: =E82-F82 -> 0 | U82: =SUMIF('PL_DEC.2026'!$D:$D,$D82,'PL_DEC.2026'!$E:$E) -> 0 | V82: =E82-U82 -> 0 | W82: =SUMIF('PL_DEC.2026'!$D:$D,$D82,'PL_DEC.2026'!$L:$L) -> 0 | X82: =F82-W82 -> 0
C83: 7. | D83: 기타수입수수료 | E83: =-SUMIF(FS_map!$H:$H,$D83,FS_map!$M:$M) -> 0 | F83: =-SUMIF(FS_map!$H:$H,$D83,FS_map!$P:$P) -> 0 | G83: =F83*12/9 -> 0 | H83: =SUMIF(WPL_2025YE!$D:$D,$D83,WPL_2025YE!$AI:$AI) -> 0 | I83: =G83-H83 -> 0 | J83: =IFERROR(I83/H83,IF(I83>0,100%,IF(I83=0,0,-100%))) -> 0 | K83: =IF(AND(ABS(I83)>$K$5,ABS(J83)>5%),"O","") | M83: =E83-F83 -> 0 | U83: =SUMIF('PL_DEC.2026'!$D:$D,$D83,'PL_DEC.2026'!$E:$E) -> 0 | V83: =E83-U83 -> 0 | W83: =SUMIF('PL_DEC.2026'!$D:$D,$D83,'PL_DEC.2026'!$L:$L) -> 0 | X83: =F83-W83 -> 0
C84: 8. | D84: 대손충당금환입 | E84: =-SUMIF(FS_map!$H:$H,$D84,FS_map!$M:$M) -> 0 | F84: =-SUMIF(FS_map!$H:$H,$D84,FS_map!$P:$P) -> 0 | G84: =F84*12/9 -> 0 | H84: =SUMIF(WPL_2025YE!$D:$D,$D84,WPL_2025YE!$AI:$AI) -> 0 | I84: =G84-H84 -> 0 | J84: =IFERROR(I84/H84,IF(I84>0,100%,IF(I84=0,0,-100%))) -> 0 | K84: =IF(AND(ABS(I84)>$K$5,ABS(J84)>5%),"O","") | M84: =E84-F84 -> 0 | U84: =SUMIF('PL_DEC.2026'!$D:$D,$D84,'PL_DEC.2026'!$E:$E) -> 0 | V84: =E84-U84 -> 0 | W84: =SUMIF('PL_DEC.2026'!$D:$D,$D84,'PL_DEC.2026'!$L:$L) -> 0 | X84: =F84-W84 -> 0
C85: 9. | D85: 법인세환급액 | E85: =-SUMIF(FS_map!$H:$H,$D85,FS_map!$M:$M) -> 0 | F85: =-SUMIF(FS_map!$H:$H,$D85,FS_map!$P:$P) -> 0 | G85: =F85*12/9 -> 0 | H85: =SUMIF(WPL_2025YE!$D:$D,$D85,WPL_2025YE!$AI:$AI) -> 0 | I85: =G85-H85 -> 0 | J85: =IFERROR(I85/H85,IF(I85>0,100%,IF(I85=0,0,-100%))) -> 0 | K85: =IF(AND(ABS(I85)>$K$5,ABS(J85)>5%),"O","") | M85: =E85-F85 -> 0 | U85: =SUMIF('PL_DEC.2026'!$D:$D,$D85,'PL_DEC.2026'!$E:$E) -> 0 | V85: =E85-U85 -> 0 | W85: =SUMIF('PL_DEC.2026'!$D:$D,$D85,'PL_DEC.2026'!$L:$L) -> 0 | X85: =F85-W85 -> 0
C86: 10. | D86: 마케팅지원금 | E86: =-SUMIF(FS_map!$H:$H,$D86,FS_map!$M:$M) -> 0 | F86: =-SUMIF(FS_map!$H:$H,$D86,FS_map!$P:$P) -> 0 | G86: =F86*12/9 -> 0 | H86: =SUMIF(WPL_2025YE!$D:$D,$D86,WPL_2025YE!$AI:$AI) -> 0 | I86: =G86-H86 -> 0 | J86: =IFERROR(I86/H86,IF(I86>0,100%,IF(I86=0,0,-100%))) -> 0 | K86: =IF(AND(ABS(I86)>$K$5,ABS(J86)>5%),"O","") | M86: =E86-F86 -> 0 | U86: =SUMIF('PL_DEC.2026'!$D:$D,$D86,'PL_DEC.2026'!$E:$E) -> 0 | V86: =E86-U86 -> 0 | W86: =SUMIF('PL_DEC.2026'!$D:$D,$D86,'PL_DEC.2026'!$L:$L) -> 0 | X86: =F86-W86 -> 0
C87: 11. | D87: 잡이익 | E87: =-SUMIF(FS_map!$H:$H,$D87,FS_map!$M:$M) -> 21474711333 | F87: =-SUMIF(FS_map!$H:$H,$D87,FS_map!$P:$P) -> 730375017 | G87: =F87*12/9 -> 973833356 | H87: =SUMIF(WPL_2025YE!$D:$D,$D87,WPL_2025YE!$AI:$AI) -> 18946687440 | I87: =G87-H87 -> -17972854084 | J87: =IFERROR(I87/H87,IF(I87>0,100%,IF(I87=0,0,-100%))) -> -0.94860139 | K87: =IF(AND(ABS(I87)>$K$5,ABS(J87)>5%),"O","") -> O | L87: 9월 누적 7.3억원 (전년 동기 85.6억원 대비 −78.3억원), 전기 연간 189.5억원 1. 전기에는 제미글로 소송 승소에 따른 소송충당부채 환입(법원공탁금 회수) 84억원 등 일회성 이익이 포함됨. 당기 해당 없음 2. CRU(R&D 임상) rebilling 관계사 수익(74250001) 9월 누적 230.5억원 (전년 동기 145.9억원, +84.6억원) 중 207.9억원은 statutory 조정(#2)으로 관련 비용과 상계 → 잡이익 잔액은 로열티수익 9.8억원(Aprovasc·디트로반) 등 3. P16 잡이익 조정(86200400) 차변 25.1억원은 전기말 CRU true-up 미수금(22.6억원)의 역분개 성격으로 추정됨 → 차이 2.5억원 확인 필요 4. 회사 PL_DEC.2026의 statutory 잡이익은 산식 오류로 101백만원 과소 (정산표는 조정분개 기준으로 반영) | M87: =E87-F87 -> 20744336316 | U87: =SUMIF('PL_DEC.2026'!$D:$D,$D87,'PL_DEC.2026'!$E:$E) -> 21474711333 | V87: =E87-U87 -> 0 | W87: =SUMIF('PL_DEC.2026'!$D:$D,$D87,'PL_DEC.2026'!$L:$L) -> 629162757 | X87: =F87-W87 -> 101212260
C88: 12. | D88: 지분법이익 | E88: =-SUMIF(FS_map!$H:$H,$D88,FS_map!$M:$M) -> 0 | F88: =-SUMIF(FS_map!$H:$H,$D88,FS_map!$P:$P) -> 0 | G88: =F88*12/9 -> 0 | H88: =SUMIF(WPL_2025YE!$D:$D,$D88,WPL_2025YE!$AI:$AI) -> 0 | I88: =G88-H88 -> 0 | J88: =IFERROR(I88/H88,IF(I88>0,100%,IF(I88=0,0,-100%))) -> 0 | K88: =IF(AND(ABS(I88)>$K$5,ABS(J88)>5%),"O","") | M88: =E88-F88 -> 0 | U88: =SUMIF('PL_DEC.2026'!$D:$D,$D88,'PL_DEC.2026'!$E:$E) -> 0 | V88: =E88-U88 -> 0 | W88: =SUMIF('PL_DEC.2026'!$D:$D,$D88,'PL_DEC.2026'!$L:$L) -> 0 | X88: =F88-W88 -> 0
C89: 13. | D89: 복구공사이익 | E89: =-SUMIF(FS_map!$H:$H,$D89,FS_map!$M:$M) -> 0 | F89: =-SUMIF(FS_map!$H:$H,$D89,FS_map!$P:$P) -> 0 | G89: =F89*12/9 -> 0 | H89: =SUMIF(WPL_2025YE!$D:$D,$D89,WPL_2025YE!$AI:$AI) -> 0 | I89: =G89-H89 -> 0 | J89: =IFERROR(I89/H89,IF(I89>0,100%,IF(I89=0,0,-100%))) -> 0 | K89: =IF(AND(ABS(I89)>$K$5,ABS(J89)>5%),"O","") | M89: =E89-F89 -> 0 | U89: =SUMIF('PL_DEC.2026'!$D:$D,$D89,'PL_DEC.2026'!$E:$E) -> 0 | V89: =E89-U89 -> 0 | W89: =SUMIF('PL_DEC.2026'!$D:$D,$D89,'PL_DEC.2026'!$L:$L) -> 0 | X89: =F89-W89 -> 0
C90: 14 | D90: 배당금수익 | E90: =-SUMIF(FS_map!$H:$H,$D90,FS_map!$M:$M) -> 0 | F90: =-SUMIF(FS_map!$H:$H,$D90,FS_map!$P:$P) -> 0 | G90: =F90*12/9 -> 0 | H90: =SUMIF(WPL_2025YE!$D:$D,$D90,WPL_2025YE!$AI:$AI) -> 0 | I90: =G90-H90 -> 0 | J90: =IFERROR(I90/H90,IF(I90>0,100%,IF(I90=0,0,-100%))) -> 0 | K90: =IF(AND(ABS(I90)>$K$5,ABS(J90)>5%),"O","") | M90: =E90-F90 -> 0 | U90: =SUMIF('PL_DEC.2026'!$D:$D,$D90,'PL_DEC.2026'!$E:$E) -> 0 | V90: =E90-U90 -> 0 | W90: =SUMIF('PL_DEC.2026'!$D:$D,$D90,'PL_DEC.2026'!$L:$L) -> 0 | X90: =F90-W90 -> 0
C91: VII. 영업외비용 | E91: =SUM(E92:E107) -> 2174644784 | F91: =SUM(F92:F107) -> 2174644784 | G91: =F91*12/9 -> 2.8995264e+09 | H91: =SUM(H92:H107) -> 483100924 | I91: =G91-H91 -> 2.4164255e+09 | J91: =IFERROR(I91/H91,IF(I91>0,100%,IF(I91=0,0,-100%))) -> 5.0019061 | M91: =E91-F91 -> 0 | U91: =SUM(U92:U107) -> 2174644784 | V91: =E91-U91 -> 0 | W91: =SUM(W92:W107) -> 2174644784 | X91: =F91-W91 -> 0
C92: 1. | D92: 이자비용 | E92: =SUMIF(FS_map!$H:$H,$D92,FS_map!$M:$M) -> 149258988 | F92: =SUMIF(FS_map!$H:$H,$D92,FS_map!$P:$P) -> 149258988 | G92: =F92*12/9 -> 199011984 | H92: =SUMIF(WPL_2025YE!$D:$D,$D92,WPL_2025YE!$AI:$AI) -> 92801999 | I92: =G92-H92 -> 106209985 | J92: =IFERROR(I92/H92,IF(I92>0,100%,IF(I92=0,0,-100%))) -> 1.1444795 | K92: =IF(AND(ABS(I92)>$K$5,ABS(J92)>5%),"O","") | L92: 신용한도(credit line) 이자 1.4억원 등. 9월 누적 1.5억원 (전년 동기 1.2억원) | M92: =E92-F92 -> 0 | U92: =SUMIF('PL_DEC.2026'!$D:$D,$D92,'PL_DEC.2026'!$E:$E) -> 149258988 | V92: =E92-U92 -> 0 | W92: =SUMIF('PL_DEC.2026'!$D:$D,$D92,'PL_DEC.2026'!$L:$L) -> 149258988 | X92: =F92-W92 -> 0
C93: 2. | D93: 매출채권매각손실 | E93: =SUMIF(FS_map!$H:$H,$D93,FS_map!$M:$M) -> 0 | F93: =SUMIF(FS_map!$H:$H,$D93,FS_map!$P:$P) -> 0 | G93: =F93*12/9 -> 0 | H93: =SUMIF(WPL_2025YE!$D:$D,$D93,WPL_2025YE!$AI:$AI) -> 0 | I93: =G93-H93 -> 0 | J93: =IFERROR(I93/H93,IF(I93>0,100%,IF(I93=0,0,-100%))) -> 0 | K93: =IF(AND(ABS(I93)>$K$5,ABS(J93)>5%),"O","") | M93: =E93-F93 -> 0 | U93: =SUMIF('PL_DEC.2026'!$D:$D,$D93,'PL_DEC.2026'!$E:$E) -> 0 | V93: =E93-U93 -> 0 | W93: =SUMIF('PL_DEC.2026'!$D:$D,$D93,'PL_DEC.2026'!$L:$L) -> 0 | X93: =F93-W93 -> 0
C94: 3. | D94: 외환차손 | E94: =SUMIF(FS_map!$H:$H,$D94,FS_map!$M:$M) -> -37435248 | F94: =SUMIF(FS_map!$H:$H,$D94,FS_map!$P:$P) -> -37435248 | G94: =F94*12/9 -> -49913664 | H94: =SUMIF(WPL_2025YE!$D:$D,$D94,WPL_2025YE!$AI:$AI) -> 33586551 | I94: =G94-H94 -> -83500215 | J94: =IFERROR(I94/H94,IF(I94>0,100%,IF(I94=0,0,-100%))) -> -2.4861206 | K94: =IF(AND(ABS(I94)>$K$5,ABS(J94)>5%),"O","") | L94: 외환차익(74100000) 7.9억원과 외환차손(74110000) 7.5억원의 순액이 이익 0.4억원이어서 외환차손이 음수로 표시됨 → 전기처럼 외환차익으로 재분류 검토 | M94: =E94-F94 -> 0 | U94: =SUMIF('PL_DEC.2026'!$D:$D,$D94,'PL_DEC.2026'!$E:$E) -> -37435248 | V94: =E94-U94 -> 0 | W94: =SUMIF('PL_DEC.2026'!$D:$D,$D94,'PL_DEC.2026'!$L:$L) -> -37435248 | X94: =F94-W94 -> 0
C95: 4. | D95: 외화환산손실 | E95: =SUMIF(FS_map!$H:$H,$D95,FS_map!$M:$M) -> 0 | F95: =SUMIF(FS_map!$H:$H,$D95,FS_map!$P:$P) -> 0 | G95: =F95*12/9 -> 0 | H95: =SUMIF(WPL_2025YE!$D:$D,$D95,WPL_2025YE!$AI:$AI) -> 0 | I95: =G95-H95 -> 0 | J95: =IFERROR(I95/H95,IF(I95>0,100%,IF(I95=0,0,-100%))) -> 0 | K95: =IF(AND(ABS(I95)>$K$5,ABS(J95)>5%),"O","") | M95: =E95-F95 -> 0 | U95: =SUMIF('PL_DEC.2026'!$D:$D,$D95,'PL_DEC.2026'!$E:$E) -> 0 | V95: =E95-U95 -> 0 | W95: =SUMIF('PL_DEC.2026'!$D:$D,$D95,'PL_DEC.2026'!$L:$L) -> 0 | X95: =F95-W95 -> 0
C96: 5. | D96: 기부금 | E96: =SUMIF(FS_map!$H:$H,$D96,FS_map!$M:$M) -> 290797619 | F96: =SUMIF(FS_map!$H:$H,$D96,FS_map!$P:$P) -> 290797619 | G96: =F96*12/9 -> 3.8773016e+08 | H96: =SUMIF(WPL_2025YE!$D:$D,$D96,WPL_2025YE!$AI:$AI) -> 259053818 | I96: =G96-H96 -> 1.2867634e+08 | J96: =IFERROR(I96/H96,IF(I96>0,100%,IF(I96=0,0,-100%))) -> 0.49671663 | K96: =IF(AND(ABS(I96)>$K$5,ABS(J96)>5%),"O","") | L96: 9월 누적 2.9억원 (전년 동기 2.1억원) | M96: =E96-F96 -> 0 | U96: =SUMIF('PL_DEC.2026'!$D:$D,$D96,'PL_DEC.2026'!$E:$E) -> 290797619 | V96: =E96-U96 -> 0 | W96: =SUMIF('PL_DEC.2026'!$D:$D,$D96,'PL_DEC.2026'!$L:$L) -> 290797619 | X96: =F96-W96 -> 0
C97: 6. | D97: 퇴직위로금 | E97: =SUMIF(FS_map!$H:$H,$D97,FS_map!$M:$M) -> 0 | F97: =SUMIF(FS_map!$H:$H,$D97,FS_map!$P:$P) -> 0 | G97: =F97*12/9 -> 0 | H97: =SUMIF(WPL_2025YE!$D:$D,$D97,WPL_2025YE!$AI:$AI) -> 0 | I97: =G97-H97 -> 0 | J97: =IFERROR(I97/H97,IF(I97>0,100%,IF(I97=0,0,-100%))) -> 0 | K97: =IF(AND(ABS(I97)>$K$5,ABS(J97)>5%),"O","") | M97: =E97-F97 -> 0 | U97: =SUMIF('PL_DEC.2026'!$D:$D,$D97,'PL_DEC.2026'!$E:$E) -> 0 | V97: =E97-U97 -> 0 | W97: =SUMIF('PL_DEC.2026'!$D:$D,$D97,'PL_DEC.2026'!$L:$L) -> 0 | X97: =F97-W97 -> 0
C98: 7. | D98: 투자자산처분손실 | E98: =SUMIF(FS_map!$H:$H,$D98,FS_map!$M:$M) -> 1372357643 | F98: =SUMIF(FS_map!$H:$H,$D98,FS_map!$P:$P) -> 1372357643 | G98: =F98*12/9 -> 1.8298102e+09 | H98: =SUMIF(WPL_2025YE!$D:$D,$D98,WPL_2025YE!$AI:$AI) -> 0 | I98: =G98-H98 -> 1.8298102e+09 | J98: =IFERROR(I98/H98,IF(I98>0,100%,IF(I98=0,0,-100%))) -> 1 | K98: =IF(AND(ABS(I98)>$K$5,ABS(J98)>5%),"O","") | L98: Taxotere 글로벌 divestment에 따른 처분손실 13.7억원 (회사: EUR 797천) 1. 처분대가 18.7억원 (EUR 1,088천) − 양도 재고자산 장부가 32.5억원 (EUR 1,885천) 2. 관련 법인세 효과 −3.3억원 3. 재고자산(사업) 양도에 따른 손실이므로 K-GAAP 계정분류(투자자산처분손실 → 사업양도손실 등) 검토 필요 ※ 전년 동기 −74.3억원은 SMIP 주식 처분이익(SMIP → SA 합병) | M98: =E98-F98 -> 0 | U98: =SUMIF('PL_DEC.2026'!$D:$D,$D98,'PL_DEC.2026'!$E:$E) -> 1372357643 | V98: =E98-U98 -> 0 | W98: =SUMIF('PL_DEC.2026'!$D:$D,$D98,'PL_DEC.2026'!$L:$L) -> 1372357643 | X98: =F98-W98 -> 0
C99: 8. | D99: 유형자산처분손실 | E99: =SUMIF(FS_map!$H:$H,$D99,FS_map!$M:$M) -> 0 | F99: =SUMIF(FS_map!$H:$H,$D99,FS_map!$P:$P) -> 0 | G99: =F99*12/9 -> 0 | H99: =SUMIF(WPL_2025YE!$D:$D,$D99,WPL_2025YE!$AI:$AI) -> 0 | I99: =G99-H99 -> 0 | J99: =IFERROR(I99/H99,IF(I99>0,100%,IF(I99=0,0,-100%))) -> 0 | K99: =IF(AND(ABS(I99)>$K$5,ABS(J99)>5%),"O","") | M99: =E99-F99 -> 0 | U99: =SUMIF('PL_DEC.2026'!$D:$D,$D99,'PL_DEC.2026'!$E:$E) -> 0 | V99: =E99-U99 -> 0 | W99: =SUMIF('PL_DEC.2026'!$D:$D,$D99,'PL_DEC.2026'!$L:$L) -> 0 | X99: =F99-W99 -> 0
C100: 9. | D100: 무형자산감액손실 | E100: =SUMIF(FS_map!$H:$H,$D100,FS_map!$M:$M) -> 0 | F100: =SUMIF(FS_map!$H:$H,$D100,FS_map!$P:$P) -> 0 | G100: =F100*12/9 -> 0 | H100: =SUMIF(WPL_2025YE!$D:$D,$D100,WPL_2025YE!$AI:$AI) -> 0 | I100: =G100-H100 -> 0 | J100: =IFERROR(I100/H100,IF(I100>0,100%,IF(I100=0,0,-100%))) -> 0 | K100: =IF(AND(ABS(I100)>$K$5,ABS(J100)>5%),"O","") | M100: =E100-F100 -> 0 | U100: =SUMIF('PL_DEC.2026'!$D:$D,$D100,'PL_DEC.2026'!$E:$E) -> 0 | V100: =E100-U100 -> 0 | W100: =SUMIF('PL_DEC.2026'!$D:$D,$D100,'PL_DEC.2026'!$L:$L) -> 0 | X100: =F100-W100 -> 0
C101: 10. | D101: 무형자산처분손실 | E101: =SUMIF(FS_map!$H:$H,$D101,FS_map!$M:$M) -> 0 | F101: =SUMIF(FS_map!$H:$H,$D101,FS_map!$P:$P) -> 0 | G101: =F101*12/9 -> 0 | H101: =SUMIF(WPL_2025YE!$D:$D,$D101,WPL_2025YE!$AI:$AI) -> 0 | I101: =G101-H101 -> 0 | J101: =IFERROR(I101/H101,IF(I101>0,100%,IF(I101=0,0,-100%))) -> 0 | K101: =IF(AND(ABS(I101)>$K$5,ABS(J101)>5%),"O","") | M101: =E101-F101 -> 0 | U101: =SUMIF('PL_DEC.2026'!$D:$D,$D101,'PL_DEC.2026'!$E:$E) -> 0 | V101: =E101-U101 -> 0 | W101: =SUMIF('PL_DEC.2026'!$D:$D,$D101,'PL_DEC.2026'!$L:$L) -> 0 | X101: =F101-W101 -> 0
C102: 11. | D102: 법인세추납액 | E102: =SUMIF(FS_map!$H:$H,$D102,FS_map!$M:$M) -> 0 | F102: =SUMIF(FS_map!$H:$H,$D102,FS_map!$P:$P) -> 0 | G102: =F102*12/9 -> 0 | H102: =SUMIF(WPL_2025YE!$D:$D,$D102,WPL_2025YE!$AI:$AI) -> 0 | I102: =G102-H102 -> 0 | J102: =IFERROR(I102/H102,IF(I102>0,100%,IF(I102=0,0,-100%))) -> 0 | K102: =IF(AND(ABS(I102)>$K$5,ABS(J102)>5%),"O","") | M102: =E102-F102 -> 0 | U102: =SUMIF('PL_DEC.2026'!$D:$D,$D102,'PL_DEC.2026'!$E:$E) -> 0 | V102: =E102-U102 -> 0 | W102: =SUMIF('PL_DEC.2026'!$D:$D,$D102,'PL_DEC.2026'!$L:$L) -> 0 | X102: =F102-W102 -> 0
...

Sheet FS_map
D2: SAP GL | E2: Description | F2: Type | G2: Type | H2: Local Class(결산보고서) | I2: English | J2: (01.2026-09.2026) SAP | K2: Debit | L2: Credit | M2: 수정전 | N2: Debit | O2: Credit | P2: 수정후 | Q2: 2025.12 SAP(YTD) | R2: Source | S2: 회사 매핑 (BSPL2026 M열) | T2: 매핑 check
D3: 10100082 | E3: Lands and Buildings -Right of Use -Man | F3: BS | G3: 자산 | H3: 구축물 | I3: Lands and Buildings -Right of use (Man) | J3: =IFERROR(VLOOKUP(VALUE($D3),BSPL2026!$B:$Z,25,FALSE()),0) -> 12060074810 | M3: =J3+K3-L3 -> 12060074810 | N3: =SUMIF('statutory adj_2026 조정분개'!$S:$S,$D3,'statutory adj_2026 조정분개'!$K:$K) -> 0 | O3: =SUMIF('statutory adj_2026 조정분개'!$S:$S,$D3,'statutory adj_2026 조정분개'!$L:$L) -> 0 | P3: =M3+N3-O3 -> 12060074810 | Q3: =IFERROR(VLOOKUP(VALUE($D3),BSPL2026!$B:$Q,16,FALSE()),0) -> 12060074810 | R3: from BSPL2026 | S3: =IFERROR(VLOOKUP(VALUE($D3),BSPL2026!$B:$M,12,FALSE()),"") -> 구축물 | T3: =IF(OR(S3="",S3=0,LEFT(S3,5)="(원본오류"),"",IF(S3=H3,"","매핑차이"))
D4: 10100083 | E4: Depreciation Land and Build -Right of Use -Man | F4: BS | G4: 자산 | H4: 감가상각누계액-구축물 | I4: Acc.dep.Land and Build.-Right (Man) | J4: =IFERROR(VLOOKUP(VALUE($D4),BSPL2026!$B:$Z,25,FALSE()),0) -> -11842919020 | M4: =J4+K4-L4 -> -11842919020 | N4: =SUMIF('statutory adj_2026 조정분개'!$S:$S,$D4,'statutory adj_2026 조정분개'!$K:$K) -> 0 | O4: =SUMIF('statutory adj_2026 조정분개'!$S:$S,$D4,'statutory adj_2026 조정분개'!$L:$L) -> 0 | P4: =M4+N4-O4 -> -11842919020 | Q4: =IFERROR(VLOOKUP(VALUE($D4),BSPL2026!$B:$Q,16,FALSE()),0) -> -10865717938 | R4: from BSPL2026 | S4: =IFERROR(VLOOKUP(VALUE($D4),BSPL2026!$B:$M,12,FALSE()),"") -> 감가상각누계액-구축물 | T4: =IF(OR(S4="",S4=0,LEFT(S4,5)="(원본오류"),"",IF(S4=H4,"","매핑차이"))
D5: 10100850 | E5: Buildings -(A) Rec | F5: BS | G5: 자산 | H5: 구축물 | I5: Structures | J5: =IFERROR(VLOOKUP(VALUE($D5),BSPL2026!$B:$Z,25,FALSE()),0) -> 239169200 | M5: =J5+K5-L5 -> 239169200 | N5: =SUMIF('statutory adj_2026 조정분개'!$S:$S,$D5,'statutory adj_2026 조정분개'!$K:$K) -> 0 | O5: =SUMIF('statutory adj_2026 조정분개'!$S:$S,$D5,'statutory adj_2026 조정분개'!$L:$L) -> 0 | P5: =M5+N5-O5 -> 239169200 | Q5: =IFERROR(VLOOKUP(VALUE($D5),BSPL2026!$B:$Q,16,FALSE()),0) -> 239169200 | R5: from BSPL2026 | S5: =IFERROR(VLOOKUP(VALUE($D5),BSPL2026!$B:$M,12,FALSE()),"") -> 구축물 | T5: =IF(OR(S5="",S5=0,LEFT(S5,5)="(원본오류"),"",IF(S5=H5,"","매핑차이"))
D6: 10150000 | E6: Buildings -Leasehold Improvements -(A) Rec | F6: BS | G6: 자산 | H6: 구축물 | I6: Depreciation Buildings -Leasehold Improve -(A) Rec | J6: =IFERROR(VLOOKUP(VALUE($D6),BSPL2026!$B:$Z,25,FALSE()),0) -> 1304901001 | M6: =J6+K6-L6 -> 1304901001 | N6: =SUMIF('statutory adj_2026 조정분개'!$S:$S,$D6,'statutory adj_2026 조정분개'!$K:$K) -> 0 | O6: =SUMIF('statutory adj_2026 조정분개'!$S:$S,$D6,'statutory adj_2026 조정분개'!$L:$L) -> 0 | P6: =M6+N6-O6 -> 1304901001 | Q6: =IFERROR(VLOOKUP(VALUE($D6),BSPL2026!$B:$Q,16,FALSE()),0) -> 1304901001 | R6: from BSPL2026 | S6: =IFERROR(VLOOKUP(VALUE($D6),BSPL2026!$B:$M,12,FALSE()),"") -> 구축물 | T6: =IF(OR(S6="",S6=0,LEFT(S6,5)="(원본오류"),"",IF(S6=H6,"","매핑차이"))
D7: 10200000 | E7: Machinery and Equipment -(A) Rec | F7: BS | G7: 자산 | H7: 기계장치 | I7: Plant & Machinery | J7: =IFERROR(VLOOKUP(VALUE($D7),BSPL2026!$B:$Z,25,FALSE()),0) -> 1434004742 | M7: =J7+K7-L7 -> 1434004742 | N7: =SUMIF('statutory adj_2026 조정분개'!$S:$S,$D7,'statutory adj_2026 조정분개'!$K:$K) -> 0 | O7: =SUMIF('statutory adj_2026 조정분개'!$S:$S,$D7,'statutory adj_2026 조정분개'!$L:$L) -> 485029742 | P7: =M7+N7-O7 -> 948975000 | Q7: =IFERROR(VLOOKUP(VALUE($D7),BSPL2026!$B:$Q,16,FALSE()),0) -> 1434004742 | R7: from BSPL2026 | S7: =IFERROR(VLOOKUP(VALUE($D7),BSPL2026!$B:$M,12,FALSE()),"") -> 기계장치 | T7: =IF(OR(S7="",S7=0,LEFT(S7,5)="(원본오류"),"",IF(S7=H7,"","매핑차이"))
D8: 10200921 | E8: Samples -Manual | F8: BS | G8: 자산 | H8: 상품 | I8: Samples -Manual | J8: =IFERROR(VLOOKUP(VALUE($D8),BSPL2026!$B:$Z,25,FALSE()),0) -> 0 | M8: =J8+K8-L8 -> 0 | N8: =SUMIF('statutory adj_2026 조정분개'!$S:$S,$D8,'statutory adj_2026 조정분개'!$K:$K) -> 0 | O8: =SUMIF('statutory adj_2026 조정분개'!$S:$S,$D8,'statutory adj_2026 조정분개'!$L:$L) -> 0 | P8: =M8+N8-O8 -> 0 | Q8: =IFERROR(VLOOKUP(VALUE($D8),BSPL2026!$B:$Q,16,FALSE()),0) -> 0 | R8: from BSPL2026 | S8: =IFERROR(VLOOKUP(VALUE($D8),BSPL2026!$B:$M,12,FALSE()),"") -> 상품 | T8: =IF(OR(S8="",S8=0,LEFT(S8,5)="(원본오류"),"",IF(S8=H8,"","매핑차이"))
D9: 10300000 | E9: Other FA -Furniture Fixtures & Office Equ -(A) Rec | F9: BS | G9: 자산 | H9: 집기비품 | I9: Furniture/Fittings/Office Equipment | J9: =IFERROR(VLOOKUP(VALUE($D9),BSPL2026!$B:$Z,25,FALSE()),0) -> 350199634 | M9: =J9+K9-L9 -> 350199634 | N9: =SUMIF('statutory adj_2026 조정분개'!$S:$S,$D9,'statutory adj_2026 조정분개'!$K:$K) -> 0 | O9: =SUMIF('statutory adj_2026 조정분개'!$S:$S,$D9,'statutory adj_2026 조정분개'!$L:$L) -> 0 | P9: =M9+N9-O9 -> 350199634 | Q9: =IFERROR(VLOOKUP(VALUE($D9),BSPL2026!$B:$Q,16,FALSE()),0) -> 350199634 | R9: from BSPL2026 | S9: =IFERROR(VLOOKUP(VALUE($D9),BSPL2026!$B:$M,12,FALSE()),"") -> 집기비품 | T9: =IF(OR(S9="",S9=0,LEFT(S9,5)="(원본오류"),"",IF(S9=H9,"","매핑차이"))
D10: 10300850 | E10: Other Fixed Assets -(A) Rec | F10: BS | G10: 자산 | H10: 공구와기구 | I10: Other Tools and Furniture | J10: =IFERROR(VLOOKUP(VALUE($D10),BSPL2026!$B:$Z,25,FALSE()),0) -> 42938000 | M10: =J10+K10-L10 -> 42938000 | N10: =SUMIF('statutory adj_2026 조정분개'!$S:$S,$D10,'statutory adj_2026 조정분개'!$K:$K) -> 485029742 | O10: =SUMIF('statutory adj_2026 조정분개'!$S:$S,$D10,'statutory adj_2026 조정분개'!$L:$L) -> 0 | P10: =M10+N10-O10 -> 527967742 | Q10: =IFERROR(VLOOKUP(VALUE($D10),BSPL2026!$B:$Q,16,FALSE()),0) -> 42938000 | R10: from BSPL2026 | S10: =IFERROR(VLOOKUP(VALUE($D10),BSPL2026!$B:$M,12,FALSE()),"") -> 공구와기구 | T10: =IF(OR(S10="",S10=0,LEFT(S10,5)="(원본오류"),"",IF(S10=H10,"","매핑차이"))
D11: 10350000 | E11: Other FA -IT Equipment -(A) Rec | F11: BS | G11: 자산 | H11: 집기비품 | I11: EDP Equipment | J11: =IFERROR(VLOOKUP(VALUE($D11),BSPL2026!$B:$Z,25,FALSE()),0) -> 1369225145 | M11: =J11+K11-L11 -> 1369225145 | N11: =SUMIF('statutory adj_2026 조정분개'!$S:$S,$D11,'statutory adj_2026 조정분개'!$K:$K) -> 0 | O11: =SUMIF('statutory adj_2026 조정분개'!$S:$S,$D11,'statutory adj_2026 조정분개'!$L:$L) -> 0 | P11: =M11+N11-O11 -> 1369225145 | Q11: =IFERROR(VLOOKUP(VALUE($D11),BSPL2026!$B:$Q,16,FALSE()),0) -> 1282738705 | R11: from BSPL2026 | S11: =IFERROR(VLOOKUP(VALUE($D11),BSPL2026!$B:$M,12,FALSE()),"") -> 집기비품 | T11: =IF(OR(S11="",S11=0,LEFT(S11,5)="(원본오류"),"",IF(S11=H11,"","매핑차이"))
D12: 10350303 | E12: Other Fixed Assets -(A) Rec | F12: BS | G12: 자산 | H12: 공구와기구 | I12: Depreciation Other Fixed Assets -(A) Rec | J12: =IFERROR(VLOOKUP(VALUE($D12),BSPL2026!$B:$Z,25,FALSE()),0) -> 34046016 | M12: =J12+K12-L12 -> 34046016 | N12: =SUMIF('statutory adj_2026 조정분개'!$S:$S,$D12,'statutory adj_2026 조정분개'!$K:$K) -> 0 | O12: =SUMIF('statutory adj_2026 조정분개'!$S:$S,$D12,'statutory adj_2026 조정분개'!$L:$L) -> 0 | P12: =M12+N12-O12 -> 34046016 | Q12: =IFERROR(VLOOKUP(VALUE($D12),BSPL2026!$B:$Q,16,FALSE()),0) -> 34046016 | R12: from BSPL2026 | S12: =IFERROR(VLOOKUP(VALUE($D12),BSPL2026!$B:$M,12,FALSE()),"") -> 공구와기구 | T12: =IF(OR(S12="",S12=0,LEFT(S12,5)="(원본오류"),"",IF(S12=H12,"","매핑차이"))
D13: 10550400 | E13: In Progress -Other -IT Equipment -(A) | F13: BS | G13: 자산 | H13: 소프트웨어 | I13: In Progress -Other -IT Equipment -(A) | J13: =IFERROR(VLOOKUP(VALUE($D13),BSPL2026!$B:$Z,25,FALSE()),0) -> 22468609 | M13: =J13+K13-L13 -> 22468609 | N13: =SUMIF('statutory adj_2026 조정분개'!$S:$S,$D13,'statutory adj_2026 조정분개'!$K:$K) -> 0 | O13: =SUMIF('statutory adj_2026 조정분개'!$S:$S,$D13,'statutory adj_2026 조정분개'!$L:$L) -> 0 | P13: =M13+N13-O13 -> 22468609 | Q13: =IFERROR(VLOOKUP(VALUE($D13),BSPL2026!$B:$Q,16,FALSE()),0) -> 0 | R13: from BSPL2026 | S13: =IFERROR(VLOOKUP(VALUE($D13),BSPL2026!$B:$M,12,FALSE()),"") -> 소프트웨어 | T13: =IF(OR(S13="",S13=0,LEFT(S13,5)="(원본오류"),"",IF(S13=H13,"","매핑차이"))
D14: 10550900 | E14: In Progress -Buildings -(A) Rec | F14: BS | G14: 자산 | H14: 건설중인자산 | I14: Const.in Process | J14: =IFERROR(VLOOKUP(VALUE($D14),BSPL2026!$B:$Z,25,FALSE()),0) -> 51562836 | M14: =J14+K14-L14 -> 51562836 | N14: =SUMIF('statutory adj_2026 조정분개'!$S:$S,$D14,'statutory adj_2026 조정분개'!$K:$K) -> 0 | O14: =SUMIF('statutory adj_2026 조정분개'!$S:$S,$D14,'statutory adj_2026 조정분개'!$L:$L) -> 0 | P14: =M14+N14-O14 -> 51562836 | Q14: =IFERROR(VLOOKUP(VALUE($D14),BSPL2026!$B:$Q,16,FALSE()),0) -> 8237836 | R14: from BSPL2026 | S14: =IFERROR(VLOOKUP(VALUE($D14),BSPL2026!$B:$M,12,FALSE()),"") -> 건설중인자산 | T14: =IF(OR(S14="",S14=0,LEFT(S14,5)="(원본오류"),"",IF(S14=H14,"","매핑차이"))
... D444: 반품충당금비유동 | E444: 반품충당금(비유동) - statutory reclass 가상계정 | F444: BS | G444: 부채 | H444: 반품충당금 | I444: Provision for sales return (Non-current) | J444: =IFERROR(VLOOKUP(VALUE($D444),BSPL2026!$B:$Z,25,FALSE()),0) -> 0 | M444: =J444+K444-L444 -> 0 | N444: =SUMIF('statutory adj_2026 조정분개'!$S:$S,$D444,'statutory adj_2026 조정분개'!$K:$K) -> 0 | O444: =SUMIF('statutory adj_2026 조정분개'!$S:$S,$D444,'statutory adj_2026 조정분개'!$L:$L) -> 646256500 | P444: =M444+N444-O444 -> -646256500 | Q444: =IFERROR(VLOOKUP(VALUE($D444),BSPL2026!$B:$Q,16,FALSE()),0) -> 0 | R444: manual (statutory adj #3) | S444: =IFERROR(VLOOKUP(VALUE($D444),BSPL2026!$B:$M,12,FALSE()),"") | T444: =IF(OR(S444="",S444=0,LEFT(S444,5)="(원본오류"),"",IF(S444=H444,"","매핑차이"))
D445: Total | J445: =SUM(J3:J444) -> 0 | K445: =SUM(K3:K444) -> 0 | L445: =SUM(L3:L444) -> 0 | M445: =SUM(M3:M444) -> 0 | N445: =SUM(N3:N444) -> 36539768561 | O445: =SUM(O3:O444) -> 36539768561 | P445: =SUM(P3:P444) -> 0 | Q445: =SUM(Q3:Q444) -> 4
D446: check: 조정분개 반영대상 합계(S열 연결분) | N446: =N445-SUMPRODUCT(('statutory adj_2026 조정분개'!$S$7:$S$77<>"")*'statutory adj_2026 조정분개'!$K$7:$K$77) -> 0 | O446: =O445-SUMPRODUCT(('statutory adj_2026 조정분개'!$S$7:$S$77<>"")*'statutory adj_2026 조정분개'!$L$7:$L$77) -> 0
D447: check: 조정분개 전체 합계 대비(부가세 9원 미반영분) | N447: =N445-'statutory adj_2026 조정분개'!K78 -> -9 | O447: =O445-'statutory adj_2026 조정분개'!L78 -> -9
I449: BS | J449: =SUMIF($F$3:$F$444,I449,$J$3:$J$444) -> 49288887022 | O449: BS | P449: =SUMIF($F$3:$F$444,O449,$P$3:$P$444) -> 49288887022
I450: PL | J450: =SUMIF($F$3:$F$444,I450,$J$3:$J$444) -> -49288887022 | O450: PL | P450: =SUMIF($F$3:$F$444,O450,$P$3:$P$444) -> -49288887022
D452: 매핑차이 건수 | J452: =COUNTIF($T$3:$T$444,"매핑차이") -> 1
D453: 가계정(GR/IR) 잔액 – 0이어야 함 | J453: =SUMIF($H$3:$H$444,"가계정",$M$3:$M$444) -> 0
D454: BS_KO/P&L_KO 미집계 FS과목 건수 – 0이어야 함 | J454: =SUMPRODUCT(--($H$3:$H$444<>"가계정"),--($H$3:$H$444<>"제품매출원가"),--($H$3:$H$444<>"판매 및 일반관리비 대체"),--ISNA(MATCH($H$3:$H$444,BS_KO!$D$1:$D$130,0)),--ISNA(MATCH($H$3:$H$444,'P&L_KO'!$D$1:$D$120,0))) -> 0

Sheet statutory adj_2026 조정분개
Q1: 계정대체
I2: Summary of Statutory adjustment (2026)
P3: - 이익 / + 손실
C5: Current year effect adjustment - NOT BOOKED | H5: P16 ADJ
A6: SAP BOOKED? 2025.16 | B6: Reversal | F6: BSPL | G6: GL account | H6: GL account | K6: DR | L6: CR | M6: Asset | N6: Liability | O6: Equity | P6: P&L | S6: FS_map 연결 GL | T6: 비고(정산표 반영)
C7: 1 | D7: GL reclassification (보증금 중 회원권 구분 대체) | F7: BS | G7: 15800870 | H7: 86158008 | I7: 기타투자자산 | K7: 30000000 | M7: =++K7 -> 30000000 | S7: =IF(ISNUMBER(MATCH(G7&"",FS_map!$D:$D,0)),G7&"",IF(H7="","",H7&"")) -> 86158008 | T7: SAP GL 15800870 미존재 → P16 GL 86158008(기타의 투자자산) 사용
F8: BS | G8: 15800853 | H8: 86260033 | J8: 보증금 | L8: 30000000 | M8: =++-L8 -> -30000000 | S8: =IF(ISNUMBER(MATCH(G8&"",FS_map!$D:$D,0)),G8&"",IF(H8="","",H8&"")) -> 15800853
C11: 2 | D11: GL reclassification (CRU rebilling 비용차감대체) | F11: PL | G11: 74250001 | H11: 86200400 | I11: 잡이익 | K11: 20794942446 | P11: =++K11 -> 20794942446 | S11: =IF(ISNUMBER(MATCH(G11&"",FS_map!$D:$D,0)),G11&"",IF(H11="","",H11&"")) -> 74250001
F12: PL | G12: 86000300 | H12: 86000300 | J12: 급여 | L12: 2369648232 | P12: =++-L12 -> -2369648232 | S12: =IF(ISNUMBER(MATCH(G12&"",FS_map!$D:$D,0)),G12&"",IF(H12="","",H12&"")) -> 86000300
F13: PL | G13: 86000004 | H13: 86000004 | J13: 복리후생비 | L13: 155357637 | P13: =++-L13 -> -155357637 | S13: =IF(ISNUMBER(MATCH(G13&"",FS_map!$D:$D,0)),G13&"",IF(H13="","",H13&"")) -> 86000004
F14: PL | G14: 86400910 | H14: 86400910 | J14: 성과급여 | L14: 333409964 | P14: =++-L14 -> -333409964 | S14: =IF(ISNUMBER(MATCH(G14&"",FS_map!$D:$D,0)),G14&"",IF(H14="","",H14&"")) -> 86400910
F15: PL | G15: 86100747 | H15: 86100747 | J15: 퇴직급여 | L15: 349405261 | P15: =++-L15 -> -349405261 | S15: =IF(ISNUMBER(MATCH(G15&"",FS_map!$D:$D,0)),G15&"",IF(H15="","",H15&"")) -> 86100747
F16: PL | G16: 86000400 | H16: 86000400 | J16: 교육훈련비 | L16: 6474004 | P16: =++-L16 -> -6474004 | S16: =IF(ISNUMBER(MATCH(G16&"",FS_map!$D:$D,0)),G16&"",IF(H16="","",H16&"")) -> 86000400
F17: PL | G17: 86073501 | H17: 86073501 | J17: 임상증례조사비 | L17: 13314198758 | P17: =++-L17 -> -13314198758 | S17: =IF(ISNUMBER(MATCH(G17&"",FS_map!$D:$D,0)),G17&"",IF(H17="","",H17&"")) -> 86073501
F18: PL | G18: 86514001 | H18: 86514001 | J18: 광고선전비 | L18: 7481129 | P18: =++-L18 -> -7481129 | S18: =IF(ISNUMBER(MATCH(G18&"",FS_map!$D:$D,0)),G18&"",IF(H18="","",H18&"")) -> 86514001
F19: PL | G19: 86000006 | H19: 86000006 | J19: 여비교통비 | L19: 128225390 | P19: =++-L19 -> -128225390 | S19: =IF(ISNUMBER(MATCH(G19&"",FS_map!$D:$D,0)),G19&"",IF(H19="","",H19&"")) -> 86000006
F20: PL | G20: 86290000 | H20: 86290000 | J20: 지급수수료 | L20: 61682684 | P20: =++-L20 -> -61682684 | S20: =IF(ISNUMBER(MATCH(G20&"",FS_map!$D:$D,0)),G20&"",IF(H20="","",H20&"")) -> 86290000
F21: PL | G21: 86100925 | H21: 86100925 | J21: 보험료 | L21: 3977948983 | P21: =++-L21 -> -3977948983 | S21: =IF(ISNUMBER(MATCH(G21&"",FS_map!$D:$D,0)),G21&"",IF(H21="","",H21&"")) -> 86100925
F22: PL | G22: 86900000 | H22: 86900000 | J22: 통신비 | L22: 15020622 | P22: =++-L22 -> -15020622 | S22: =IF(ISNUMBER(MATCH(G22&"",FS_map!$D:$D,0)),G22&"",IF(H22="","",H22&"")) -> 86900000
F23: PL | G23: 86300510 | H23: 86300510 | J23: 소모품비 | L23: 17966376 | P23: =++-L23 -> -17966376 | S23: =IF(ISNUMBER(MATCH(G23&"",FS_map!$D:$D,0)),G23&"",IF(H23="","",H23&"")) -> 86300510
... F26: PL | G26: 86200400 | H26: 86200400 | J26: 잡이익 | L26: 50606130 | P26: =++-L26 -> -50606130 | S26: =IF(ISNUMBER(MATCH(G26&"",FS_map!$D:$D,0)),G26&"",IF(H26="","",H26&"")) -> 86200400
C28: 3 | D28: GL reclassification (반품충당금 유동->비 유동대체) | F28: BS | G28: 38010000 | H28: 86380100 | I28: 반품충당금유동 | K28: 646256500 | N28: =++K28 -> 646256500 | S28: =IF(ISNUMBER(MATCH(G28&"",FS_map!$D:$D,0)),G28&"",IF(H28="","",H28&"")) -> 38010000
F29: BS | G29: 반품충당금비유동 | H29: 86380100 | J29: 반품충당금비유동 | L29: =++K28 -> 646256500 | N29: =++-L29 -> -646256500 | S29: =IF(ISNUMBER(MATCH(G29&"",FS_map!$D:$D,0)),G29&"",IF(H29="","",H29&"")) -> 반품충당금비유동 | T29: FS_map 가상계정 "반품충당금비유동" 사용
C31: 5 | D31: GL reclass GTN 미지급비용 부채계상에서 매출채권에서 직접차감 | F31: BS | G31: 42910850 | H31: 86429108 | I31: 미지급비용 | K31: 758423387 | N31: =++K31 -> 758423387 | Q31: 미지급비용-미지급에누리 | S31: =IF(ISNUMBER(MATCH(G31&"",FS_map!$D:$D,0)),G31&"",IF(H31="","",H31&"")) -> 42910850
F32: BS | G32: 42910852 | H32: 86429108 | I32: 미지급비용 | K32: 10532431629 | N32: =++K32 -> 10532431629 | Q32: 미지급비용-미지급에누리 | S32: =IF(ISNUMBER(MATCH(G32&"",FS_map!$D:$D,0)),G32&"",IF(H32="","",H32&"")) -> 42910852
F33: BS | G33: 42910853 | H33: 86429108 | I33: 미지급비용 | K33: 1124955108 | N33: =++K33 -> 1124955108 | Q33: 미지급비용-미지급에누리 | S33: =IF(ISNUMBER(MATCH(G33&"",FS_map!$D:$D,0)),G33&"",IF(H33="","",H33&"")) -> 42910853
F34: BS | G34: 24000000 | H34: 86240007 | J34: 매출채권 | L34: =++K31+K32+K33 -> 12415810124 | M34: =++-L34 -> -12415810124 | Q34: 외상매출금-내수일반 | S34: =IF(ISNUMBER(MATCH(G34&"",FS_map!$D:$D,0)),G34&"",IF(H34="","",H34&"")) -> 24000000
C36: 6 | D36: GL reclassification (국민연금전환금 미수금 → 선급금) | F36: BS | G36: 26650000 | H36: 86260008 | I36: 선급금 | K36: 0 | M36: =++K36 -> 0 | S36: =IF(ISNUMBER(MATCH(G36&"",FS_map!$D:$D,0)),G36&"",IF(H36="","",H36&"")) -> 26650000
F37: BS | G37: 16350702 | H37: 86260033 | J37: Other receivables for employees | L37: =++K36 -> 0 | N37: =++-L37 -> 0 | S37: =IF(ISNUMBER(MATCH(G37&"",FS_map!$D:$D,0)),G37&"",IF(H37="","",H37&"")) -> 16350702
C40: 7 | D40: GL reclassification (기계장치 → 공기구비품_집기비품 대체) | F40: BS | G40: 10200000 | H40: 86102007 | I40: 기계장치 | L40: 485029742 | M40: =++-L40 -> -485029742 | S40: =IF(ISNUMBER(MATCH(G40&"",FS_map!$D:$D,0)),G40&"",IF(H40="","",H40&"")) -> 10200000
F41: BS | G41: 11200000 | H41: 86112007 | I41: 감가상각누계액-기계장치 | K41: 422529742 | M41: =++K41 -> 422529742 | S41: =IF(ISNUMBER(MATCH(G41&"",FS_map!$D:$D,0)),G41&"",IF(H41="","",H41&"")) -> 11200000
F42: BS | G42: 10300850 | H42: 86104100 | I42: 공구와기구 | K42: =++L40 -> 485029742 | M42: =++K42 -> 485029742 | S42: =IF(ISNUMBER(MATCH(G42&"",FS_map!$D:$D,0)),G42&"",IF(H42="","",H42&"")) -> 10300850
F43: BS | G43: 11300850 | H43: 86111500 | I43: 감가상각누계액-공구와기구 | L43: =++K41 -> 422529742 | M43: =++-L43 -> -422529742 | S43: =IF(ISNUMBER(MATCH(G43&"",FS_map!$D:$D,0)),G43&"",IF(H43="","",H43&"")) -> 11300850
C45: 8 | D45: GL reclassification (미지급비용 → 예수금) | F45: BS | G45: 42910000 | I45: 미지급비용 | L45: 612260090 | N45: =-L45 -> -612260090 | S45: =IF(ISNUMBER(MATCH(G45&"",FS_map!$D:$D,0)),G45&"",IF(H45="","",H45&"")) -> 42910000
D46: social security liab - 그룹리포팅과 SAP 매핑차이로 인한 월말 reclass | F46: BS | G46: 40000012 | I46: 미지급금 | K46: =L45 -> 612260090 | N46: =K46 -> 612260090 | S46: =IF(ISNUMBER(MATCH(G46&"",FS_map!$D:$D,0)),G46&"",IF(H46="","",H46&"")) -> 40000012
A49: BOOKED P16 | B49: 2026.02 | C49: =C45+1 -> 9 | D49: 205년 CRU rebilling True-up (2월에 확정) | F49: PL | G49: 74250001 | H49: 86200400 | I49: 잡이익 | L49: 0 | P49: =++-L49 -> 0 | S49: =IF(ISNUMBER(MATCH(G49&"",FS_map!$D:$D,0)),G49&"",IF(H49="","",H49&"")) -> 74250001
F50: BS | G50: 26050000 | H50: 86260033 | J50: 미수금 | K50: =++L49 -> 0 | N50: =++K50 -> 0 | S50: =IF(ISNUMBER(MATCH(G50&"",FS_map!$D:$D,0)),G50&"",IF(H50="","",H50&"")) -> 26050000
A52: BOOKED P16 | B52: 2026.02 | C52: 10 | D52: 25년 TP Adjustment (2월 확정 금액) | F52: PL | G52: 53000005 | H52: 86000800 | I52: 매출원가 | K52: 0 | P52: =++K52 -> 0 | Q52: 2025.12 invoice/credit 홀딩됨 | S52: =IF(ISNUMBER(MATCH(G52&"",FS_map!$D:$D,0)),G52&"",IF(H52="","",H52&"")) -> 53000005
D53: Statutory: 매출원가로 인식 | F53: BS | G53: 40100000 | H53: 86429100 | J53: 매입채무 | L53: =++K52 -> 0 | N53: =++-L53 -> 0 | Q53: 2025.12 invoice/credit 홀딩됨 | S53: =IF(ISNUMBER(MATCH(G53&"",FS_map!$D:$D,0)),G53&"",IF(H53="","",H53&"")) -> 40100000
D54: Internal: 잡손실/잡이익
C56: 11 | D56: GL reclassficiation_부가세미수금 잔액 오류 수정 | F56: BS | J56: 부가가치세미수금 | L56: 9 | M56: =++-L56 -> -9 | T56: 회사 BS_DEC 2026 미반영(당기 SAP잔액 0) → 정산표 미반영
F57: BS | I57: 부가가치세예수금 | K57: 9 | N57: =++K57 -> 9 | T57: 회사 BS_DEC 2026 미반영(당기 SAP잔액 0) → 정산표 미반영
C60: 12 | D60: GL reclassification_OHK 투자자산처분이익 계정재분류 | F60: PL | I60: 투자자산처분이익 | K60: 0 | P60: =++K60 -> 0
F61: PL | J61: 잡이익 | L61: 0 | P61: =++-L61 -> 0 | Q61: OHK 투자주식은 전기에 처분 완료되어 당기에 영업외이익 잡이익 계정으로 재분류
A63: BOOKED P16 | B63: 2026.02 | C63: 13 | D63: 전기오류수정이익 ( 한미약품 세금계산서 posting 누락) | F63: BS | G63: 40100000 | H63: 86429100 | I63: 매입채무 | K63: 0 | N63: =++K63 -> 0 | S63: =IF(ISNUMBER(MATCH(G63&"",FS_map!$D:$D,0)),G63&"",IF(H63="","",H63&"")) -> 40100000
D64: FY 21 | F64: PL | G64: 74250001 | H64: 86200400 | J64: 잡이익 | L64: 0 | P64: =++-L64 -> 0 | S64: =IF(ISNUMBER(MATCH(G64&"",FS_map!$D:$D,0)),G64&"",IF(H64="","",H64&"")) -> 74250001
D65: FY 23 | F65: PL | G65: 74250001 | H65: 86200400 | J65: 잡이익 | L65: 0 | P65: =++-L65 -> 0 | S65: =IF(ISNUMBER(MATCH(G65&"",FS_map!$D:$D,0)),G65&"",IF(H65="","",H65&"")) -> 74250001
A69: BOOKED P16 | B69: 2026.03 | C69: 14 | D69: 법인세조정 (세무조정) | F69: BS | H69: 86291000 | I69: 유동이연법인세자산 | K69: 0 | M69: =K69 -> 0 | S69: =IF(ISNUMBER(MATCH(G69&"",FS_map!$D:$D,0)),G69&"",IF(H69="","",H69&"")) -> 86291000
F70: BS | H70: 86429307 | I70: 미지급법인세 | K70: 0 | N70: =K70 -> 0 | S70: =IF(ISNUMBER(MATCH(G70&"",FS_map!$D:$D,0)),G70&"",IF(H70="","",H70&"")) -> 86429307
F71: BS | H71: 86291502 | I71: 비유동이연법인세자산 | L71: 0 | M71: =-L71 -> 0 | S71: =IF(ISNUMBER(MATCH(G71&"",FS_map!$D:$D,0)),G71&"",IF(H71="","",H71&"")) -> 86291502
F72: BS | H72: 86266003 | I72: 선급법인세 | L72: 0 | M72: =-L72 -> 0 | S72: =IF(ISNUMBER(MATCH(G72&"",FS_map!$D:$D,0)),G72&"",IF(H72="","",H72&"")) -> 86266003
F73: PL | H73: 86000000 | I73: 법인세비용 | L73: 0 | P73: =-L73 -> 0 | S73: =IF(ISNUMBER(MATCH(G73&"",FS_map!$D:$D,0)),G73&"",IF(H73="","",H73&"")) -> 86000000
C75: 15 | D75: 잉여금차이조정 | F75: BS | H75: 86429307 | I75: 미지급법인세 | K75: =1132939909+8 -> 1132939917 | S75: =IF(ISNUMBER(MATCH(G75&"",FS_map!$D:$D,0)),G75&"",IF(H75="","",H75&"")) -> 86429307
F76: BS | H76: 32200000 | I76: 이익잉여금 | L76: =1132939909+8 -> 1132939917 | S76: =IF(ISNUMBER(MATCH(G76&"",FS_map!$D:$D,0)),G76&"",IF(H76="","",H76&"")) -> 32200000
G78: Total Impact | K78: =SUM(K7:K77) -> 36539768570 | L78: =SUM(L7:L77) -> 36539768570 | M78: =SUM(M7:M77) -> -12415810133 | N78: =SUM(N7:N77) -> 12415810133 | O78: =SUM(O7:O77) -> 0 | P78: =SUM(P7:P77) -> 0 | Q78: =++M78+N78+O78+P78 -> 0

Sheet BSPL2026
L1: Vlookup | M1: Vlookup | N1: SAP | O1: SAP | P1: SAP | Q1: 2025.12 | R1: 2026.01 | S1: 2026.02 | T1: 2026.03 | U1: 2026.04 | V1: 2026.05 | W1: 2026.06 | X1: 2026.07 | Y1: 2026.08 | Z1: 2026.09 | AE1: 2026.01 | AF1: 2026.02 | AG1: 2025.03 | AH1: 2025.04 | AI1: 2025.05 | AJ1: 2025.06 | AK1: 2025.07 | AL1: 2025.08 | AM1: 2025.09 | AN1: 2025.10 | AO1: 2025.11 | AP1: 2025.12
A2: BS/PL | B2: Account Number | C2: Text for B/S P&L item | D2: SAP Description | E2: SAP Description 2 | F2: Type | G2: Account Group | H2: Company Code | I2: Group account number | J2: CC driven | K2: Group account description | L2: 감사보고서 과목 1 | M2: 감사보고서 과목 2 | N2: Internal BookKR 구분 | O2: Internal Book KR 구분 | P2: Internal Book KR 구분 | Q2: YTD Dec 2025 | R2: YTD Jan 2026 | S2: YTD Feb 2026 | T2: YTD Mar 2026 | U2: YTD April 2026 | V2: YTD May 2026 | W2: YTD June 2026 | X2: YTD July 2026 | Y2: YTD Aug 2026 | Z2: YTD Sep 2026 | AA2: YTD Sep 2026 | AB2: YTD Oct 2026 | AC2: YTD Nov 2026 | AD2: YTD Dec 2026 | AE2: MTD Jan 2026 | AF2: MTD Feb 2026 | AG2: MTD Mar 2025 | AH2: MTD Apr 2025 | AI2: MTD May 2025 | AJ2: MTD June 2025 | AK2: MTD July 2025 | AL2: MTD Aug 2025 | AM2: MTD Sep 2025 | AN2: MTD Oct 2025 | AO2: MTD Nov 2025 | AP2: MTD Dec 2025
A3: + | B3: + | C3: + | D3: + | E3: + | F3: + | G3: + | H3: + | I3: + | J3: + | K3: + | L3: + | M3: + | Q3: + | R3: + | S3: + | T3: + | U3: + | V3: + | W3: + | X3: + | Y3: + | Z3: + | AA3: + | AB3: + | AC3: + | AD3: + | AE3: + | AF3: + | AG3: + | AH3: + | AI3: + | AJ3: + | AK3: + | AL3: + | AM3: + | AN3: + | AO3: + | AP3: + | AQ3: +
A4: BS | B4: 10100082 | C4: 10100082 Lands and Buildings -Right of Use -Man | D4: ¥±. NON-CURRENT ASSETS | E4: (2) Tangible assets | F4: 2. Buildings | G4: 01. NCA - Non Current Assets | H4: 1616 | I4: 10035 | K4: Lands and buildings - Right of use | L4: 자산 | M4: 구축물 | N4: 자산 | O4: 비유동자산 | P4: 구축물 | Q4: 12060074810 | R4: 12060074810 | S4: 12060074810 | T4: 12060074810 | U4: 12060074810 | V4: 12060074810 | W4: 12060074810 | X4: 12060074810 | Y4: 12060074810 | Z4: 12060074810 | AE4: =R4 -> 12060074810 | AF4: =S4-R4 -> 0 | AG4: =T4-S4 -> 0 | AH4: =U4-T4 -> 0 | AI4: =V4-U4 -> 0 | AJ4: =W4-V4 -> 0 | AK4: =X4-W4 -> 0 | AL4: =Y4-X4 -> 0 | AM4: =Z4-Y4 -> 0
A5: BS | B5: 10100083 | C5: 10100083 Depreciation Land and Build -Right of Use -Man | D5: ¥±. NON-CURRENT ASSETS | E5: (2) Tangible assets | F5: Accumulated depreciation | G5: 01. NCA - Non Current Assets | H5: 1616 | I5: 10115 | K5: Depreciation - Lands and buildings - Right of use | L5: 자산 | M5: 감가상각누계액-구축물 | N5: 자산 | O5: 비유동자산 | P5: 감가상각누계액-구축물 | Q5: -10865717938 | R5: -10974295836 | S5: -11082873734 | T5: -11191451632 | U5: -11300029530 | V5: -11408607428 | W5: -11517185326 | X5: -11625763224 | Y5: -11720034754 | Z5: -11842919020 | AE5: =R5 -> -10974295836 | AF5: =S5-R5 -> -108577898 | AG5: =T5-S5 -> -108577898 | AH5: =U5-T5 -> -108577898 | AI5: =V5-U5 -> -108577898 | AJ5: =W5-V5 -> -108577898 | AK5: =X5-W5 -> -108577898 | AL5: =Y5-X5 -> -94271530 | AM5: =Z5-Y5 -> -122884266 | AR5: =IFERROR(VLOOKUP(M5,'BS_DEC 2026'!$D$12:$D$109,1,FALSE()),"(미존재)") -> 감가상각누계액-구축물
A6: BS | B6: 10100850 | C6: 10100850 Buildings -(A) Rec | D6: ¥±. NON-CURRENT ASSETS | E6: (2) Tangible assets | F6: 3. Structures | G6: 01. NCA - Non Current Assets | H6: 1616 | I6: 10005 | K6: Buildings | L6: 자산 | M6: 구축물 | N6: 자산 | O6: 비유동자산 | P6: 구축물 | Q6: 239169200 | R6: 239169200 | S6: 239169200 | T6: 239169200 | U6: 239169200 | V6: 239169200 | W6: 239169200 | X6: 239169200 | Y6: 239169200 | Z6: 239169200 | AE6: =R6 -> 239169200 | AF6: =S6-R6 -> 0 | AG6: =T6-S6 -> 0 | AH6: =U6-T6 -> 0 | AI6: =V6-U6 -> 0 | AJ6: =W6-V6 -> 0 | AK6: =X6-W6 -> 0 | AL6: =Y6-X6 -> 0 | AM6: =Z6-Y6 -> 0 | AR6: =IFERROR(VLOOKUP(M6,'BS_DEC 2026'!$D$12:$D$109,1,FALSE()),"(미존재)") -> 구축물
A7: BS | B7: 10150000 | C7: 10150000 Buildings -Leasehold Improvements -(A) Rec | D7: ¥±. NON-CURRENT ASSETS | E7: (2) Tangible assets | F7: 3. Structures | G7: 01. NCA - Non Current Assets | H7: 1616 | I7: 10005 | K7: Buildings | L7: 자산 | M7: 구축물 | N7: 자산 | O7: 비유동자산 | P7: 구축물 | Q7: 1304901001 | R7: 1304901001 | S7: 1304901001 | T7: 1304901001 | U7: 1304901001 | V7: 1304901001 | W7: 1304901001 | X7: 1304901001 | Y7: 1304901001 | Z7: 1304901001 | AE7: =R7 -> 1304901001 | AF7: =S7-R7 -> 0 | AG7: =T7-S7 -> 0 | AH7: =U7-T7 -> 0 | AI7: =V7-U7 -> 0 | AJ7: =W7-V7 -> 0 | AK7: =X7-W7 -> 0 | AL7: =Y7-X7 -> 0 | AM7: =Z7-Y7 -> 0 | AR7: =IFERROR(VLOOKUP(M7,'BS_DEC 2026'!$D$12:$D$109,1,FALSE()),"(미존재)") -> 구축물
A8: BS | B8: 10200000 | C8: 10200000 Machinery and Equipment -(A) Rec | D8: ¥±. NON-CURRENT ASSETS | E8: (2) Tangible assets | F8: 4. Machinery and equipment | G8: 01. NCA - Non Current Assets | H8: 1616 | I8: 10010 | K8: Machinery and equipment | L8: 자산 | M8: 기계장치 | N8: 자산 | O8: 비유동자산 | P8: 기계장치 | Q8: 1434004742 | R8: 1434004742 | S8: 1434004742 | T8: 1434004742 | U8: 1434004742 | V8: 1434004742 | W8: 1434004742 | X8: 1434004742 | Y8: 1434004742 | Z8: 1434004742 | AE8: =R8 -> 1434004742 | AF8: =S8-R8 -> 0 | AG8: =T8-S8 -> 0 | AH8: =U8-T8 -> 0 | AI8: =V8-U8 -> 0 | AJ8: =W8-V8 -> 0 | AK8: =X8-W8 -> 0 | AL8: =Y8-X8 -> 0 | AM8: =Z8-Y8 -> 0 | AR8: =IFERROR(VLOOKUP(M8,'BS_DEC 2026'!$D$12:$D$109,1,FALSE()),"(미존재)") -> 기계장치
A9: BS | B9: 10200921 | C9: 10200921 Samples -Manual | D9: ¥°. CURRENT ASSETS | E9: (2) Inventories | F9: 6. Supplies | G9: 02. CUA - Current Assets | H9: 1616 | I9: 20015 | K9: Inventories - Samples | L9: 자산 | M9: 상품 | N9: 자산 | O9: 유동자산 | P9: 저장품 | Q9: 0 | R9: 0 | S9: 0 | T9: 0 | U9: 0 | V9: 0 | W9: 0 | X9: 0 | Y9: 0 | Z9: 0 | AE9: =R9 -> 0 | AF9: =S9-R9 -> 0 | AG9: =T9-S9 -> 0 | AH9: =U9-T9 -> 0 | AI9: =V9-U9 -> 0 | AJ9: =W9-V9 -> 0 | AK9: =X9-W9 -> 0 | AL9: =Y9-X9 -> 0 | AM9: =Z9-Y9 -> 0 | AR9: =IFERROR(VLOOKUP(M9,'BS_DEC 2026'!$D$12:$D$109,1,FALSE()),"(미존재)") -> 상품
A10: BS | B10: 10300000 | C10: 10300000 Other FA -Furniture Fixtures & Office Equ -(A) Rec | D10: ¥±. NON-CURRENT ASSETS | E10: (2) Tangible assets | F10: 6. Tools and furniture | G10: 01. NCA - Non Current Assets | H10: 1616 | I10: 10015 | K10: Other fixed assets | L10: 자산 | M10: 집기비품 | N10: 자산 | O10: 비유동자산 | P10: 집기비품 | Q10: 350199634 | R10: 350199634 | S10: 350199634 | T10: 350199634 | U10: 350199634 | V10: 350199634 | W10: 350199634 | X10: 350199634 | Y10: 350199634 | Z10: 350199634 | AE10: =R10 -> 350199634 | AF10: =S10-R10 -> 0 | AG10: =T10-S10 -> 0 | AH10: =U10-T10 -> 0 | AI10: =V10-U10 -> 0 | AJ10: =W10-V10 -> 0 | AK10: =X10-W10 -> 0 | AL10: =Y10-X10 -> 0 | AM10: =Z10-Y10 -> 0 | AR10: =IFERROR(VLOOKUP(M10,'BS_DEC 2026'!$D$12:$D$109,1,FALSE()),"(미존재)") -> 집기비품
A11: BS | B11: 10300850 | C11: 10300850 Other Fixed Assets -(A) Rec | D11: ¥±. NON-CURRENT ASSETS | E11: (2) Tangible assets | F11: 6. Tools and furniture | G11: 01. NCA - Non Current Assets | H11: 1616 | I11: 10015 | K11: Other fixed assets | L11: 자산 | M11: 공구와기구 | N11: 자산 | O11: 비유동자산 | P11: 공구와기구 | Q11: 42938000 | R11: 42938000 | S11: 42938000 | T11: 42938000 | U11: 42938000 | V11: 42938000 | W11: 42938000 | X11: 42938000 | Y11: 42938000 | Z11: 42938000 | AE11: =R11 -> 42938000 | AF11: =S11-R11 -> 0 | AG11: =T11-S11 -> 0 | AH11: =U11-T11 -> 0 | AI11: =V11-U11 -> 0 | AJ11: =W11-V11 -> 0 | AK11: =X11-W11 -> 0 | AL11: =Y11-X11 -> 0 | AM11: =Z11-Y11 -> 0 | AR11: =IFERROR(VLOOKUP(M11,'BS_DEC 2026'!$D$12:$D$109,1,FALSE()),"(미존재)") -> 공구와기구
A12: BS | B12: 10350000 | C12: 10350000 Other FA -IT Equipment -(A) Rec | D12: ¥±. NON-CURRENT ASSETS | E12: (2) Tangible assets | F12: 6. Tools and furniture | G12: 01. NCA - Non Current Assets | H12: 1616 | I12: 10015 | K12: Other fixed assets | L12: 자산 | M12: 집기비품 | N12: 자산 | O12: 비유동자산 | P12: 집기비품 | Q12: 1282738705 | R12: 1282738705 | S12: 1282738705 | T12: 1282738705 | U12: 1282738705 | V12: 1282738705 | W12: 1369225145 | X12: 1369225145 | Y12: 1369225145 | Z12: 1369225145 | AE12: =R12 -> 1282738705 | AF12: =S12-R12 -> 0 | AG12: =T12-S12 -> 0 | AH12: =U12-T12 -> 0 | AI12: =V12-U12 -> 0 | AJ12: =W12-V12 -> 86486440 | AK12: =X12-W12 -> 0 | AL12: =Y12-X12 -> 0 | AM12: =Z12-Y12 -> 0 | AR12: =IFERROR(VLOOKUP(M12,'BS_DEC 2026'!$D$12:$D$109,1,FALSE()),"(미존재)") -> 집기비품
A13: BS | B13: 10350303 | C13: 10350303 Other Fixed Assets -(A) Rec | D13: ¥±. NON-CURRENT ASSETS | E13: (2) Tangible assets | F13: 6. Tools and furniture | G13: 01. NCA - Non Current Assets | H13: 1616 | I13: 10015 | K13: Other fixed assets | L13: 자산 | M13: 공구와기구 | N13: 자산 | O13: 비유동자산 | P13: 공구와기구 | Q13: 34046016 | R13: 34046016 | S13: 34046016 | T13: 34046016 | U13: 34046016 | V13: 34046016 | W13: 34046016 | X13: 34046016 | Y13: 34046016 | Z13: 34046016 | AE13: =R13 -> 34046016 | AF13: =S13-R13 -> 0 | AG13: =T13-S13 -> 0 | AH13: =U13-T13 -> 0 | AI13: =V13-U13 -> 0 | AJ13: =W13-V13 -> 0 | AK13: =X13-W13 -> 0 | AL13: =Y13-X13 -> 0 | AM13: =Z13-Y13 -> 0 | AR13: =IFERROR(VLOOKUP(M13,'BS_DEC 2026'!$D$12:$D$109,1,FALSE()),"(미존재)") -> 공구와기구
A14: BS | B14: 10550400 | C14: 10550400 In Progress -Other -IT Equipment -(A) | D14: ¥±. NON-CURRENT ASSETS | E14: (3) Intangible assets | F14: 4. Software | G14: 01. NCA - Non Current Assets | H14: 1616 | I14: 13028 | K14: Softwares - Bought | L14: 자산 | M14: 소프트웨어 | N14: 자산 | O14: 비유동자산 | P14: 소프트웨어 | Q14: 0 | R14: 0 | S14: 0 | T14: 0 | U14: 6010900 | V14: 9990900 | W14: 15351876 | X14: 18512609 | Y14: 18512609 | Z14: 22468609 | AE14: =R14 -> 0 | AF14: =S14-R14 -> 0 | AG14: =T14-S14 -> 0 | AH14: =U14-T14 -> 6010900 | AI14: =V14-U14 -> 3980000 | AJ14: =W14-V14 -> 5360976 | AK14: =X14-W14 -> 3160733 | AL14: =Y14-X14 -> 0 | AM14: =Z14-Y14 -> 3956000 | AR14: =IFERROR(VLOOKUP(M14,'BS_DEC 2026'!$D$12:$D$109,1,FALSE()),"(미존재)") -> 소프트웨어
A15: BS | B15: 10550900 | C15: 10550900 In Progress -Buildings -(A) Rec | D15: ¥±. NON-CURRENT ASSETS | E15: (2) Tangible assets | F15: 7. Construction in-progress | G15: 01. NCA - Non Current Assets | H15: 1616 | I15: 10020 | K15: In progress - Buildings | L15: 자산 | M15: 건설중인자산 | N15: 자산 | O15: 비유동자산 | P15: 건설중인자산 | Q15: 8237836 | R15: 8237836 | S15: 8237836 | T15: 8237836 | U15: 29237836 | V15: 29237836 | W15: 30287836 | X15: 30287836 | Y15: 30287836 | Z15: 51562836 | AE15: =R15 -> 8237836 | AF15: =S15-R15 -> 0 | AG15: =T15-S15 -> 0 | AH15: =U15-T15 -> 21000000 | AI15: =V15-U15 -> 0 | AJ15: =W15-V15 -> 1050000 | AK15: =X15-W15 -> 0 | AL15: =Y15-X15 -> 0 | AM15: =Z15-Y15 -> 21275000 | AR15: =IFERROR(VLOOKUP(M15,'BS_DEC 2026'!$D$12:$D$109,1,FALSE()),"(미존재)") -> 건설중인자산
A16: BS | B16: 11100850 | C16: 11100850 Depreciation Buildings -(A) Rec | D16: ¥±. NON-CURRENT ASSETS | E16: (2) Tangible assets | F16: Accumulated depreciation | G16: 01. NCA - Non Current Assets | H16: 1616 | I16: 10100 | K16: Depreciation - Buildings | L16: 자산 | M16: 감가상각누계액-구축물 | N16: 자산 | O16: 비유동자산 | P16: 감가상각누계액-구축물 | Q16: -168102710 | R16: -174563301 | S16: -181023889 | T16: -187484480 | U16: -193945070 | V16: -200405661 | W16: -206866249 | X16: -213326840 | Y16: -219787430 | Z16: -226248021 | AE16: =R16 -> -174563301 | AF16: =S16-R16 -> -6460588 | AG16: =T16-S16 -> -6460591 | AH16: =U16-T16 -> -6460590 | AI16: =V16-U16 -> -6460591 | AJ16: =W16-V16 -> -6460588 | AK16: =X16-W16 -> -6460591 | AL16: =Y16-X16 -> -6460590 | AM16: =Z16-Y16 -> -6460591 | AR16: =IFERROR(VLOOKUP(M16,'BS_DEC 2026'!$D$12:$D$109,1,FALSE()),"(미존재)") -> 감가상각누계액-구축물
... A43: BS | B43: 24000030 | C43: 24000030 Accts Rec. Trade. S/Term for Clinic | D43: ¥°. CURRENT ASSETS | E43: (1) Quick assets | F43: 4. Trade receivables | G43: 02. CUA - Current Assets | H43: 1616 | I43: 22005 | K43: Others accounts receivable | L43: 자산 | M43: 매출채권 | N43: 자산 | O43: 유동자산 | P43: 외상매출금 | Q43: 109350608 | R43: 109130408 | S43: 108780333 | T43: 111522107 | U43: 111522107 | V43: 111427453 | W43: 111427453 | X43: 111427453 | Y43: 111427453 | Z43: 111427453 | AE43: =R43 -> 109130408 | AF43: =S43-R43 -> -350075 | AG43: =T43-S43 -> 2741774 | AH43: =U43-T43 -> 0 | AI43: =V43-U43 -> -94654 | AJ43: =W43-V43 -> 0 | AK43: =X43-W43 -> 0 | AL43: =Y43-X43 -> 0 | AM43: =Z43-Y43 -> 0 | AR43: =IFERROR(VLOOKUP(M43,'BS_DEC 2026'!$D$12:$D$109,1,FALSE()),"(미존재)") -> 매출채권
A44: BS | B44: 24000812 | C44: 24000812 AR( D) Receivable on fixed assets | D44: ¥°. CURRENT ASSETS | E44: (1) Quick assets | F44: 1. Cash and cash equivalence | G44: 04. CAS - Cash & Cash Equivalents | H44: 1616 | I44: 266 | K44: Cash in reporting currency | L44: 자산 | M44: 매출채권 | N44: 자산 | O44: 유동자산 | P44: 현금및현금등가물 | Z44: 17617 | AM44: =Z44-Y44 -> 17617 | AR44: =IFERROR(VLOOKUP(M44,'BS_DEC 2026'!$D$12:$D$109,1,FALSE()),"(미존재)") -> 매출채권
A45: BS | B45: 24050000 | C45: 24050000 AR-D Trade ICO | D45: ¥°. CURRENT ASSETS | E45: (1) Quick assets | F45: 4. Trade receivables | G45: 03. ICA - Intercompany Assets | H45: 1616 | I45: 24905 | K45: Current assets - Conso comp | L45: 자산 | M45: 매출채권 | N45: 자산 | O45: 유동자산 | P45: 외상매출금 | Q45: 8262841 | R45: 75497334 | S45: 75497334 | T45: 75497334 | U45: 8262841 | V45: 8262841 | W45: 10103 | X45: 10103 | Y45: 10103 | Z45: 10103 | AE45: =R45 -> 75497334 | AF45: =S45-R45 -> 0 | AG45: =T45-S45 -> 0 | AH45: =U45-T45 -> -67234493 | AI45: =V45-U45 -> 0 | AJ45: =W45-V45 -> -8252738 | AK45: =X45-W45 -> 0 | AL45: =Y45-X45 -> 0 | AM45: =Z45-Y45 -> 0 | AR45: =IFERROR(VLOOKUP(M45,'BS_DEC 2026'!$D$12:$D$109,1,FALSE()),"(미존재)") -> 매출채권
A46: BS | B46: 24050051 | C46: 24050051 AR Trade ICO MANUAL | D46: ¥°. CURRENT ASSETS | E46: (1) Quick assets | F46: 4. Trade receivables | G46: 03. ICA - Intercompany Assets | H46: 1616 | I46: 24905 | K46: Current assets - Conso comp | L46: 자산 | M46: 매출채권 | N46: 자산 | O46: 유동자산 | P46: 외상매출금 | Q46: 0 | R46: 0 | S46: 0 | T46: 6795422000 | U46: 6795422000 | V46: 6795422000 | W46: 0 | X46: 0 | Y46: 0 | Z46: 0 | AE46: =R46 -> 0 | AF46: =S46-R46 -> 0 | AG46: =T46-S46 -> 6795422000 | AH46: =U46-T46 -> 0 | AI46: =V46-U46 -> 0 | AJ46: =W46-V46 -> -6795422000 | AK46: =X46-W46 -> 0 | AL46: =Y46-X46 -> 0 | AM46: =Z46-Y46 -> 0 | AR46: =IFERROR(VLOOKUP(M46,'BS_DEC 2026'!$D$12:$D$109,1,FALSE()),"(미존재)") -> 매출채권
A47: BS | B47: 24100002 | C47: 24100002 AR (D) SGLI -Provision Bad Debt Trade 3rd Party | D47: ¥°. CURRENT ASSETS | E47: (1) Quick assets | F47: 4. Trade receivables | G47: 02. CUA - Current Assets | H47: 1616 | I47: 22200 | K47: Prov - Accounts & notes receivable | L47: 자산 | M47: 대손충당금 | N47: 자산 | O47: 유동자산 | P47: 대손충당금 | Q47: 0 | R47: 0 | S47: 0 | T47: 0 | U47: 0 | V47: 0 | W47: 0 | X47: 0 | Y47: 0 | Z47: 0 | AE47: =R47 -> 0 | AF47: =S47-R47 -> 0 | AG47: =T47-S47 -> 0 | AH47: =U47-T47 -> 0 | AI47: =V47-U47 -> 0 | AJ47: =W47-V47 -> 0 | AK47: =X47-W47 -> 0 | AL47: =Y47-X47 -> 0 | AM47: =Z47-Y47 -> 0 | AR47: =IFERROR(VLOOKUP(M47,'BS_DEC 2026'!$D$12:$D$109,1,FALSE()),"(미존재)") -> 대손충당금
A48: BS | B48: 26000000 | C48: 26000000 Other receivable | G48: 02. CUA - Current Assets | H48: 1616 | I48: 24032 | K48: Sundry current assets (excluding restructuring) | L48: 자산 | M48: 미수금 | N48: 자산 | O48: 유동자산 | P48: 미수금 | Q48: -8851971 | R48: -709221 | S48: -9672517 | T48: 978472424 | U48: -9335194 | V48: -9049424 | W48: 1819980 | X48: 1819980 | Y48: 1819980 | Z48: 1002240 | AE48: =R48 -> -709221 | AF48: =S48-R48 -> -8963296 | AG48: =T48-S48 -> 988144941 | AH48: =U48-T48 -> -987807618 | AI48: =V48-U48 -> 285770 | AJ48: =W48-V48 -> 10869404 | AK48: =X48-W48 -> 0 | AL48: =Y48-X48 -> 0 | AM48: =Z48-Y48 -> -817740 | AR48: =IFERROR(VLOOKUP(M48,'BS_DEC 2026'!$D$12:$D$109,1,FALSE()),"(미존재)") -> 미수금
A49: BS | B49: 26000015 | C49: 26000015 Other Receivables - manual | D49: ¥°. CURRENT ASSETS | E49: (1) Quick assets | F49: 7. Accrued income | G49: 02. CUA - Current Assets | H49: 1616 | I49: 24032 | K49: Sundry current assets (excluding restructuring) | L49: 자산 | M49: 미수수익 | N49: 자산 | O49: 유동자산 | P49: 미수수익 | Q49: 979522379 | R49: 1077942840 | S49: 1125785792 | T49: 280033537 | U49: 392172650 | V49: 515379905 | W49: 627623527 | X49: 742453168 | Y49: 867874852 | Z49: 981690770 | AE49: =R49 -> 1077942840 | AF49: =S49-R49 -> 47842952 | AG49: =T49-S49 -> -845752255 | AH49: =U49-T49 -> 112139113 | AI49: =V49-U49 -> 123207255 | AJ49: =W49-V49 -> 112243622 | AK49: =X49-W49 -> 114829641 | AL49: =Y49-X49 -> 125421684 | AM49: =Z49-Y49 -> 113815918 | AR49: =IFERROR(VLOOKUP(M49,'BS_DEC 2026'!$D$12:$D$109,1,FALSE()),"(미존재)") -> 미수수익
A50: BS | B50: 26000033 | C50: 26000033 Other partners relationship - Assets | D50: ¥°. CURRENT ASSETS | E50: (1) Quick assets | F50: 6. Other receivables | G50: 02. CUA - Current Assets | H50: 1616 | I50: 24028 | K50: Other partners relationship - Assets | L50: 자산 | M50: 미수금 | N50: 자산 | O50: 유동자산 | P50: 미수금 | Q50: 0 | R50: 0 | S50: 0 | T50: 0 | U50: 0 | V50: 0 | W50: 0 | X50: 0 | Y50: 0 | Z50: 0 | AE50: =R50 -> 0 | AF50: =S50-R50 -> 0 | AG50: =T50-S50 -> 0 | AH50: =U50-T50 -> 0 | AI50: =V50-U50 -> 0 | AJ50: =W50-V50 -> 0 | AK50: =X50-W50 -> 0 | AL50: =Y50-X50 -> 0 | AM50: =Z50-Y50 -> 0 | AR50: =IFERROR(VLOOKUP(M50,'BS_DEC 2026'!$D$12:$D$109,1,FALSE()),"(미존재)") -> 미수금
A51: BS | B51: 26000200 | C51: 26000200 AP Prepaid OneCASA Clinical Studies -Man | D51: ¥°. CURRENT ASSETS | E51: (1) Quick assets | F51: 10. Prepaid expenses | G51: 02. CUA - Current Assets | H51: 1616 | I51: 24016 | K51: Prepaid expenses - C. assets | L51: 자산 | M51: 선급비용 | N51: 자산 | O51: 유동자산 | P51: 선급비용 | R51: 0 | X51: 706023118 | Y51: 664962455 | Z51: 656604886 | AK51: =X51-W51 -> 706023118 | AL51: =Y51-X51 -> -41060663 | AM51: =Z51-Y51 -> -8357569 | AR51: =IFERROR(VLOOKUP(M51,'BS_DEC 2026'!$D$12:$D$109,1,FALSE()),"(미존재)") -> 선급비용
A52: BS | B52: 26000810 | C52: 26000810 Payroll deductions | D52: ¥°. CURRENT ASSETS | E52: (1) Quick assets | F52: 6. Other receivables | G52: 02. CUA - Current Assets | H52: 1616 | I52: 24002 | K52: Employees | L52: 자산 | M52: 선급금 | N52: 자산 | O52: 유동자산 | P52: 미수금 | Q52: 6858752 | R52: 5564992 | S52: 1797332242 | T52: 1370773380 | U52: -5652220 | V52: 291870 | W52: 23161190 | X52: 8878580 | Y52: 808630 | Z52: 809597490 | AE52: =R52 -> 5564992 | AF52: =S52-R52 -> 1791767250 | AG52: =T52-S52 -> -426558862 | AH52: =U52-T52 -> -1376425600 | AI52: =V52-U52 -> 5944090 | AJ52: =W52-V52 -> 22869320 | AK52: =X52-W52 -> -14282610 | AL52: =Y52-X52 -> -8069950 | AM52: =Z52-Y52 -> 808788860 | AR52: =IFERROR(VLOOKUP(M52,'BS_DEC 2026'!$D$12:$D$109,1,FALSE()),"(미존재)") -> 선급금
A53: BS | B53: 26030000 | C53: 26030000 Allowances on other accounts receivable | D53: ¥°. CURRENT ASSETS | E53: (1) Quick assets | F53: 4. Trade receivables | G53: 02. CUA - Current Assets | H53: 1616 | I53: 24205 | K53: Prov - Other current assets | L53: 자산 | M53: 대손충당금 | N53: 자산 | O53: 유동자산 | P53: 대손충당금 | Q53: 0 | R53: 0 | S53: 0 | T53: 0 | U53: 0 | V53: 0 | W53: 0 | X53: 0 | Y53: 0 | Z53: 0 | AE53: =R53 -> 0 | AF53: =S53-R53 -> 0 | AG53: =T53-S53 -> 0 | AH53: =U53-T53 -> 0 | AI53: =V53-U53 -> 0 | AJ53: =W53-V53 -> 0 | AK53: =X53-W53 -> 0 | AL53: =Y53-X53 -> 0 | AM53: =Z53-Y53 -> 0 | AR53: =IFERROR(VLOOKUP(M53,'BS_DEC 2026'!$D$12:$D$109,1,FALSE()),"(미존재)") -> 대손충당금
A54: BS | B54: 26050000 | C54: 26050000 AR-D Other non-trade ICO | D54: ¥°. CURRENT ASSETS | E54: (1) Quick assets | F54: 6. Other receivables | G54: 03. ICA - Intercompany Assets | H54: 1616 | I54: 24905 | K54: Current assets - Conso comp | L54: 자산 | M54: 미수금 | N54: 자산 | O54: 유동자산 | P54: 미수금 | Q54: 16694851073 | R54: 7065437572 | S54: 3216733556 | T54: 6828696225 | U54: 3660460828 | V54: 11400 | W54: 5605566971 | X54: 5605555571 | Y54: 0 | Z54: 11576676956 | AE54: =R54 -> 7065437572 | AF54: =S54-R54 -> -3848704016 | AG54: =T54-S54 -> 3611962669 | AH54: =U54-T54 -> -3168235397 | AI54: =V54-U54 -> -3660449428 | AJ54: =W54-V54 -> 5605555571 | AK54: =X54-W54 -> -11400 | AL54: =Y54-X54 -> -5605555571 | AM54: =Z54-Y54 -> 11576676956 | AR54: =IFERROR(VLOOKUP(M54,'BS_DEC 2026'!$D$12:$D$109,1,FALSE()),"(미존재)") -> 미수금
A55: BS | B55: 26220000 | C55: 26220000 S/T Loans Rec Group.Comp | G55: 03. ICA - Intercompany Assets | H55: 1616 | I55: 24905 | K55: Current assets - Conso comp | L55: (원본오류 N/A) | M55: (원본오류 N/A) | N55: (원본오류 N/A) | O55: (원본오류 N/A) | P55: (원본오류 N/A) | Q55: 0 | R55: 0 | S55: 0 | T55: 0 | U55: 0 | V55: 0 | W55: 0 | X55: 0 | Y55: 0 | Z55: 0 | AE55: =R55 -> 0 | AF55: =S55-R55 -> 0 | AG55: =T55-S55 -> 0 | AH55: =U55-T55 -> 0 | AI55: =V55-U55 -> 0 | AJ55: =W55-V55 -> 0 | AK55: =X55-W55 -> 0 | AL55: =Y55-X55 -> 0 | AM55: =Z55-Y55 -> 0 | AR55: =IFERROR(VLOOKUP(M55,'BS_DEC 2026'!$D$12:$D$109,1,FALSE()),"(미존재)") -> (미존재)
A56: BS | B56: 26220101 | C56: 26220101 Other accrued liabilities - ICO - Manual | D56: LIABILITIES | E56: ¥°. CURRENT LIABILITIES | F56: 5. Accrued expenses | G56: 07. CUL - Current Liabilities | H56: 1616 | I56: 42905 | K56: Current liabilities - Conso comp | L56: 부채 | M56: 미지급비용 | N56: 부채 | O56: 유동부채 | P56: 미지급비용 | Q56: 0 | R56: 0 | S56: 0 | T56: -6795422000 | U56: -6795422000 | V56: -6795422000 | W56: -944645152 | X56: 0 | Y56: 0 | Z56: 0 | AE56: =R56 -> 0 | AF56: =S56-R56 -> 0 | AG56: =T56-S56 -> -6795422000 | AH56: =U56-T56 -> 0 | AI56: =V56-U56 -> 0 | AJ56: =W56-V56 -> 5850776848 | AK56: =X56-W56 -> 944645152 | AL56: =Y56-X56 -> 0 | AM56: =Z56-Y56 -> 0 | AR56: =IFERROR(VLOOKUP(M56,'BS_DEC 2026'!$D$12:$D$109,1,FALSE()),"(미존재)") -> 미지급비용
A57: BS | B57: 26530000 | C57: 26530000 GST/VAT paid to Vendors | D57: LIABILITIES | E57: ¥°. CURRENT LIABILITIES | F57: 4. Withholdings | G57: 02. CUA - Current Assets | H57: 1616 | I57: 24006 | K57: Taxes - Local VAT recoverable | L57: 부채 | M57: 부가가치세예수금 | N57: 부채 | O57: 유동부채 | P57: 예수금 | Q57: 13474110429 | R57: 2811582736 | S57: 6626665468 | T57: 9051617494 | U57: 5944970041 | V57: 12496740386 | W57: 16163569015 | X57: 6011487310 | Y57: 15682617357 | Z57: 18421587033 | AE57: =R57 -> 2811582736 | AF57: =S57-R57 -> 3815082732 | AG57: =T57-S57 -> 2424952026 | AH57: =U57-T57 -> -3106647453 | AI57: =V57-U57 -> 6551770345 | AJ57: =W57-V57 -> 3666828629 | AK57: =X57-W57 -> -10152081705 | AL57: =Y57-X57 -> 9671130047 | AM57: =Z57-Y57 -> 2738969676 | AQ57: 통관부가세 납부 | AR57: =IFERROR(VLOOKUP(M57,'BS_DEC 2026'!$D$12:$D$109,1,FALSE()),"(미존재)") -> 부가가치세예수금
A58: BS | B58: 26550000 | C58: 26550000 Prepaid - Expenses | D58: ¥°. CURRENT ASSETS | E58: (1) Quick assets | F58: 10. Prepaid expenses | G58: 02. CUA - Current Assets | H58: 1616 | I58: 24016 | K58: Prepaid expenses - C. assets | L58: 자산 | M58: 선급비용 | N58: 자산 | O58: 유동자산 | P58: 선급비용 | Q58: 0 | R58: 328225333 | S58: 314386666 | T58: 282947999 | U58: 251509332 | V58: 220070665 | W58: 188631998 | X58: 157193331 | Y58: 125754664 | Z58: 96387997 | AE58: =R58 -> 328225333 | AF58: =S58-R58 -> -13838667 | AG58: =T58-S58 -> -31438667 | AH58: =U58-T58 -> -31438667 | AI58: =V58-U58 -> -31438667 | AJ58: =W58-V58 -> -31438667 | AK58: =X58-W58 -> -31438667 | AL58: =Y58-X58 -> -31438667 | AM58: =Z58-Y58 -> -29366667 | AR58: =IFERROR(VLOOKUP(M58,'BS_DEC 2026'!$D$12:$D$109,1,FALSE()),"(미존재)") -> 선급비용
A59: BS | B59: 26550001 | C59: 26550001 Prep.Exp.Insurance Premiums | D59: ¥°. CURRENT ASSETS | E59: (1) Quick assets | F59: 10. Prepaid expenses | G59: 02. CUA - Current Assets | H59: 1616 | I59: 24016 | K59: Prepaid expenses - C. assets | L59: 자산 | M59: 선급비용 | N59: 자산 | O59: 유동자산 | P59: 선급비용 | Q59: 307501499 | R59: 265926124 | S59: 224350749 | T59: 182775374 | U59: 194467519 | V59: 153402724 | W59: 427151676 | X59: 383679702 | Y59: 340207728 | Z59: 296735751 | AE59: =R59 -> 265926124 | AF59: =S59-R59 -> -41575375 | AG59: =T59-S59 -> -41575375 | AH59: =U59-T59 -> 11692145 | AI59: =V59-U59 -> -41064795 | AJ59: =W59-V59 -> 273748952 | AK59: =X59-W59 -> -43471974 | AL59: =Y59-X59 -> -43471974 | AM59: =Z59-Y59 -> -43471977 | AR59: =IFERROR(VLOOKUP(M59,'BS_DEC 2026'!$D$12:$D$109,1,FALSE()),"(미존재)") -> 선급비용
A60: BS | B60: 26550002 | C60: 26550002 Prepaid Rental | G60: 02. CUA - Current Assets | H60: 1616 | I60: 24016 | K60: Prepaid expenses - C. assets | L60: (원본오류 N/A) | M60: (원본오류 N/A) | N60: (원본오류 N/A) | O60: (원본오류 N/A) | P60: (원본오류 N/A) | Q60: 0 | R60: 0 | S60: 0 | T60: 0 | U60: 0 | V60: 0 | W60: 0 | X60: 0 | Y60: 0 | Z60: 0 | AE60: =R60 -> 0 | AF60: =S60-R60 -> 0 | AG60: =T60-S60 -> 0 | AH60: =U60-T60 -> 0 | AI60: =V60-U60 -> 0 | AJ60: =W60-V60 -> 0 | AK60: =X60-W60 -> 0 | AL60: =Y60-X60 -> 0 | AM60: =Z60-Y60 -> 0 | AR60: =IFERROR(VLOOKUP(M60,'BS_DEC 2026'!$D$12:$D$109,1,FALSE()),"(미존재)") -> (미존재)
A61: BS | B61: 26550303 | C61: 26550303 Prepaid expenses / Other | D61: ¥°. CURRENT ASSETS | E61: (1) Quick assets | F61: 10. Prepaid expenses | G61: 02. CUA - Current Assets | H61: 1616 | I61: 24016 | K61: Prepaid expenses - C. assets | L61: 자산 | M61: 선급비용 | N61: 자산 | O61: 유동자산 | P61: 선급비용 | Q61: 0 | R61: 0 | S61: 0 | T61: 0 | U61: 830238594 | V61: 731318606 | W61: 1409937688 | X61: 0 | Y61: 0 | Z61: 0 | AE61: =R61 -> 0 | AF61: =S61-R61 -> 0 | AG61: =T61-S61 -> 0 | AH61: =U61-T61 -> 830238594 | AI61: =V61-U61 -> -98919988 | AJ61: =W61-V61 -> 678619082 | AK61: =X61-W61 -> -1409937688 | AL61: =Y61-X61 -> 0 | AM61: =Z61-Y61 -> 0 | AR61: =IFERROR(VLOOKUP(M61,'BS_DEC 2026'!$D$12:$D$109,1,FALSE()),"(미존재)") -> 선급비용
A62: BS | B62: 26550450 | C62: 26550450 SPPI amortized costs-curr-all but collateral given | D62: ¥°. CURRENT ASSETS | E62: (1) Quick assets | F62: 6. Other receivables | G62: 02. CUA - Current Assets | H62: 1616 | I62: 24042 | K62: SPPI amortized costs - current | L62: 자산 | M62: 미수금 | N62: 자산 | O62: 유동자산 | P62: 미수금 | Q62: 311870229 | R62: 261437384 | S62: 211004539 | T62: 177558870 | U62: 132574612 | V62: 88355066 | W62: 43313453 | X62: 510408090 | Y62: 467695498 | Z62: 424982906 | AE62: =R62 -> 261437384 | AF62: =S62-R62 -> -50432845 | AG62: =T62-S62 -> -33445669 | AH62: =U62-T62 -> -44984258 | AI62: =V62-U62 -> -44219546 | AJ62: =W62-V62 -> -45041613 | AK62: =X62-W62 -> 467094637 | AL62: =Y62-X62 -> -42712592 | AM62: =Z62-Y62 -> -42712592 | AR62: =IFERROR(VLOOKUP(M62,'BS_DEC 2026'!$D$12:$D$109,1,FALSE()),"(미존재)") -> 미수금
A63: BS | B63: 26650000 | C63: 26650000 Advance payments | D63: ¥°. CURRENT ASSETS | E63: (1) Quick assets | F63: 9. Advance payments | G63: 02. CUA - Current Assets | H63: 1616 | I63: 24018 | K63: Advance payments to suppliers & agents | L63: 자산 | M63: 선급금 | N63: 자산 | O63: 유동자산 | P63: 선급금 | Q63: 14382500 | R63: 134916960 | S63: 60617995 | T63: 225440723 | U63: 380328349 | V63: 373074381 | W63: 285912800 | X63: 470895240 | Y63: 327256800 | Z63: 415218875 | AE63: =R63 -> 134916960 | AF63: =S63-R63 -> -74298965 | AG63: =T63-S63 -> 164822728 | AH63: =U63-T63 -> 154887626 | AI63: =V63-U63 -> -7253968 | AJ63: =W63-V63 -> -87161581 | AK63: =X63-W63 -> 184982440 | AL63: =Y63-X63 -> -143638440 | AM63: =Z63-Y63 -> 87962075 | AR63: =IFERROR(VLOOKUP(M63,'BS_DEC 2026'!$D$12:$D$109,1,FALSE()),"(미존재)") -> 선급금
A64: BS | B64: 26650851 | C64: 26650851 Advance Payments-Foreign currency adj. acct. | G64: 02. CUA - Current Assets | H64: 1616 | I64: 24018 | K64: Advance payments to suppliers & agents | L64: (원본오류 N/A) | M64: (원본오류 N/A) | N64: (원본오류 N/A) | O64: (원본오류 N/A) | P64: (원본오류 N/A) | Q64: 0 | R64: 0 | S64: 0 | T64: 0 | U64: 0 | V64: 0 | W64: 0 | X64: 0 | Y64: 0 | Z64: 0 | AE64: =R64 -> 0 | AF64: =S64-R64 -> 0 | AG64: =T64-S64 -> 0 | AH64: =U64-T64 -> 0 | AI64: =V64-U64 -> 0 | AJ64: =W64-V64 -> 0 | AK64: =X64-W64 -> 0 | AL64: =Y64-X64 -> 0 | AM64: =Z64-Y64 -> 0 | AR64: =IFERROR(VLOOKUP(M64,'BS_DEC 2026'!$D$12:$D$109,1,FALSE()),"(미존재)") -> (미존재)
A65: BS | B65: 26650852 | C65: 26650852 Sundry - Ot | D65: ¥°. CURRENT ASSETS | E65: (1) Quick assets | F65: 9. Advance payments | G65: 02. CUA - Current Assets | H65: 1616 | I65: 24032 | K65: Sundry current assets (excluding restructuring) | L65: 자산 | M65: 선급금 | N65: 자산 | O65: 유동자산 | P65: 선급금 | Q65: 0 | R65: 0 | S65: 0 | T65: 0 | U65: 0 | V65: 0 | W65: 0 | X65: 0 | Y65: 0 | Z65: 0 | AE65: =R65 -> 0 | AF65: =S65-R65 -> 0 | AG65: =T65-S65 -> 0 | AH65: =U65-T65 -> 0 | AI65: =V65-U65 -> 0 | AJ65: =W65-V65 -> 0 | AK65: =X65-W65 -> 0 | AL65: =Y65-X65 -> 0 | AM65: =Z65-Y65 -> 0 | AR65: =IFERROR(VLOOKUP(M65,'BS_DEC 2026'!$D$12:$D$109,1,FALSE()),"(미존재)") -> 선급금
A66: BS | B66: 26650854 | C66: 26650854 Local VAT Refund asked | D66: ¥°. CURRENT ASSETS | E66: (1) Quick assets | F66: 9. Advance payments | G66: 02. CUA - Current Assets | H66: 1616 | I66: 24006 | K66: Taxes - Local VAT recoverable | L66: 자산 | M66: 부가가치세미수금 | N66: 자산 | O66: 유동자산 | P66: 선급금 | Q66: 9 | R66: 9 | S66: 9 | T66: 9 | U66: 0 | V66: 0 | W66: 0 | X66: 0 | Y66: 0 | Z66: 0 | AE66: =R66 -> 9 | AF66: =S66-R66 -> 0 | AG66: =T66-S66 -> 0 | AH66: =U66-T66 -> -9 | AI66: =V66-U66 -> 0 | AJ66: =W66-V66 -> 0 | AK66: =X66-W66 -> 0 | AL66: =Y66-X66 -> 0 | AM66: =Z66-Y66 -> 0 | AR66: =IFERROR(VLOOKUP(M66,'BS_DEC 2026'!$D$12:$D$109,1,FALSE()),"(미존재)") -> 부가가치세미수금
A67: BS | B67: 28100821 | C67: 28100821 Deutsche Bank Money Market Deposit Account | D67: ¥°. CURRENT ASSETS | E67: (1) Quick assets | F67: 1. Cash and cash equivalence | G67: 04. CAS - Cash & Cash Equivalents | H67: 1616 | I67: 262 | K67: Cash equivalents - Money Market Mutual funds | L67: 자산 | M67: 현금및현금등가물 | N67: 자산 | O67: 유동자산 | P67: 현금및현금등가물 | Q67: 0 | R67: 0 | S67: 0 | T67: 0 | U67: 0 | V67: 0 | W67: 0 | X67: 0 | Y67: 0 | Z67: 0 | AE67: =R67 -> 0 | AF67: =S67-R67 -> 0 | AG67: =T67-S67 -> 0 | AH67: =U67-T67 -> 0 | AI67: =V67-U67 -> 0 | AJ67: =W67-V67 -> 0 | AK67: =X67-W67 -> 0 | AL67: =Y67-X67 -> 0 | AM67: =Z67-Y67 -> 0 | AR67: =IFERROR(VLOOKUP(M67,'BS_DEC 2026'!$D$12:$D$109,1,FALSE()),"(미존재)") -> 현금및현금등가물
A68: BS | B68: 28100861 | C68: 28100861 KEB HANA Bank SA KRW Main | D68: ¥°. CURRENT ASSETS | E68: (1) Quick assets | F68: 1. Cash and cash equivalence | G68: 04. CAS - Cash & Cash Equivalents | H68: 1616 | I68: 266 | K68: Cash in reporting currency | L68: 자산 | M68: 현금및현금등가물 | N68: 자산 | O68: 유동자산 | P68: 현금및현금등가물 | Q68: 0 | R68: 0 | S68: 0 | T68: 0 | U68: 0 | V68: 0 | W68: 0 | X68: 0 | Y68: 0 | Z68: 0 | AE68: =R68 -> 0 | AF68: =S68-R68 -> 0 | AG68: =T68-S68 -> 0 | AH68: =U68-T68 -> 0 | AI68: =V68-U68 -> 0 | AJ68: =W68-V68 -> 0 | AK68: =X68-W68 -> 0 | AL68: =Y68-X68 -> 0 | AM68: =Z68-Y68 -> 0 | AR68: =IFERROR(VLOOKUP(M68,'BS_DEC 2026'!$D$12:$D$109,1,FALSE()),"(미존재)") -> 현금및현금등가물
A69: BS | B69: 28101193 | C69: 28101193 Bank of Tokyo - Mitsubishi UFJ KRW Main | D69: ¥°. CURRENT ASSETS | E69: (1) Quick assets | F69: 1. Cash and cash equivalence | G69: 04. CAS - Cash & Cash Equivalents | H69: 1616 | I69: 262 | K69: Cash equivalents - Money Market Mutual funds | L69: 자산 | M69: 현금및현금등가물 | N69: 자산 | O69: 유동자산 | P69: 현금및현금등가물 | Q69: 0 | R69: 0 | S69: 0 | T69: 0 | U69: 0 | V69: 0 | W69: 0 | X69: 0 | Y69: 0 | Z69: 0 | AE69: =R69 -> 0 | AF69: =S69-R69 -> 0 | AG69: =T69-S69 -> 0 | AH69: =U69-T69 -> 0 | AI69: =V69-U69 -> 0 | AJ69: =W69-V69 -> 0 | AK69: =X69-W69 -> 0 | AL69: =Y69-X69 -> 0 | AM69: =Z69-Y69 -> 0 | AR69: =IFERROR(VLOOKUP(M69,'BS_DEC 2026'!$D$12:$D$109,1,FALSE()),"(미존재)") -> 현금및현금등가물
A70: BS | B70: 28330000 | C70: 28330000 HSBC - Main Bank Account EUR | D70: ¥°. CURRENT ASSETS | E70: (1) Quick assets | F70: 1. Cash and cash equivalence | G70: 04. CAS - Cash & Cash Equivalents | H70: 1616 | I70: 267 | K70: Cash in foreign currencies | L70: 자산 | M70: 현금및현금등가물 | N70: 자산 | O70: 유동자산 | P70: 현금및현금등가물 | Q70: 135 | R70: 0 | S70: 0 | T70: 0 | U70: 0 | V70: 0 | W70: 84 | X70: 0 | Y70: 0 | Z70: 0 | AE70: =R70 -> 0 | AF70: =S70-R70 -> 0 | AG70: =T70-S70 -> 0 | AH70: =U70-T70 -> 0 | AI70: =V70-U70 -> 0 | AJ70: =W70-V70 -> 84 | AK70: =X70-W70 -> -84 | AL70: =Y70-X70 -> 0 | AM70: =Z70-Y70 -> 0 | AR70: =IFERROR(VLOOKUP(M70,'BS_DEC 2026'!$D$12:$D$109,1,FALSE()),"(미존재)") -> 현금및현금등가물
A71: BS | B71: 28330001 | C71: 28330001 HSBC - Automatic Payment Clearing EUR | D71: ¥°. CURRENT ASSETS | E71: (1) Quick assets | F71: 1. Cash and cash equivalence | G71: 04. CAS - Cash & Cash Equivalents | H71: 1616 | I71: 267 | K71: Cash in foreign currencies | L71: 자산 | M71: 현금및현금등가물 | N71: 자산 | O71: 유동자산 | P71: 현금및현금등가물 | Q71: 0 | R71: 0 | S71: 0 | T71: 0 | U71: 0 | V71: 0 | W71: 0 | X71: 0 | Y71: 0 | Z71: 0 | AE71: =R71 -> 0 | AF71: =S71-R71 -> 0 | AG71: =T71-S71 -> 0 | AH71: =U71-T71 -> 0 | AI71: =V71-U71 -> 0 | AJ71: =W71-V71 -> 0 | AK71: =X71-W71 -> 0 | AL71: =Y71-X71 -> 0 | AM71: =Z71-Y71 -> 0 | AR71: =IFERROR(VLOOKUP(M71,'BS_DEC 2026'!$D$12:$D$109,1,FALSE()),"(미존재)") -> 현금및현금등가물
A72: BS | B72: 28330002 | C72: 28330002 HSBC - Automatic Receipt Clearing EUR | D72: ¥°. CURRENT ASSETS | E72: (1) Quick assets | F72: 1. Cash and cash equivalence | G72: 04. CAS - Cash & Cash Equivalents | H72: 1616 | I72: 267 | K72: Cash in foreign currencies | L72: 자산 | M72: 현금및현금등가물 | N72: 자산 | O72: 유동자산 | P72: 현금및현금등가물 | Q72: 0 | R72: 0 | S72: 0 | T72: 0 | U72: 0 | V72: 0 | W72: 0 | X72: 0 | Y72: 0 | Z72: 0 | AE72: =R72 -> 0 | AF72: =S72-R72 -> 0 | AG72: =T72-S72 -> 0 | AH72: =U72-T72 -> 0 | AI72: =V72-U72 -> 0 | AJ72: =W72-V72 -> 0 | AK72: =X72-W72 -> 0 | AL72: =Y72-X72 -> 0 | AM72: =Z72-Y72 -> 0 | AR72: =IFERROR(VLOOKUP(M72,'BS_DEC 2026'!$D$12:$D$109,1,FALSE()),"(미존재)") -> 현금및현금등가물
A73: BS | B73: 28330010 | C73: 28330010 HSBC - Main Bank Account USD | D73: ¥°. CURRENT ASSETS | E73: (1) Quick assets | F73: 1. Cash and cash equivalence | G73: 04. CAS - Cash & Cash Equivalents | H73: 1616 | I73: 267 | K73: Cash in foreign currencies | L73: 자산 | M73: 현금및현금등가물 | N73: 자산 | O73: 유동자산 | P73: 현금및현금등가물 | Q73: 14 | R73: 0 | S73: 0 | T73: 0 | U73: 0 | V73: 0 | W73: 5430 | X73: 0 | Y73: 0 | Z73: 0 | AE73: =R73 -> 0 | AF73: =S73-R73 -> 0 | AG73: =T73-S73 -> 0 | AH73: =U73-T73 -> 0 | AI73: =V73-U73 -> 0 | AJ73: =W73-V73 -> 5430 | AK73: =X73-W73 -> -5430 | AL73: =Y73-X73 -> 0 | AM73: =Z73-Y73 -> 0 | AR73: =IFERROR(VLOOKUP(M73,'BS_DEC 2026'!$D$12:$D$109,1,FALSE()),"(미존재)") -> 현금및현금등가물
A74: BS | B74: 28330011 | C74: 28330011 HSBC - Automatic Payment Clearing USD | D74: ¥°. CURRENT ASSETS | E74: (1) Quick assets | F74: 1. Cash and cash equivalence | G74: 04. CAS - Cash & Cash Equivalents | H74: 1616 | I74: 267 | K74: Cash in foreign currencies | L74: 자산 | M74: 현금및현금등가물 | N74: 자산 | O74: 유동자산 | P74: 현금및현금등가물 | Q74: 0 | R74: 0 | S74: 0 | T74: 0 | U74: 0 | V74: 0 | W74: 0 | X74: 0 | Y74: 0 | Z74: 0 | AE74: =R74 -> 0 | AF74: =S74-R74 -> 0 | AG74: =T74-S74 -> 0 | AH74: =U74-T74 -> 0 | AI74: =V74-U74 -> 0 | AJ74: =W74-V74 -> 0 | AK74: =X74-W74 -> 0 | AL74: =Y74-X74 -> 0 | AM74: =Z74-Y74 -> 0 | AR74: =IFERROR(VLOOKUP(M74,'BS_DEC 2026'!$D$12:$D$109,1,FALSE()),"(미존재)") -> 현금및현금등가물
A75: BS | B75: 28330990 | C75: 28330990 HSBC - Main Bank GL Code - Local Curr | D75: ¥°. CURRENT ASSETS | E75: (1) Quick assets | F75: 1. Cash and cash equivalence | G75: 04. CAS - Cash & Cash Equivalents | H75: 1616 | I75: 266 | K75: Cash in reporting currency | L75: 자산 | M75: 현금및현금등가물 | N75: 자산 | O75: 유동자산 | P75: 현금및현금등가물 | Q75: 11105202195 | R75: 49471618364 | S75: 42980820239 | T75: 42437933542 | U75: 11228414742 | V75: 24908566662 | W75: 6624241878 | X75: 11103221799 | Y75: 6235120849 | Z75: 8328079411 | AE75: =R75 -> 49471618364 | AF75: =S75-R75 -> -6490798125 | AG75: =T75-S75 -> -542886697 | AH75: =U75-T75 -> -31209518800 | AI75: =V75-U75 -> 13680151920 | AJ75: =W75-V75 -> -18284324784 | AK75: =X75-W75 -> 4478979921 | AL75: =Y75-X75 -> -4868100950 | AM75: =Z75-Y75 -> 2092958562 | AR75: =IFERROR(VLOOKUP(M75,'BS_DEC 2026'!$D$12:$D$109,1,FALSE()),"(미존재)") -> 현금및현금등가물
A76: BS | B76: 29100000 | C76: 29100000 Def.Tax Asset(due<=1 year) - If Net Asset | D76: ¥°. CURRENT ASSETS | E76: (1) Quick assets | F76: 15. Def.Tax Asset(due<=1 year) | G76: 01. NCA - Non Current Assets | H76: 1616 | I76: 19000 | K76: Deferred tax assets | L76: 자산 | M76: 유동성이연법인세자산 | N76: 자산 | O76: 유동자산 | P76: 유동성이연법인세자산 | Q76: 24413452320 | R76: 24413452320 | S76: 24413452320 | T76: 20300794341 | U76: 20519643421 | V76: 20519643421 | W76: 20519643421 | X76: 19485272641 | Y76: 19485272641 | Z76: 19784758242 | AE76: =R76 -> 24413452320 | AF76: =S76-R76 -> 0 | AG76: =T76-S76 -> -4112657979 | AH76: =U76-T76 -> 218849080 | AI76: =V76-U76 -> 0 | AJ76: =W76-V76 -> 0 | AK76: =X76-W76 -> -1034370780 | AL76: =Y76-X76 -> 0 | AM76: =Z76-Y76 -> 299485601 | AN76: (원본오류 REF) | AO76: =AB76-AA76 -> 0 | AP76: =AC76-AB76 -> 0 | AR76: =IFERROR(VLOOKUP(M76,'BS_DEC 2026'!$D$12:$D$109,1,FALSE()),"(미존재)") -> 유동성이연법인세자산
A77: BS | B77: 29150000 | C77: 29150000 Deferred Tax Asset - Gross | D77: ¥°. CURRENT ASSETS | E77: (1) Quick assets | F77: 15. Def.Tax Asset(due<=1 year) | G77: 01. NCA - Non Current Assets | H77: 1616 | I77: 19000 | K77: Deferred tax assets | L77: 자산 | M77: 유동성이연법인세자산 | N77: 자산 | O77: 유동자산 | P77: 유동성이연법인세자산 | Q77: 0 | R77: 0 | S77: 0 | T77: 422237592 | U77: 0 | V77: 0 | W77: 0 | X77: 0 | Y77: 0 | Z77: 0 | AE77: =R77 -> 0 | AF77: =S77-R77 -> 0 | AG77: =T77-S77 -> 422237592 | AH77: =U77-T77 -> -422237592 | AI77: =V77-U77 -> 0 | AJ77: =W77-V77 -> 0 | AK77: =X77-W77 -> 0 | AL77: =Y77-X77 -> 0 | AM77: =Z77-Y77 -> 0 | AN77: (원본오류 REF) | AO77: =AB77-AA77 -> 0 | AP77: =AC77-AB77 -> 0 | AR77: =IFERROR(VLOOKUP(M77,'BS_DEC 2026'!$D$12:$D$109,1,FALSE()),"(미존재)") -> 유동성이연법인세자산
A78: BS | B78: 30000000 | C78: 30000000 Ordinary shares issued and uncalled | D78: STOCKHOLDERS' EQUITY | E78: ¥°. CAPITAL STOCK | F78: 0 | G78: 05. EQU - Equity | H78: 1616 | I78: 30000 | K78: Share capital | L78: 자본 | M78: 보통주자본금 | N78: 자본 | O78: 자본금 | P78: 자본금 | Q78: -4287180000 | R78: -4287180000 | S78: -4287180000 | T78: -4287180000 | U78: -4287180000 | V78: -4287180000 | W78: -4287180000 | X78: -4287180000 | Y78: -4287180000 | Z78: -4287180000 | AE78: =R78 -> -4287180000 | AF78: =S78-R78 -> 0 | AG78: =T78-S78 -> 0 | AH78: =U78-T78 -> 0 | AI78: =V78-U78 -> 0 | AJ78: =W78-V78 -> 0 | AK78: =X78-W78 -> 0 | AL78: =Y78-X78 -> 0 | AM78: =Z78-Y78 -> 0 | AN78: (원본오류 REF) | AO78: =AB78-AA78 -> 0 | AP78: =AC78-AB78 -> 0 | AR78: =IFERROR(VLOOKUP(M78,'BS_DEC 2026'!$D$12:$D$109,1,FALSE()),"(미존재)") -> 보통주자본금
A79: BS | B79: 30000100 | C79: 30000100 Share premium Equity sec | D79: STOCKHOLDERS' EQUITY | E79: ¥±. CAPITAL SURPLUS | F79: (1) Capital reserves | G79: 05. EQU - Equity | H79: 1616 | I79: 30005 | K79: Share premium | L79: 자본 | M79: 주식발행초과금 | N79: 자본 | O79: 자본잉여금 | P79: 자본잉여금 | Q79: -122441812567 | R79: -122441812567 | S79: -122441812567 | T79: -122441812567 | U79: -122441812567 | V79: -122441812567 | W79: -122441812567 | X79: -122441812567 | Y79: -122441812567 | Z79: -122441812567 | AE79: =R79 -> -122441812567 | AF79: =S79-R79 -> 0 | AG79: =T79-S79 -> 0 | AH79: =U79-T79 -> 0 | AI79: =V79-U79 -> 0 | AJ79: =W79-V79 -> 0 | AK79: =X79-W79 -> 0 | AL79: =Y79-X79 -> 0 | AM79: =Z79-Y79 -> 0 | AN79: (원본오류 REF) | AO79: =AB79-AA79 -> 0 | AP79: =AC79-AB79 -> 0 | AR79: =IFERROR(VLOOKUP(M79,'BS_DEC 2026'!$D$12:$D$109,1,FALSE()),"(미존재)") -> 주식발행초과금
A80: BS | B80: 31000001 | C80: 31000001 Capital contribution premium | D80: STOCKHOLDERS' EQUITY | E80: ¥±. CAPITAL SURPLUS | F80: (1) Capital reserves | G80: 05. EQU - Equity | H80: 1616 | I80: 30005 | K80: Share premium | L80: 자본 | M80: 기타자본잉여금 | N80: 자본 | O80: 자본잉여금 | P80: 자본잉여금 | Q80: 21035577720 | R80: 21035577720 | S80: 21035577720 | T80: 21035577720 | U80: 21035577720 | V80: 21035577720 | W80: 21035577720 | X80: 21035577720 | Y80: 21035577720 | Z80: 21035577720 | AE80: =R80 -> 21035577720 | AF80: =S80-R80 -> 0 | AG80: =T80-S80 -> 0 | AH80: =U80-T80 -> 0 | AI80: =V80-U80 -> 0 | AJ80: =W80-V80 -> 0 | AK80: =X80-W80 -> 0 | AL80: =Y80-X80 -> 0 | AM80: =Z80-Y80 -> 0 | AN80: (원본오류 REF) | AO80: =AB80-AA80 -> 0 | AP80: =AC80-AB80 -> 0 | AR80: =IFERROR(VLOOKUP(M80,'BS_DEC 2026'!$D$12:$D$109,1,FALSE()),"(미존재)") -> 기타자본잉여금
A81: BS | B81: 32100000 | C81: 32100000 Revaluation reserve | D81: STOCKHOLDERS' EQUITY | E81: ¥². RETAINED EARNINGS | F81: 1. Legal reserve | G81: 05. EQU - Equity | H81: 1616 | I81: 30010 | K81: Reserves & retained earnings | L81: 자본 | M81: 이익준비금 | N81: 자본 | O81: 이익잉여금 | P81: 이익준비금 | Q81: -1886200000 | R81: -1886200000 | S81: -1886200000 | T81: -2168590000 | U81: -2168590000 | V81: -2168590000 | W81: -2168590000 | X81: -2168590000 | Y81: -2168590000 | Z81: -2168590000 | AE81: =R81 -> -1886200000 | AF81: =S81-R81 -> 0 | AG81: =T81-S81 -> -282390000 | AH81: =U81-T81 -> 0 | AI81: =V81-U81 -> 0 | AJ81: =W81-V81 -> 0 | AK81: =X81-W81 -> 0 | AL81: =Y81-X81 -> 0 | AM81: =Z81-Y81 -> 0 | AN81: (원본오류 REF) | AO81: =AB81-AA81 -> 0 | AP81: =AC81-AB81 -> 0 | AR81: =IFERROR(VLOOKUP(M81,'BS_DEC 2026'!$D$12:$D$109,1,FALSE()),"(미존재)") -> 이익준비금
A82: BS | B82: 32200000 | C82: 32200000 Retained earnings (R/E) | D82: STOCKHOLDERS' EQUITY | E82: ¥². RETAINED EARNINGS | F82: 10.Unappropriated retained earnings | G82: 05. EQU - Equity | H82: 1616 | I82: 30010 | K82: Reserves & retained earnings | L82: 자본 | M82: 이익잉여금 | N82: 자본 | O82: 이익잉여금 | P82: 전기이월이익잉여금 | Q82: -113587447204 | R82: -153446688682 | S82: -153446688682 | T82: -153164298682 | U82: -153164298682 | V82: -153164298682 | W82: -153164298682 | X82: -153164298682 | Y82: -153164298682 | Z82: -153164298682 | AE82: =R82 -> -153446688682 | AF82: =S82-R82 -> 0 | AG82: =T82-S82 -> 282390000 | AH82: =U82-T82 -> 0 | AI82: =V82-U82 -> 0 | AJ82: =W82-V82 -> 0 | AK82: =X82-W82 -> 0 | AL82: =Y82-X82 -> 0 | AM82: =Z82-Y82 -> 0 | AN82: (원본오류 REF) | AO82: =AB82-AA82 -> 0 | AP82: =AC82-AB82 -> 0 | AR82: =IFERROR(VLOOKUP(M82,'BS_DEC 2026'!$D$12:$D$109,1,FALSE()),"(미존재)") -> 이익잉여금
A83: BS | B83: 32200001 | C83: 32200001 Dividends paid to subsidiaries | D83: STOCKHOLDERS' EQUITY | E83: ¥². RETAINED EARNINGS | F83: 10.Unappropriated retained earnings | G83: 05. EQU - Equity | H83: 1616 | I83: 30010 | K83: Reserves & retained earnings | L83: 자본 | M83: 이익잉여금 | N83: 자본 | O83: 이익잉여금 | P83: 전기이월이익잉여금 | Q83: 6453000000 | R83: 6453000000 | S83: 6453000000 | T83: 58453000000 | U83: 58453000000 | V83: 58453000000 | W83: 58453000000 | X83: 58453000000 | Y83: 58453000000 | Z83: 58453000000 | AE83: =R83 -> 6453000000 | AF83: =S83-R83 -> 0 | AG83: =T83-S83 -> 52000000000 | AH83: =U83-T83 -> 0 | AI83: =V83-U83 -> 0 | AJ83: =W83-V83 -> 0 | AK83: =X83-W83 -> 0 | AL83: =Y83-X83 -> 0 | AM83: =Z83-Y83 -> 0 | AN83: (원본오류 REF) | AO83: =AB83-AA83 -> 0 | AP83: =AC83-AB83 -> 0 | AR83: =IFERROR(VLOOKUP(M83,'BS_DEC 2026'!$D$12:$D$109,1,FALSE()),"(미존재)") -> 이익잉여금
A84: BS | B84: 32300000 | C84: 32300000 Surplus from merger operations | D84: STOCKHOLDERS' EQUITY | E84: ¥³. CAPITAL ADJUSTMENTS | F84: 0 | G84: 05. EQU - Equity | H84: 1616 | I84: 30010 | K84: Reserves & retained earnings | L84: 자본 | M84: 이익잉여금 | N84: 자본 | O84: 자본조정 | P84: 이익잉여금 | Q84: -2041430576 | R84: -2041430576 | S84: -2041430576 | T84: -2041430576 | U84: -2041430576 | V84: -2041430576 | W84: -2041430576 | X84: -2041430576 | Y84: -2041430576 | Z84: -2041430576 | AE84: =R84 -> -2041430576 | AF84: =S84-R84 -> 0 | AG84: =T84-S84 -> 0 | AH84: =U84-T84 -> 0 | AI84: =V84-U84 -> 0 | AJ84: =W84-V84 -> 0 | AK84: =X84-W84 -> 0 | AL84: =Y84-X84 -> 0 | AM84: =Z84-Y84 -> 0 | AN84: (원본오류 REF) | AO84: =AB84-AA84 -> 0 | AP84: =AC84-AB84 -> 0 | AR84: =IFERROR(VLOOKUP(M84,'BS_DEC 2026'!$D$12:$D$109,1,FALSE()),"(미존재)") -> 이익잉여금
A85: BS | B85: 32900000 | C85: 32900000 Pensions - Actuarial gain & losses | D85: STOCKHOLDERS' EQUITY | E85: ¥³. CAPITAL ADJUSTMENTS | F85: 0 | G85: 05. EQU - Equity | H85: 1616 | I85: 30525 | K85: Pensions - Actuarial gains and losses - OCI | L85: 자본 | M85: 이익잉여금 | N85: 자본 | O85: 자본조정 | P85: 이익잉여금 | Q85: -2187462000 | R85: -2187462000 | S85: -2187462000 | T85: -2187462000 | U85: -2187462000 | V85: -2187462000 | W85: -2187462000 | X85: -2187462000 | Y85: -2187462000 | Z85: -2187462000 | AE85: =R85 -> -2187462000 | AF85: =S85-R85 -> 0 | AG85: =T85-S85 -> 0 | AH85: =U85-T85 -> 0 | AI85: =V85-U85 -> 0 | AJ85: =W85-V85 -> 0 | AK85: =X85-W85 -> 0 | AL85: =Y85-X85 -> 0 | AM85: =Z85-Y85 -> 0 | AN85: (원본오류 REF) | AO85: =AB85-AA85 -> 0 | AP85: =AC85-AB85 -> 0 | AR85: =IFERROR(VLOOKUP(M85,'BS_DEC 2026'!$D$12:$D$109,1,FALSE()),"(미존재)") -> 이익잉여금
A86: BS | B86: 32910000 | C86: 32910000 Deferred tax on pensions - Actuarial gain & losse | D86: STOCKHOLDERS' EQUITY | E86: ¥³. CAPITAL ADJUSTMENTS | F86: 0 | G86: 05. EQU - Equity | H86: 1616 | I86: 30530 | K86: Tax on pensions - Actuarial gains and losses - OCI | L86: 자본 | M86: 이익잉여금 | N86: 자본 | O86: 자본조정 | P86: 이익잉여금 | Q86: 1258532858 | R86: 1258532858 | S86: 1258532858 | T86: 1258532858 | U86: 1258532858 | V86: 1258532858 | W86: 1258532858 | X86: 1258532858 | Y86: 1258532858 | Z86: 1258532858 | AE86: =R86 -> 1258532858 | AF86: =S86-R86 -> 0 | AG86: =T86-S86 -> 0 | AH86: =U86-T86 -> 0 | AI86: =V86-U86 -> 0 | AJ86: =W86-V86 -> 0 | AK86: =X86-W86 -> 0 | AL86: =Y86-X86 -> 0 | AM86: =Z86-Y86 -> 0 | AN86: (원본오류 REF) | AO86: =AB86-AA86 -> 0 | AP86: =AC86-AB86 -> 0 | AR86: =IFERROR(VLOOKUP(M86,'BS_DEC 2026'!$D$12:$D$109,1,FALSE()),"(미존재)") -> 이익잉여금
A87: BS | B87: 38010000 | C87: 38010000 Provision for Sales Returns -Manual | D87: LIABILITIES | E87: ¥°. CURRENT LIABILITIES | F87: 7. Allow sales return | G87: 07. CUL - Current Liabilities | H87: 1616 | I87: 42230 | K87: Prov - Return | L87: 부채 | M87: 반품충당금유동 | N87: 부채 | O87: 유동부채 | P87: 반품충당금유동 | Q87: -7662339101 | R87: -7811126280 | S87: -7894289713 | T87: -8099635071 | U87: -8129405443 | V87: -7651614265 | W87: -6405690581 | X87: -6019476466 | Y87: -5735385714 | Z87: -6930294786 | AE87: =R87 -> -7811126280 | AF87: =S87-R87 -> -83163433 | AG87: =T87-S87 -> -205345358 | AH87: =U87-T87 -> -29770372 | AI87: =V87-U87 -> 477791178 | AJ87: =W87-V87 -> 1245923684 | AK87: =X87-W87 -> 386214115 | AL87: =Y87-X87 -> 284090752 | AM87: =Z87-Y87 -> -1194909072 | AN87: (원본오류 REF) | AO87: =AB87-AA87 -> 0 | AP87: =AC87-AB87 -> 0 | AR87: =IFERROR(VLOOKUP(M87,'BS_DEC 2026'!$D$12:$D$109,1,FALSE()),"(미존재)") -> 반품충당금유동
A88: BS | B88: 38100001 | C88: 38100001 Provision for settl./damages of litigation >1 year | D88: LIABILITIES | E88: ¥°. CURRENT LIABILITIES | F88: 5. Accrued expenses | G88: 06. NCL - Non Current Liabilities | H88: 1616 | I88: 36200 | K88: Prov-Risk,litigation,penalties&fines-Non current | L88: 부채 | M88: 미지급비용 | N88: 부채 | O88: 유동부채 | P88: 미지급비용 | Q88: 0 | R88: 0 | S88: 0 | T88: 0 | U88: 0 | V88: 0 | W88: 0 | X88: 0 | Y88: 0 | Z88: 0 | AE88: =R88 -> 0 | AF88: =S88-R88 -> 0 | AG88: =T88-S88 -> 0 | AH88: =U88-T88 -> 0 | AI88: =V88-U88 -> 0 | AJ88: =W88-V88 -> 0 | AK88: =X88-W88 -> 0 | AL88: =Y88-X88 -> 0 | AM88: =Z88-Y88 -> 0 | AN88: (원본오류 REF) | AO88: =AB88-AA88 -> 0 | AP88: =AC88-AB88 -> 0 | AR88: =IFERROR(VLOOKUP(M88,'BS_DEC 2026'!$D$12:$D$109,1,FALSE()),"(미존재)") -> 미지급비용
A89: BS | B89: 38160000 | C89: 38160000 Prov.restr.costs - term.benefits ST | D89: LIABILITIES | E89: ¥°. CURRENT LIABILITIES | F89: 5. Accrued expenses | G89: 07. CUL - Current Liabilities | H89: 1616 | I89: 42215 | K89: Prov-Restructuring costs–termination benefits - CL | L89: 부채 | M89: 미지급비용 | N89: 부채 | O89: 유동부채 | P89: 미지급비용 | Q89: -16873571611 | R89: -7843692983 | S89: -7079882252 | T89: -4808530380 | U89: -5262628149 | V89: -5799086075 | W89: -5799086075 | X89: -5056586075 | Y89: -5056586075 | Z89: -4473184387 | AE89: =R89 -> -7843692983 | AF89: =S89-R89 -> 763810731 | AG89: =T89-S89 -> 2271351872 | AH89: =U89-T89 -> -454097769 | AI89: =V89-U89 -> -536457926 | AJ89: =W89-V89 -> 0 | AK89: =X89-W89 -> 742500000 | AL89: =Y89-X89 -> 0 | AM89: =Z89-Y89 -> 583401688 | AN89: (원본오류 REF) | AO89: =AB89-AA89 -> 0 | AP89: =AC89-AB89 -> 0 | AR89: =IFERROR(VLOOKUP(M89,'BS_DEC 2026'!$D$12:$D$109,1,FALSE()),"(미존재)") -> 미지급비용
A90: BS | B90: 38170010 | C90: 38170010 Provision for vacation | D90: LIABILITIES | E90: ¥°. CURRENT LIABILITIES | F90: 5. Accrued expenses | G90: 07. CUL - Current Liabilities | H90: 1616 | I90: 42002 | K90: Employee - Prov paid holiday/premium | L90: 부채 | M90: 미지급비용 | N90: 부채 | O90: 유동부채 | P90: 미지급비용 | Q90: -1200612826 | R90: -130733519 | S90: -261467038 | T90: -392200557 | U90: -503939420 | V90: -623621855 | W90: -748346226 | X90: -877267041 | Y90: -1002590904 | Z90: -1127914767 | AE90: =R90 -> -130733519 | AF90: =S90-R90 -> -130733519 | AG90: =T90-S90 -> -130733519 | AH90: =U90-T90 -> -111738863 | AI90: =V90-U90 -> -119682435 | AJ90: =W90-V90 -> -124724371 | AK90: =X90-W90 -> -128920815 | AL90: =Y90-X90 -> -125323863 | AM90: =Z90-Y90 -> -125323863 | AN90: (원본오류 REF) | AO90: =AB90-AA90 -> 0 | AP90: =AC90-AB90 -> 0 | AR90: =IFERROR(VLOOKUP(M90,'BS_DEC 2026'!$D$12:$D$109,1,FALSE()),"(미존재)") -> 미지급비용
A91: BS | B91: 39070851 | C91: 39070851 LT tranfert titres | D91: LIABILITIES | E91: ¥±. LONG-TERM LIABILITIES | F91: 4. Long-term lease deposits | G91: 06. NCL - Non Current Liabilities | H91: 1616 | I91: 36915 | K91: Payables to conso comp | L91: 부채 | M91: 임대보증금 | N91: 부채 | O91: 비유동부채 | P91: 임대보증금 | Q91: 0 | R91: 0 | S91: 0 | T91: 0 | U91: 0 | V91: 0 | W91: 0 | X91: 0 | Y91: 0 | Z91: 0 | AE91: =R91 -> 0 | AF91: =S91-R91 -> 0 | AG91: =T91-S91 -> 0 | AH91: =U91-T91 -> 0 | AI91: =V91-U91 -> 0 | AJ91: =W91-V91 -> 0 | AK91: =X91-W91 -> 0 | AL91: =Y91-X91 -> 0 | AM91: =Z91-Y91 -> 0 | AN91: (원본오류 REF) | AO91: =AB91-AA91 -> 0 | AP91: =AC91-AB91 -> 0 | AR91: =IFERROR(VLOOKUP(M91,'BS_DEC 2026'!$D$12:$D$109,1,FALSE()),"(미존재)") -> 임대보증금
A92: BS | B92: 39200800 | C92: 39200800 Long Term lease liability | D92: LIABILITIES | E92: ¥°. CURRENT LIABILITIES | F92: 5. Accrued expenses | G92: 06. NCL - Non Current Liabilities | H92: 1616 | I92: 33000 | K92: Long-term lease liability | L92: 부채 | M92: 미지급비용 | N92: 부채 | O92: 유동부채 | P92: 미지급비용 | Q92: 4 | R92: 4 | S92: 4 | T92: 0 | U92: 0 | V92: 0 | W92: 0 | X92: 0 | Y92: 0 | Z92: 0 | AE92: =R92 -> 4 | AF92: =S92-R92 -> 0 | AG92: =T92-S92 -> -4 | AH92: =U92-T92 -> 0 | AI92: =V92-U92 -> 0 | AJ92: =W92-V92 -> 0 | AK92: =X92-W92 -> 0 | AL92: =Y92-X92 -> 0 | AM92: =Z92-Y92 -> 0 | AN92: (원본오류 REF) | AO92: =AB92-AA92 -> 0 | AP92: =AC92-AB92 -> 0 | AR92: =IFERROR(VLOOKUP(M92,'BS_DEC 2026'!$D$12:$D$109,1,FALSE()),"(미존재)") -> 미지급비용
A93: BS | B93: 40000000 | C93: 40000000 Accts.Pay.Trade Short term | D93: LIABILITIES | E93: ¥°. CURRENT LIABILITIES | F93: 1. Trade payables | G93: 07. CUL - Current Liabilities | H93: 1616 | I93: 40000 | K93: Accounts and notes payable | L93: 부채 | M93: 매입채무 | N93: 부채 | O93: 유동부채 | P93: 외상매입금 | Q93: -13530627993 | R93: -16054738733 | S93: -13503626674 | T93: -11382563929 | U93: -18704621529 | V93: -9999667134 | W93: -11186700694 | X93: -16411868331 | Y93: -5472974326 | Z93: -2711048610 | AE93: =R93 -> -16054738733 | AF93: =S93-R93 -> 2551112059 | AG93: =T93-S93 -> 2121062745 | AH93: =U93-T93 -> -7322057600 | AI93: =V93-U93 -> 8704954395 | AJ93: =W93-V93 -> -1187033560 | AK93: =X93-W93 -> -5225167637 | AL93: =Y93-X93 -> 10938894005 | AM93: =Z93-Y93 -> 2761925716 | AN93: (원본오류 REF) | AO93: =AB93-AA93 -> 0 | AP93: =AC93-AB93 -> 0 | AR93: =IFERROR(VLOOKUP(M93,'BS_DEC 2026'!$D$12:$D$109,1,FALSE()),"(미존재)") -> 매입채무
A94: BS | B94: 40000001 | C94: 40000001 AP Trade 3rd ST Reeval. | D94: LIABILITIES | E94: ¥°. CURRENT LIABILITIES | F94: 1. Trade payables | G94: 07. CUL - Current Liabilities | H94: 1616 | I94: 40000 | K94: Accounts and notes payable | L94: 부채 | M94: 매입채무 | N94: 부채 | O94: 유동부채 | P94: 외상매입금 | Q94: 2032298 | R94: 2032298 | S94: 2032298 | T94: 2032298 | U94: 0 | V94: 0 | W94: 0 | X94: 0 | Y94: 0 | Z94: 0 | AE94: =R94 -> 2032298 | AF94: =S94-R94 -> 0 | AG94: =T94-S94 -> 0 | AH94: =U94-T94 -> -2032298 | AI94: =V94-U94 -> 0 | AJ94: =W94-V94 -> 0 | AK94: =X94-W94 -> 0 | AL94: =Y94-X94 -> 0 | AM94: =Z94-Y94 -> 0 | AN94: (원본오류 REF) | AO94: =AB94-AA94 -> 0 | AP94: =AC94-AB94 -> 0 | AR94: =IFERROR(VLOOKUP(M94,'BS_DEC 2026'!$D$12:$D$109,1,FALSE()),"(미존재)") -> 매입채무
A95: BS | B95: 40000003 | C95: 40000003 Exch.Rate adj.Non-Trade Creditors | D95: LIABILITIES | E95: ¥°. CURRENT LIABILITIES | F95: 1. Trade payables | G95: 07. CUL - Current Liabilities | H95: 1616 | I95: 40000 | K95: Accounts and notes payable | L95: 부채 | M95: 미지급금 | N95: 부채 | O95: 유동부채 | P95: 외상매입금 | Q95: 1051034 | R95: 3116783 | S95: 3113162 | T95: -3674992 | U95: 6090852 | V95: -80474126 | W95: 0 | X95: 119277272 | Y95: 20156623 | Z95: 5693788 | AE95: =R95 -> 3116783 | AF95: =S95-R95 -> -3621 | AG95: =T95-S95 -> -6788154 | AH95: =U95-T95 -> 9765844 | AI95: =V95-U95 -> -86564978 | AJ95: =W95-V95 -> 80474126 | AK95: =X95-W95 -> 119277272 | AL95: =Y95-X95 -> -99120649 | AM95: =Z95-Y95 -> -14462835 | AN95: (원본오류 REF) | AO95: =AB95-AA95 -> 0 | AP95: =AC95-AB95 -> 0 | AR95: =IFERROR(VLOOKUP(M95,'BS_DEC 2026'!$D$12:$D$109,1,FALSE()),"(미존재)") -> 미지급금
A96: BS | B96: 40000004 | C96: 40000004 AP Trade ICO ST Reeval. | D96: LIABILITIES | E96: ¥°. CURRENT LIABILITIES | F96: 1. Trade payables | G96: 07. CUL - Current Liabilities | H96: 1616 | I96: 42905 | K96: Current liabilities - Conso comp | L96: 부채 | M96: 미지급금 | N96: 부채 | O96: 유동부채 | P96: 외상매입금 | Q96: 0 | R96: 0 | S96: 0 | T96: 0 | U96: 0 | V96: 0 | W96: 0 | X96: 0 | Y96: 0 | Z96: 8838853 | AE96: =R96 -> 0 | AF96: =S96-R96 -> 0 | AG96: =T96-S96 -> 0 | AH96: =U96-T96 -> 0 | AI96: =V96-U96 -> 0 | AJ96: =W96-V96 -> 0 | AK96: =X96-W96 -> 0 | AL96: =Y96-X96 -> 0 | AM96: =Z96-Y96 -> 8838853 | AN96: (원본오류 REF) | AO96: =AB96-AA96 -> 0 | AP96: =AC96-AB96 -> 0 | AR96: =IFERROR(VLOOKUP(M96,'BS_DEC 2026'!$D$12:$D$109,1,FALSE()),"(미존재)") -> 미지급금
A97: BS | B97: 40000005 | C97: 40000005 Exch.Rate adj.NonTrade Creditors Group | G97: 07. CUL - Current Liabilities | H97: 1616 | I97: 42905 | K97: Current liabilities - Conso comp | L97: 부채 | M97: 미지급금 | N97: 부채 | O97: 유동부채 | P97: 외상매입금 | Q97: -21174 | R97: 745707 | S97: 1281245 | T97: -1780678 | U97: -761470 | V97: 0 | W97: 0 | X97: 0 | Y97: 0 | Z97: 0 | AE97: =R97 -> 745707 | AF97: =S97-R97 -> 535538 | AG97: =T97-S97 -> -3061923 | AH97: =U97-T97 -> 1019208 | AI97: =V97-U97 -> 761470 | AJ97: =W97-V97 -> 0 | AK97: =X97-W97 -> 0 | AL97: =Y97-X97 -> 0 | AM97: =Z97-Y97 -> 0 | AN97: (원본오류 REF) | AO97: =AB97-AA97 -> 0 | AP97: =AC97-AB97 -> 0 | AR97: =IFERROR(VLOOKUP(M97,'BS_DEC 2026'!$D$12:$D$109,1,FALSE()),"(미존재)") -> 미지급금
A98: BS | B98: 40000012 | C98: 40000012 AP Trade other | D98: LIABILITIES | E98: ¥°. CURRENT LIABILITIES | F98: 3. Other account payable | G98: 07. CUL - Current Liabilities | H98: 1616 | I98: 40000 | K98: Accounts and notes payable | L98: 부채 | M98: 미지급금 | N98: 부채 | O98: 유동부채 | P98: 미지급금 | Q98: -12776261877 | R98: -12631555947 | S98: -9672756719 | T98: -10464382484 | U98: -9319990558 | V98: -21302520896 | W98: -15356642892 | X98: -10476178887 | Y98: -14118573583 | Z98: -7686947311 | AE98: =R98 -> -12631555947 | AF98: =S98-R98 -> 2958799228 | AG98: =T98-S98 -> -791625765 | AH98: =U98-T98 -> 1144391926 | AI98: =V98-U98 -> -11982530338 | AJ98: =W98-V98 -> 5945878004 | AK98: =X98-W98 -> 4880464005 | AL98: =Y98-X98 -> -3642394696 | AM98: =Z98-Y98 -> 6431626272 | AN98: (원본오류 REF) | AO98: =AB98-AA98 -> 0 | AP98: =AC98-AB98 -> 0 | AR98: =IFERROR(VLOOKUP(M98,'BS_DEC 2026'!$D$12:$D$109,1,FALSE()),"(미존재)") -> 미지급금
A99: BS | B99: 40000850 | C99: 40000850 AP Accrual OneCASA Clinical Studies -Man | E99: ¥°. CURRENT LIABILITIES | G99: 07. CUL - Current Liabilities | H99: 1616 | I99: 40000 | L99: 부채 | M99: 미지급비용 | R99: 0 | X99: -8588931019 | Y99: -12751438695 | Z99: -13141943761 | AE99: =R99 -> 0 | AF99: =S99-R99 -> 0 | AG99: =T99-S99 -> 0 | AH99: =U99-T99 -> 0 | AI99: =V99-U99 -> 0 | AJ99: =W99-V99 -> 0 | AK99: =X99-W99 -> -8588931019 | AL99: =Y99-X99 -> -4162507676 | AM99: =Z99-Y99 -> -390505066 | AN99: (원본오류 REF) | AO99: =AB99-AA99 -> 0 | AP99: =AC99-AB99 -> 0 | AR99: =IFERROR(VLOOKUP(M99,'BS_DEC 2026'!$D$12:$D$109,1,FALSE()),"(미존재)") -> 미지급비용
A100: BS | B100: 40000851 | C100: 40000851 AP Royalties 3rd Party Accrued Liabilities -Manual | D100: LIABILITIES | E100: ¥°. CURRENT LIABILITIES | F100: 1. Trade payables | G100: N/A | H100: 1616 | I100: 40000 | K100: Accounts and notes payable | L100: 부채 | M100: 미지급비용 | N100: 부채 | O100: 유동부채 | P100: 외상매입금 | Q100: -210450356 | R100: -153864109 | S100: -155707347 | T100: -369320590 | U100: -100585538 | V100: -399266002 | W100: -707398378 | X100: -1011749990 | Y100: -1416291883 | Z100: -1794368419 | AE100: =R100 -> -153864109 | AF100: =S100-R100 -> -1843238 | AG100: =T100-S100 -> -213613243 | AH100: =U100-T100 -> 268735052 | AI100: =V100-U100 -> -298680464 | AJ100: =W100-V100 -> -308132376 | AK100: =X100-W100 -> -304351612 | AL100: =Y100-X100 -> -404541893 | AM100: =Z100-Y100 -> -378076536 | AN100: (원본오류 REF) | AO100: =AB100-AA100 -> 0 | AP100: =AC100-AB100 -> 0 | AR100: =IFERROR(VLOOKUP(M100,'BS_DEC 2026'!$D$12:$D$109,1,FALSE()),"(미존재)") -> 미지급비용
A101: BS | B101: 40000852 | C101: 40000852 A/P Trade (Manual Adjust) | G101: 07. CUL - Current Liabilities | H101: 1616 | I101: 40000 | K101: Accounts and notes payable | L101: 부채 | M101: 매입채무 | N101: 부채 | O101: 유동부채 | P101: 외상매입금 | Q101: 0 | R101: 0 | S101: 0 | T101: 0 | U101: 0 | V101: 0 | W101: 0 | X101: 0 | Y101: 0 | Z101: -8609260 | AE101: =R101 -> 0 | AF101: =S101-R101 -> 0 | AG101: =T101-S101 -> 0 | AH101: =U101-T101 -> 0 | AI101: =V101-U101 -> 0 | AJ101: =W101-V101 -> 0 | AK101: =X101-W101 -> 0 | AL101: =Y101-X101 -> 0 | AM101: =Z101-Y101 -> -8609260 | AN101: (원본오류 REF) | AO101: =AB101-AA101 -> 0 | AP101: =AC101-AB101 -> 0 | AR101: =IFERROR(VLOOKUP(M101,'BS_DEC 2026'!$D$12:$D$109,1,FALSE()),"(미존재)") -> 매입채무
A102: BS | B102: 40100000 | C102: 40100000 AP-K Trade ICO Import Short Term | D102: LIABILITIES | E102: ¥°. CURRENT LIABILITIES | F102: 1. Trade payables | G102: 07. CUL - Current Liabilities | H102: 1616 | I102: 42905 | K102: Current liabilities - Conso comp | L102: 부채 | M102: 매입채무 | N102: 부채 | O102: 유동부채 | P102: 외상매입금 | Q102: 0 | R102: -27872461883 | S102: -9842716629 | T102: -3722543090 | U102: -8830333670 | V102: -39592158887 | W102: -32461766582 | X102: -70187431824 | Y102: -91046530749 | Z102: -87544156013 | AE102: =R102 -> -27872461883 | AF102: =S102-R102 -> 18029745254 | AG102: =T102-S102 -> 6120173539 | AH102: =U102-T102 -> -5107790580 | AI102: =V102-U102 -> -30761825217 | AJ102: =W102-V102 -> 7130392305 | AK102: =X102-W102 -> -37725665242 | AL102: =Y102-X102 -> -20859098925 | AM102: =Z102-Y102 -> 3502374736 | AN102: (원본오류 REF) | AO102: =AB102-AA102 -> 0 | AP102: =AC102-AB102 -> 0 | AR102: =IFERROR(VLOOKUP(M102,'BS_DEC 2026'!$D$12:$D$109,1,FALSE()),"(미존재)") -> 매입채무
A103: BS | B103: 40100856 | C103: 40100856 Exch.Rate adj.Trade Creditors-Group | G103: 07. CUL - Current Liabilities | H103: 1616 | I103: 42905 | K103: Current liabilities - Conso comp | L103: 부채 | M103: 매입채무 | N103: 부채 | O103: 유동부채 | P103: 외상매입금 | Q103: 0 | R103: 0 | S103: 0 | T103: 0 | U103: 0 | V103: 0 | W103: 0 | X103: 0 | Y103: 0 | Z103: 0 | AE103: =R103 -> 0 | AF103: =S103-R103 -> 0 | AG103: =T103-S103 -> 0 | AH103: =U103-T103 -> 0 | AI103: =V103-U103 -> 0 | AJ103: =W103-V103 -> 0 | AK103: =X103-W103 -> 0 | AL103: =Y103-X103 -> 0 | AM103: =Z103-Y103 -> 0 | AN103: (원본오류 REF) | AO103: =AB103-AA103 -> 0 | AP103: =AC103-AB103 -> 0 | AR103: =IFERROR(VLOOKUP(M103,'BS_DEC 2026'!$D$12:$D$109,1,FALSE()),"(미존재)") -> 매입채무
A104: BS | B104: 40500000 | C104: 40500000 GR/IR A/C Inventory | D104: ¥°. CURRENT ASSETS | E104: (2) Inventories | F104: 7. Goods Rcvd/Invoice Rcvd | G104: 07. CUL - Current Liabilities | H104: 1616 | I104: 40000 | K104: Accounts and notes payable | L104: 가계정 | M104: 가계정 | N104: 자산 | O104: 유동자산 | P104: 미착품 | Q104: 20691651164 | R104: 30433840707 | S104: 25505981853 | T104: 24154739684 | U104: 13962872882 | V104: 47491182298 | W104: 53529456912 | X104: 50203880378 | Y104: 18886915434 | Z104: 17852337563 | AE104: =R104 -> 30433840707 | AF104: =S104-R104 -> -4927858854 | AG104: =T104-S104 -> -1351242169 | AH104: =U104-T104 -> -10191866802 | AI104: =V104-U104 -> 33528309416 | AJ104: =W104-V104 -> 6038274614 | AK104: =X104-W104 -> -3325576534 | AL104: =Y104-X104 -> -31316964944 | AM104: =Z104-Y104 -> -1034577871 | AN104: (원본오류 REF) | AO104: =AB104-AA104 -> 0 | AP104: =AC104-AB104 -> 0
A105: BS | B105: 40500001 | C105: 40500001 GR/IR Invoice Clearing Inventory | D105: ¥°. CURRENT ASSETS | E105: (2) Inventories | F105: 7. Goods Rcvd/Invoice Rcvd | G105: 07. CUL - Current Liabilities | H105: 1616 | I105: 40000 | K105: Accounts and notes payable | L105: 자산 | M105: 미착품 | N105: 자산 | O105: 유동자산 | P105: 미착품 | Q105: 20691651164 | R105: 30433840707 | S105: 25505981853 | T105: 24154739684 | U105: 13962872882 | V105: 47491182298 | W105: 53529456912 | X105: 50203880378 | Y105: 18886915434 | Z105: 17852337563 | AE105: =R105 -> 30433840707 | AF105: =S105-R105 -> -4927858854 | AG105: =T105-S105 -> -1351242169 | AH105: =U105-T105 -> -10191866802 | AI105: =V105-U105 -> 33528309416 | AJ105: =W105-V105 -> 6038274614 | AK105: =X105-W105 -> -3325576534 | AL105: =Y105-X105 -> -31316964944 | AM105: =Z105-Y105 -> -1034577871 | AN105: (원본오류 REF) | AO105: =AB105-AA105 -> 0 | AP105: =AC105-AB105 -> 0
A106: BS | B106: 40500002 | C106: 40500002 GR/IR Delivery Clearing Inventory | D106: LIABILITIES | E106: ¥°. CURRENT LIABILITIES | F106: 1. Trade payables | G106: 07. CUL - Current Liabilities | H106: 1616 | I106: 40000 | K106: Accounts and notes payable | L106: 부채 | M106: 매입채무 | N106: 부채 | O106: 유동부채 | P106: 매입채무 | Q106: -1386404 | R106: -5652388 | S106: -1386404 | T106: -39737058 | U106: -92248005 | V106: -398087752 | W106: -340397392 | X106: -458314185 | Y106: -459632895 | Z106: -360236150 | AE106: =R106 -> -5652388 | AF106: =S106-R106 -> 4265984 | AG106: =T106-S106 -> -38350654 | AH106: =U106-T106 -> -52510947 | AI106: =V106-U106 -> -305839747 | AJ106: =W106-V106 -> 57690360 | AK106: =X106-W106 -> -117916793 | AL106: =Y106-X106 -> -1318710 | AM106: =Z106-Y106 -> 99396745 | AN106: (원본오류 REF) | AO106: =AB106-AA106 -> 0 | AP106: =AC106-AB106 -> 0
A107: BS | B107: 40500003 | C107: 40500003 GR/IR Analysis Account Inventory | D107: ¥°. CURRENT ASSETS | E107: (2) Inventories | F107: 7. Goods Rcvd/Invoice Rcvd | G107: 07. CUL - Current Liabilities | H107: 1616 | I107: 40000 | K107: Accounts and notes payable | L107: 가계정 | M107: 가계정 | N107: 자산 | O107: 유동자산 | P107: 미착품 | Q107: -20690264760 | R107: -30428188319 | S107: -25504595449 | T107: -24115002626 | U107: -13870624877 | V107: -47093094546 | W107: -53189059520 | X107: -49745566193 | Y107: -18427282539 | Z107: -17492101413 | AE107: =R107 -> -30428188319 | AF107: =S107-R107 -> 4923592870 | AG107: =T107-S107 -> 1389592823 | AH107: =U107-T107 -> 10244377749 | AI107: =V107-U107 -> -33222469669 | AJ107: =W107-V107 -> -6095964974 | AK107: =X107-W107 -> 3443493327 | AL107: =Y107-X107 -> 31318283654 | AM107: =Z107-Y107 -> 935181126 | AN107: (원본오류 REF) | AO107: =AB107-AA107 -> 0 | AP107: =AC107-AB107 -> 0
A108: BS | B108: 40500004 | C108: 40500004 Plan Delv Csts | D108: ¥°. CURRENT ASSETS | E108: (2) Inventories | F108: 7. Goods Rcvd/Invoice Rcvd | G108: 07. CUL - Current Liabilities | H108: 1616 | I108: 40000 | K108: Accounts and notes payable | L108: 가계정 | M108: 가계정 | N108: 자산 | O108: 유동자산 | P108: 미착품 | Q108: -1149824 | R108: -1149824 | S108: -1149824 | T108: -31085767 | U108: -92248005 | V108: -398087752 | W108: -340397392 | X108: -458314185 | Y108: -459632895 | Z108: -360236150 | AE108: =R108 -> -1149824 | AF108: =S108-R108 -> 0 | AG108: =T108-S108 -> -29935943 | AH108: =U108-T108 -> -61162238 | AI108: =V108-U108 -> -305839747 | AJ108: =W108-V108 -> 57690360 | AK108: =X108-W108 -> -117916793 | AL108: =Y108-X108 -> -1318710 | AM108: =Z108-Y108 -> 99396745 | AN108: (원본오류 REF) | AO108: =AB108-AA108 -> 0 | AP108: =AC108-AB108 -> 0
A109: BS | B109: 40500005 | C109: 40500005 GR/IR A/C Non-Inventory | D109: ¥°. CURRENT ASSETS | E109: (2) Inventories | F109: 7. Goods Rcvd/Invoice Rcvd | G109: 07. CUL - Current Liabilities | H109: 1616 | I109: 40000 | K109: Accounts and notes payable | L109: 가계정 | M109: 가계정 | N109: 자산 | O109: 유동자산 | P109: 미착품 | Q109: -1871052780 | R109: -2793603966 | S109: -2863924326 | T109: -2355759888 | U109: -1771064581 | V109: -1575994011 | W109: -1986781887 | X109: -1704132566 | Y109: -1665064635 | Z109: -1864310651 | AE109: =R109 -> -2793603966 | AF109: =S109-R109 -> -70320360 | AG109: =T109-S109 -> 508164438 | AH109: =U109-T109 -> 584695307 | AI109: =V109-U109 -> 195070570 | AJ109: =W109-V109 -> -410787876 | AK109: =X109-W109 -> 282649321 | AL109: =Y109-X109 -> 39067931 | AM109: =Z109-Y109 -> -199246016 | AN109: (원본오류 REF) | AO109: =AB109-AA109 -> 0 | AP109: =AC109-AB109 -> 0
A110: BS | B110: 40500006 | C110: 40500006 GR/IR Invoice Clearing Non-Inventory | D110: ¥°. CURRENT ASSETS | E110: (2) Inventories | F110: 7. Goods Rcvd/Invoice Rcvd | G110: 07. CUL - Current Liabilities | H110: 1616 | I110: 40000 | K110: Accounts and notes payable | L110: 자산 | M110: 선급금 | N110: 자산 | O110: 유동자산 | P110: 미착품 | Q110: 46265404 | R110: 29171042 | S110: -307368883 | T110: -437897642 | U110: -61444164 | V110: 20045920 | W110: 90481470 | X110: 35242607 | Y110: -84151472 | Z110: -65382929 | AE110: =R110 -> 29171042 | AF110: =S110-R110 -> -336539925 | AG110: =T110-S110 -> -130528759 | AH110: =U110-T110 -> 376453478 | AI110: =V110-U110 -> 81490084 | AJ110: =W110-V110 -> 70435550 | AK110: =X110-W110 -> -55238863 | AL110: =Y110-X110 -> -119394079 | AM110: =Z110-Y110 -> 18768543 | AN110: (원본오류 REF) | AO110: =AB110-AA110 -> 0 | AP110: =AC110-AB110 -> 0 | AR110: =IFERROR(VLOOKUP(M110,'BS_DEC 2026'!$D$12:$D$109,1,FALSE()),"(미존재)") -> 선급금
A111: BS | B111: 40500007 | C111: 40500007 GR/IR Delivery Clearing Non-Inventory | D111: LIABILITIES | E111: ¥°. CURRENT LIABILITIES | F111: 3. Other account payable | G111: 07. CUL - Current Liabilities | H111: 1616 | I111: 40000 | K111: Accounts and notes payable | L111: 부채 | M111: 미지급금 | N111: 부채 | O111: 유동부채 | P111: 미지급금 | Q111: -1917318184 | R111: -2822775008 | S111: -2556555443 | T111: -1917862246 | U111: -1709620417 | V111: -1596039931 | W111: -2077263357 | X111: -1739375173 | Y111: -1580913163 | Z111: -1798927722 | AE111: =R111 -> -2822775008 | AF111: =S111-R111 -> 266219565 | AG111: =T111-S111 -> 638693197 | AH111: =U111-T111 -> 208241829 | AI111: =V111-U111 -> 113580486 | AJ111: =W111-V111 -> -481223426 | AK111: =X111-W111 -> 337888184 | AL111: =Y111-X111 -> 158462010 | AM111: =Z111-Y111 -> -218014559 | AN111: (원본오류 REF) | AO111: =AB111-AA111 -> 0 | AP111: =AC111-AB111 -> 0 | AR111: =IFERROR(VLOOKUP(M111,'BS_DEC 2026'!$D$12:$D$109,1,FALSE()),"(미존재)") -> 미지급금
A112: BS | B112: 40500008 | C112: 40500008 GR/IR Analysis Account Non-Inventory | D112: ¥°. CURRENT ASSETS | E112: (2) Inventories | F112: 7. Goods Rcvd/Invoice Rcvd | G112: 07. CUL - Current Liabilities | H112: 1616 | I112: 40000 | K112: Accounts and notes payable | L112: 가계정 | M112: 가계정 | N112: 자산 | O112: 유동자산 | P112: 미착품 | Q112: 1871052780 | R112: 2793603966 | S112: 2863924326 | T112: 2355759888 | U112: 1771064581 | V112: 1575994011 | W112: 1986781887 | X112: 1704132566 | Y112: 1665064635 | Z112: 1864310651 | AE112: =R112 -> 2793603966 | AF112: =S112-R112 -> 70320360 | AG112: =T112-S112 -> -508164438 | AH112: =U112-T112 -> -584695307 | AI112: =V112-U112 -> -195070570 | AJ112: =W112-V112 -> 410787876 | AK112: =X112-W112 -> -282649321 | AL112: =Y112-X112 -> -39067931 | AM112: =Z112-Y112 -> 199246016 | AN112: (원본오류 REF) | AO112: =AB112-AA112 -> 0 | AP112: =AC112-AB112 -> 0
A113: BS | B113: 40500009 | C113: 40500009 Plan Delv Csts - Freight | D113: ¥°. CURRENT ASSETS | E113: (2) Inventories | F113: 7. Goods Rcvd/Invoice Rcvd | G113: 07. CUL - Current Liabilities | H113: 1616 | I113: 40000 | K113: Accounts and notes payable | L113: 가계정 | M113: 가계정 | N113: 자산 | O113: 유동자산 | P113: 미착품 | Q113: -236580 | R113: -4502564 | S113: -236580 | T113: -8651291 | U113: 0 | V113: 0 | W113: 0 | X113: 0 | Y113: 0 | Z113: 0 | AE113: =R113 -> -4502564 | AF113: =S113-R113 -> 4265984 | AG113: =T113-S113 -> -8414711 | AH113: =U113-T113 -> 8651291 | AI113: =V113-U113 -> 0 | AJ113: =W113-V113 -> 0 | AK113: =X113-W113 -> 0 | AL113: =Y113-X113 -> 0 | AM113: =Z113-Y113 -> 0 | AN113: (원본오류 REF) | AO113: =AB113-AA113 -> 0 | AP113: =AC113-AB113 -> 0 | AR113: =IFERROR(VLOOKUP(M113,'BS_DEC 2026'!$D$12:$D$109,1,FALSE()),"(미존재)") -> (미존재)
A114: BS | B114: 40500017 | C114: 40500017 Goods Received or Invoice Rec -GR/IR -COGS -Manual | D114: ¥°. CURRENT ASSETS | E114: (2) Inventories | F114: 7. Goods Rcvd/Invoice Rcvd | G114: (원본오류 N/A) | H114: 1616 | I114: 40000 | K114: Accounts and notes payable | L114: 자산 | M114: 미착품 | N114: 자산 | O114: 유동자산 | P114: 미착품 | Q114: -20691651164 | R114: -30433840707 | S114: -25505981853 | T114: -24154739684 | U114: -13962872882 | V114: -47491182298 | W114: 0 | X114: -50203880378 | Y114: -16785550434 | Z114: -17908151541 | AE114: =R114 -> -30433840707 | AF114: =S114-R114 -> 4927858854 | AG114: =T114-S114 -> 1351242169 | AH114: =U114-T114 -> 10191866802 | AI114: =V114-U114 -> -33528309416 | AJ114: =W114-V114 -> 47491182298 | AK114: =X114-W114 -> -50203880378 | AL114: =Y114-X114 -> 33418329944 | AM114: =Z114-Y114 -> -1122601107 | AN114: (원본오류 REF) | AO114: =AB114-AA114 -> 0 | AP114: =AC114-AB114 -> 0 | AR114: =IFERROR(VLOOKUP(M114,'BS_DEC 2026'!$D$12:$D$109,1,FALSE()),"(미존재)") -> 미착품
A115: BS | B115: 40500018 | C115: 40500018 Goods Rec or Invoice Rec -GR/IR -COGS ICO -Manual | G115: (원본오류 N/A) | H115: 1616 | I115: 42905 | K115: Current liabilities - Conso comp | L115: 자산 | M115: 미착품 | N115: 자산 | O115: 유동자산 | P115: 미착품 | Q115: 0 | R115: 0 | S115: 0 | T115: 0 | U115: 0 | V115: 0 | W115: 0 | X115: 0 | Y115: 0 | Z115: 0 | AE115: =R115 -> 0 | AF115: =S115-R115 -> 0 | AG115: =T115-S115 -> 0 | AH115: =U115-T115 -> 0 | AI115: =V115-U115 -> 0 | AJ115: =W115-V115 -> 0 | AK115: =X115-W115 -> 0 | AL115: =Y115-X115 -> 0 | AM115: =Z115-Y115 -> 0 | AN115: (원본오류 REF) | AO115: =AB115-AA115 -> 0 | AP115: =AC115-AB115 -> 0 | AR115: =IFERROR(VLOOKUP(M115,'BS_DEC 2026'!$D$12:$D$109,1,FALSE()),"(미존재)") -> 미착품
A116: BS | B116: 42000007 | C116: 42000007 Other partners relationship – Liabilities | D116: LIABILITIES | E116: ¥°. CURRENT LIABILITIES | F116: 1. Trade payables | G116: 07. CUL - Current Liabilities | H116: 1616 | I116: 40000 | K116: Accounts and notes payable | L116: 부채 | M116: 매입채무 | N116: 부채 | O116: 유동부채 | P116: 외상매입금 | Q116: 0 | R116: 0 | S116: 0 | T116: 0 | U116: 0 | V116: -6051696989 | W116: -6051696989 | X116: -6051696989 | Y116: 0 | Z116: 0 | AE116: =R116 -> 0 | AF116: =S116-R116 -> 0 | AG116: =T116-S116 -> 0 | AH116: =U116-T116 -> 0 | AI116: =V116-U116 -> -6051696989 | AJ116: =W116-V116 -> 0 | AK116: =X116-W116 -> 0 | AL116: =Y116-X116 -> 6051696989 | AM116: =Z116-Y116 -> 0 | AN116: (원본오류 REF) | AO116: =AB116-AA116 -> 0 | AP116: =AC116-AB116 -> 0 | AR116: =IFERROR(VLOOKUP(M116,'BS_DEC 2026'!$D$12:$D$109,1,FALSE()),"(미존재)") -> 매입채무
